Workbook

Sheet MAIN
A1: Link | B1: Order Name | C1: Email | D1: Phone | E1: Shipping Name | F1: Address | G1: City | H1: State/Province | I1: Zip/Postal Code | J1: Country | K1: Product Name | L1: Product SKU | M1: Product Price | N1: Delivery Location | O1: Room Number | P1: Delivery Date | Q1: Delivery Time | R1: Non-University Housing Address | S1: Location Type | T1: Delivery Location 2 | U1: Building | V1: Room Number 2 | W1: Address 2 | X1: Delivery Date 2 | Y1: Delivery Time 2 | Z1: Insurance | AA1: Non-University Housing Address 2 | AB1: Location Type 2 | AC1: Ship From Address | AD1: Pickup Address | AE1: Pickup Date | AF1: Pickup Time | AG1: Pickup Location | AH1: Ship To Address | AI1: Notes | AJ1: Student Name | AK1: Customer Name | AL1: Kit delivery status | AM1: Student/Customer Phone number NEW
A2: =HYPERLINK("https://utrucking.myshopify.com/admin/orders?query="&RIGHT(B2,LEN(B2)-1)) -> https://utrucking.myshopify.com/admin/orders?query=13851 | B2: #13851 | C2: a.dalen@wustl.edu | D2: 5402078205 | E2: Dalen Ainsworth | K2: Summer Storage | L2: 1 [Included with Registration] | O2: 3091 | P2: 45877 | Q2: 09:00 AM to 11:00 AM | U2: Eliot A | V2: 3091 | X2: 45877 | Y2: 09:00 AM to 11:00 AM | Z2: Included Insurance | AL2: {=IFERROR(IFS(XLOOKUP(B2, 'Kit Delivery Status'!$U:$U, 'Kit Delivery Status'!$K:$K) = "Complete", "DELIVERED", XLOOKUP(B2, 'Kit Delivery Status'!$U:$U, 'Kit Delivery Status'!$K:$K) = "Issue", "ISSUE"), "")}
A3: =HYPERLINK("https://utrucking.myshopify.com/admin/orders?query="&RIGHT(B3,LEN(B3)-1)) -> https://utrucking.myshopify.com/admin/orders?query=14045 | B3: #14045 | C3: helenmives@gmail.com | D3: 857-218-8168 | E3: Helen Ives | K3: Storage Item Return | N3: University Housing | O3: Apartment 324-B | P3: 45890 | Q3: 09:00 AM - 11:00 AM | U3: Greenway Apartments | V3: Apartment 324-B | X3: 45890 | Y3: 09:00 AM - 11:00 AM | AI3: The address on my boxes is no longer accurate, and the address I have put here (for WashU housing) is the one that should be used for all of my boxes. Many thanks! | AL3: {=IFERROR(IFS(XLOOKUP(B3, 'Kit Delivery Status'!$U:$U, 'Kit Delivery Status'!$K:$K) = "Complete", "DELIVERED", XLOOKUP(B3, 'Kit Delivery Status'!$U:$U, 'Kit Delivery Status'!$K:$K) = "Issue", "ISSUE"), "")}
A4: =HYPERLINK("https://utrucking.myshopify.com/admin/orders?query="&RIGHT(B4,LEN(B4)-1)) -> https://utrucking.myshopify.com/admin/orders?query=14075 | B4: #14075 | C4: cclee@wustl.edu | D4: 9495312000 | E4: Chelsea Lee | K4: Storage Item Return | N4: University Housing | O4: 4052 | P4: 45891 | Q4: 03:00 PM - 05:00 PM | U4: Nemerov | V4: 4052 | X4: 45891 | Y4: 03:00 PM - 05:00 PM | AI4: It would be appreciated if my stuff can be delivered to my room, but if not possible, leaving it in the common room of 4050 is good as well. | AL4: {=IFERROR(IFS(XLOOKUP(B4, 'Kit Delivery Status'!$U:$U, 'Kit Delivery Status'!$K:$K) = "Complete", "DELIVERED", XLOOKUP(B4, 'Kit Delivery Status'!$U:$U, 'Kit Delivery Status'!$K:$K) = "Issue", "ISSUE"), "")}
A5: =HYPERLINK("https://utrucking.myshopify.com/admin/orders?query="&RIGHT(B5,LEN(B5)-1)) -> https://utrucking.myshopify.com/admin/orders?query=14116 | B5: #14116 | C5: benschwed9876@wustl.edu | D5: 5169985553 | E5: Benjamin Schwed | K5: Appliance Rental | L5: Standard Mini Fridge + Microwave | N5: University Housing | O5: 3304 | P5: 45883 | Q5: 09:00 AM - 11:00 AM | U5: Danforth | V5: 3304 | X5: 45883 | Y5: 09:00 AM - 11:00 AM | AI5: delivery-08/13/2025 pick up-05/06/2026 | AL5: {=IFERROR(IFS(XLOOKUP(B5, 'Kit Delivery Status'!$U:$U, 'Kit Delivery Status'!$K:$K) = "Complete", "DELIVERED", XLOOKUP(B5, 'Kit Delivery Status'!$U:$U, 'Kit Delivery Status'!$K:$K) = "Issue", "ISSUE"), "")}
A6: https://admin.shopify.com/store/utrucking/orders/5794999468220?link_source=search | B6: #14171 | C6: Marlowe@wustl.edu | D6: 914-646-4187 | E6: Taylor Marlowe | K6: Tri-State Area Home Pickups | L6: $100 per item [Included] | N6: University Housing | O6: 3331 | P6: 45877 | Q6: 09:00 AM - 11:00 AM | U6: Lien | V6: 3331 | X6: 45877 | Y6: 09:00 AM - 11:00 AM | AL6: {=IFERROR(IFS(XLOOKUP(B6, 'Kit Delivery Status'!$U:$U, 'Kit Delivery Status'!$K:$K) = "Complete", "DELIVERED", XLOOKUP(B6, 'Kit Delivery Status'!$U:$U, 'Kit Delivery Status'!$K:$K) = "Issue", "ISSUE"), "")}
A7: =HYPERLINK("https://utrucking.myshopify.com/admin/orders?query="&RIGHT(B7,LEN(B7)-1)) -> https://utrucking.myshopify.com/admin/orders?query=14191 | B7: #14191 | C7: jessicajlee@wustl.edu | D7: 7087372613 | E7: Jessica Lee | K7: Storage Item Return | N7: University Housing | O7: 4000 | P7: 45876 | Q7: 09:00 AM - 11:00 AM | U7: Nemerov | V7: 4000 | X7: 45876 | Y7: 09:00 AM - 11:00 AM | AL7: {=IFERROR(IFS(XLOOKUP(B7, 'Kit Delivery Status'!$U:$U, 'Kit Delivery Status'!$K:$K) = "Complete", "DELIVERED", XLOOKUP(B7, 'Kit Delivery Status'!$U:$U, 'Kit Delivery Status'!$K:$K) = "Issue", "ISSUE"), "")}
A8: =HYPERLINK("https://utrucking.myshopify.com/admin/orders?query="&RIGHT(B8,LEN(B8)-1)) -> https://utrucking.myshopify.com/admin/orders?query=14194 | B8: #14194 | C8: cindyhellman1204@gmail.com | D8: (516) 508-8030 | E8: cindy hellman | F8: the everly 6105 delmar blvd st louis mo 63112 apt 1321 | K8: Apartment Moves | L8: 1 [Included with Registration] | P8: 45857 | Q8: 10:00 AM - 12:00 PM | X8: 45857 | Y8: 10:00 AM - 12:00 PM | AC8: the everly 6105 delmar blvd st louis mo 63112 apt 1321 | AE8: 45857 | AI8: moving to citizens park 4643 lindell blvd st louis mo 63108 apt 1110 *** CAN YOU PLEASE DROP OFF the BOXES ON MONDAY APRIL 28th *** contact phone 516-508-8030 MARISA BENJAMIN**** | AL8: {=IFERROR(IFS(XLOOKUP(B8, 'Kit Delivery Status'!$U:$U, 'Kit Delivery Status'!$K:$K) = "Complete", "DELIVERED", XLOOKUP(B8, 'Kit Delivery Status'!$U:$U, 'Kit Delivery Status'!$K:$K) = "Issue", "ISSUE"), "")}
A9: =HYPERLINK("https://utrucking.myshopify.com/admin/orders?query="&RIGHT(B9,LEN(B9)-1)) -> https://utrucking.myshopify.com/admin/orders?query=13918 | B9: #13918 | C9: garelick@wustl.edu | D9: (201) 400-7616 | E9: Jared Garelick | F9: 407 Thornden Street | K9: Nationwide Ship to School | P9: 45889 | Q9: 12:00 PM - 02:00 PM | X9: 45889 | Y9: 12:00 PM - 02:00 PM | AE9: 45889 | AL9: {=IFERROR(IFS(XLOOKUP(B9, 'Kit Delivery Status'!$U:$U, 'Kit Delivery Status'!$K:$K) = "Complete", "DELIVERED", XLOOKUP(B9, 'Kit Delivery Status'!$U:$U, 'Kit Delivery Status'!$K:$K) = "Issue", "ISSUE"), "")}
A10: =HYPERLINK("https://utrucking.myshopify.com/admin/orders?query="&RIGHT(B10,LEN(B10)-1)) -> https://utrucking.myshopify.com/admin/orders?query=14224 | B10: #14224 | C10: m.bell@wustl.edu | D10: (312) 344-0050 | E10: Chanel Bell | F10: 705 McCardle Drive | K10: Nationwide Ship to School | N10: University Housing | P10: 45870 | Q10: 09:00 AM - 11:00 AM | U10: DON'T KNOW YET (put 'XXX' for room #) | V10: XXX | X10: 45870 | Y10: 09:00 AM - 11:00 AM | AE10: 45870 | AL10: {=IFERROR(IFS(XLOOKUP(B10, 'Kit Delivery Status'!$U:$U, 'Kit Delivery Status'!$K:$K) = "Complete", "DELIVERED", XLOOKUP(B10, 'Kit Delivery Status'!$U:$U, 'Kit Delivery Status'!$K:$K) = "Issue", "ISSUE"), "")}
A11: =HYPERLINK("https://utrucking.myshopify.com/admin/orders?query="&RIGHT(B11,LEN(B11)-1)) -> https://utrucking.myshopify.com/admin/orders?query=14409 | B11: #14409 | C11: m.b.szwartz@wustl.edu | D11: (1215) 432-7954 | E11: Lynda Szwartz | F11: 605 Zollinger Way | K11: Nationwide Ship to School | N11: University Housing | P11: 45884 | Q11: 09:00 AM to 11:00 AM | U11: Umrath | V11: 3301 | X11: 45884 | Y11: 09:00 AM to 11:00 AM | AE11: 45884 | AL11: {=IFERROR(IFS(XLOOKUP(B11, 'Kit Delivery Status'!$U:$U, 'Kit Delivery Status'!$K:$K) = "Complete", "DELIVERED", XLOOKUP(B11, 'Kit Delivery Status'!$U:$U, 'Kit Delivery Status'!$K:$K) = "Issue", "ISSUE"), "")}
A12: =HYPERLINK("https://utrucking.myshopify.com/admin/orders?query="&RIGHT(B12,LEN(B12)-1)) -> https://utrucking.myshopify.com/admin/orders?query=14473 | B12: #14473 | C12: j.jaffe@wustl.edu | D12: (315) 382-7241 | E12: Jonah Jaffe | F12: 4852 Carey Drive | K12: Nationwide Ship to School | N12: University Housing | P12: 45883 | Q12: 10:00 AM - 12:00 PM | U12: Koenig | V12: 2212 | X12: 45883 | Y12: 10:00 AM - 12:00 PM | AE12: 45883 | AL12: {=IFERROR(IFS(XLOOKUP(B12, 'Kit Delivery Status'!$U:$U, 'Kit Delivery Status'!$K:$K) = "Complete", "DELIVERED", XLOOKUP(B12, 'Kit Delivery Status'!$U:$U, 'Kit Delivery Status'!$K:$K) = "Issue", "ISSUE"), "")}
A13: https://admin.shopify.com/store/utrucking/orders/5811833962684?link_source=search | B13: #14478 | C13: hermione@wustl.edu | D13: 314-745-7657 | E13: Yutong Xie | F13: 6515 Wydown Boulevard | K13: Storage Item Return | N13: Non-University Housing | P13: 45893 | Q13: 02:00 PM - 04:00 PM | R13: 6105 Delmar BIvd. Apt 515 | X13: 45893 | Y13: 02:00 PM - 04:00 PM | AE13: 45893 | AL13: {=IFERROR(IFS(XLOOKUP(B13, 'Kit Delivery Status'!$U:$U, 'Kit Delivery Status'!$K:$K) = "Complete", "DELIVERED", XLOOKUP(B13, 'Kit Delivery Status'!$U:$U, 'Kit Delivery Status'!$K:$K) = "Issue", "ISSUE"), "")}
A14: =HYPERLINK("https://utrucking.myshopify.com/admin/orders?query="&RIGHT(B14,LEN(B14)-1)) -> https://utrucking.myshopify.com/admin/orders?query=14528 | B14: #14528 | C14: qiumin@wustl.edu | D14: (571) 275-5119 | E14: Michelle Zhang | F14: 1200 N Quaker Ln | K14: Nationwide Ship to School | N14: University Housing | P14: 45883 | Q14: 03:00 PM - 05:00 PM | U14: Lee | V14: 313 | X14: 45883 | Y14: 03:00 PM - 05:00 PM | AE14: 45883 | AL14: {=IFERROR(IFS(XLOOKUP(B14, 'Kit Delivery Status'!$U:$U, 'Kit Delivery Status'!$K:$K) = "Complete", "DELIVERED", XLOOKUP(B14, 'Kit Delivery Status'!$U:$U, 'Kit Delivery Status'!$K:$K) = "Issue", "ISSUE"), "")}
A15: =HYPERLINK("https://utrucking.myshopify.com/admin/orders?query="&RIGHT(B15,LEN(B15)-1)) -> https://utrucking.myshopify.com/admin/orders?query=14587 | B15: #14587 | C15: allen.r.g@wustl.edu | D15: (713) 898-3521 | E15: Ryan Allen | F15: 3614 Durness Way | K15: Nationwide Ship to School | N15: University Housing | P15: 45784 | Q15: 02:00 PM - 04:00 PM | U15: Umrath | V15: 2237 | X15: 45784 | Y15: 02:00 PM - 04:00 PM | AE15: 45784 | AL15: {=IFERROR(IFS(XLOOKUP(B15, 'Kit Delivery Status'!$U:$U, 'Kit Delivery Status'!$K:$K) = "Complete", "DELIVERED", XLOOKUP(B15, 'Kit Delivery Status'!$U:$U, 'Kit Delivery Status'!$K:$K) = "Issue", "ISSUE"), "")}
A16: =HYPERLINK("https://utrucking.myshopify.com/admin/orders?query="&RIGHT(B16,LEN(B16)-1)) -> https://utrucking.myshopify.com/admin/orders?query=14755 | B16: #14755 | C16: c.a.warren@wustl.edu | D16: (713) 206-1500 | E16: Morgan Warren | F16: 6711 Stella Link Road | K16: Nationwide Ship to School | N16: University Housing | P16: 45883 | Q16: 9:00 AM - 11:00 AM | U16: Dauten | V16: 432 | X16: 45883 | Y16: 9:00 AM - 11:00 AM | AE16: 45883 | AL16: {=IFERROR(IFS(XLOOKUP(B16, 'Kit Delivery Status'!$U:$U, 'Kit Delivery Status'!$K:$K) = "Complete", "DELIVERED", XLOOKUP(B16, 'Kit Delivery Status'!$U:$U, 'Kit Delivery Status'!$K:$K) = "Issue", "ISSUE"), "")}
A17: =HYPERLINK("https://utrucking.myshopify.com/admin/orders?query="&RIGHT(B17,LEN(B17)-1)) -> https://utrucking.myshopify.com/admin/orders?query=14825 | B17: #14825 | C17: b.welford@wustl.edu | D17: (1949) 500-1022 | E17: Benjamin Welford | F17: 39 Blue Heron | K17: Nationwide Ship to School | N17: University Housing | P17: 45883 | Q17: 09:00 AM - 11:00 AM | U17: Park | V17: 280 | X17: 45883 | Y17: 09:00 AM - 11:00 AM | AE17: 45883 | AL17: {=IFERROR(IFS(XLOOKUP(B17, 'Kit Delivery Status'!$U:$U, 'Kit Delivery Status'!$K:$K) = "Complete", "DELIVERED", XLOOKUP(B17, 'Kit Delivery Status'!$U:$U, 'Kit Delivery Status'!$K:$K) = "Issue", "ISSUE"), "")}
A18: =HYPERLINK("https://utrucking.myshopify.com/admin/orders?query="&RIGHT(B18,LEN(B18)-1)) -> https://utrucking.myshopify.com/admin/orders?query=14979 | B18: #14979 | C18: joyce.zhao@wustl.edu | D18: (840) 205-6469 | E18: Joyce Zhao | F18: 1175 W Baseline Rd | K18: Nationwide Ship to School | N18: University Housing | P18: 45883 | Q18: 11:00 AM - 01:00 PM | U18: Shanedling | V18: 333 | X18: 45883 | Y18: 11:00 AM - 01:00 PM | AE18: 45883 | AL18: {=IFERROR(IFS(XLOOKUP(B18, 'Kit Delivery Status'!$U:$U, 'Kit Delivery Status'!$K:$K) = "Complete", "DELIVERED", XLOOKUP(B18, 'Kit Delivery Status'!$U:$U, 'Kit Delivery Status'!$K:$K) = "Issue", "ISSUE"), "")}
A19: =HYPERLINK("https://utrucking.myshopify.com/admin/orders?query="&RIGHT(B19,LEN(B19)-1)) -> https://utrucking.myshopify.com/admin/orders?query=14984 | B19: #14984 | C19: samanthar@wustl.edu | D19: (312) 351-0710 | E19: Samantha Rosenberg | F19: 256 Moraine Road | K19: Nationwide Ship to School | N19: University Housing | P19: 45883 | Q19: 09:00 AM - 11:00 AM | U19: Danforth | V19: 3321 | X19: 45883 | Y19: 09:00 AM - 11:00 AM | AE19: 45883 | AL19: {=IFERROR(IFS(XLOOKUP(B19, 'Kit Delivery Status'!$U:$U, 'Kit Delivery Status'!$K:$K) = "Complete", "DELIVERED", XLOOKUP(B19, 'Kit Delivery Status'!$U:$U, 'Kit Delivery Status'!$K:$K) = "Issue", "ISSUE"), "")}
A20: =HYPERLINK("https://utrucking.myshopify.com/admin/orders?query="&RIGHT(B20,LEN(B20)-1)) -> https://utrucking.myshopify.com/admin/orders?query=14988 | B20: #14988 | C20: eruth@wustl.edu | D20: (917) 767-3188 | E20: Lexie Ruth | F20: 3212 Gulfstream Road | K20: Nationwide Ship to School | N20: University Housing | P20: 45881 | Q20: 09:00 AM - 11:00 AM | U20: Lien | V20: 1117 | X20: 45881 | Y20: 09:00 AM - 11:00 AM | AE20: 45881 | AL20: {=IFERROR(IFS(XLOOKUP(B20, 'Kit Delivery Status'!$U:$U, 'Kit Delivery Status'!$K:$K) = "Complete", "DELIVERED", XLOOKUP(B20, 'Kit Delivery Status'!$U:$U, 'Kit Delivery Status'!$K:$K) = "Issue", "ISSUE"), "")}
A21: =HYPERLINK("https://utrucking.myshopify.com/admin/orders?query="&RIGHT(B21,LEN(B21)-1)) -> https://utrucking.myshopify.com/admin/orders?query=14989 | B21: #14989 | C21: h.thun@wustl.edu | E21: Jola Thun | F21: 500 El Medio Avenue | K21: Nationwide Ship to School | N21: University Housing | P21: 45805 | Q21: 09:00 AM - 11:00 AM | U21: Mudd | V21: 271 | X21: 45805 | Y21: 09:00 AM - 11:00 AM | AE21: 45805 | AL21: {=IFERROR(IFS(XLOOKUP(B21, 'Kit Delivery Status'!$U:$U, 'Kit Delivery Status'!$K:$K) = "Complete", "DELIVERED", XLOOKUP(B21, 'Kit Delivery Status'!$U:$U, 'Kit Delivery Status'!$K:$K) = "Issue", "ISSUE"), "")}
A22: =HYPERLINK("https://utrucking.myshopify.com/admin/orders?query="&RIGHT(B22,LEN(B22)-1)) -> https://utrucking.myshopify.com/admin/orders?query=14994 | B22: #14994 | C22: b.k.wagner@wustl.edu | D22: (678) 830-6322 | E22: Blair (Student) Wagner | F22: 7242 Sweetwater Valley | K22: Nationwide Ship to School | N22: University Housing | P22: 45870 | Q22: 09:00 AM - 11:00 AM | U22: Dardick | V22: 1109-a | X22: 45870 | Y22: 09:00 AM - 11:00 AM | AE22: 45870 | AL22: {=IFERROR(IFS(XLOOKUP(B22, 'Kit Delivery Status'!$U:$U, 'Kit Delivery Status'!$K:$K) = "Complete", "DELIVERED", XLOOKUP(B22, 'Kit Delivery Status'!$U:$U, 'Kit Delivery Status'!$K:$K) = "Issue", "ISSUE"), "")}
A23: https://admin.shopify.com/store/utrucking/orders/5837335822524?link_source=search | B23: #14996 | C23: a.dalen@wustl.edu | D23: 540-207-8205 | E23: Dalen Ainsworth | F23: 9700 Renfield Ct | K23: Appliance Rental | L23: Double Door mini fridge | M23: 145 | N23: University Housing | O23: 3301 | P23: 45792 | Q23: 09:00 AM - 11:00 AM | U23: Koenig | V23: 3301 | X23: 45792 | Y23: 09:00 AM - 11:00 AM | AL23: {=IFERROR(IFS(XLOOKUP(B23, 'Kit Delivery Status'!$U:$U, 'Kit Delivery Status'!$K:$K) = "Complete", "DELIVERED", XLOOKUP(B23, 'Kit Delivery Status'!$U:$U, 'Kit Delivery Status'!$K:$K) = "Issue", "ISSUE"), "")}
A24: =HYPERLINK("https://utrucking.myshopify.com/admin/orders?query="&RIGHT(B24,LEN(B24)-1)) -> https://utrucking.myshopify.com/admin/orders?query=15020 | B24: #15020 | C24: m.k.tan@wustl.edu | D24: (310) 808-3281 | E24: Marisa Tan | F24: 18 Misty Acres Rd | K24: Nationwide Ship to School | N24: University Housing | P24: 45883 | Q24: 09:00 AM to 11:00 AM | U24: Dardick | V24: 2208 | X24: 45883 | Y24: 09:00 AM to 11:00 AM | AE24: 45883 | AL24: {=IFERROR(IFS(XLOOKUP(B24, 'Kit Delivery Status'!$U:$U, 'Kit Delivery Status'!$K:$K) = "Complete", "DELIVERED", XLOOKUP(B24, 'Kit Delivery Status'!$U:$U, 'Kit Delivery Status'!$K:$K) = "Issue", "ISSUE"), "")}
A25: =HYPERLINK("https://utrucking.myshopify.com/admin/orders?query="&RIGHT(B25,LEN(B25)-1)) -> https://utrucking.myshopify.com/admin/orders?query=15032 | B25: #15032 | C25: j.t.lee@wustl.edu | D25: (415) 770-3664 | E25: Jacob Lee | F25: 630 11th Avenue | K25: Nationwide Ship to School | N25: University Housing | P25: 45883 | Q25: 09:00 AM - 11:00 AM | U25: Koenig | V25: 4407 | X25: 45883 | Y25: 09:00 AM - 11:00 AM | AE25: 45883 | AL25: {=IFERROR(IFS(XLOOKUP(B25, 'Kit Delivery Status'!$U:$U, 'Kit Delivery Status'!$K:$K) = "Complete", "DELIVERED", XLOOKUP(B25, 'Kit Delivery Status'!$U:$U, 'Kit Delivery Status'!$K:$K) = "Issue", "ISSUE"), "")}
A26: =HYPERLINK("https://utrucking.myshopify.com/admin/orders?query="&RIGHT(B26,LEN(B26)-1)) -> https://utrucking.myshopify.com/admin/orders?query=15036 | B26: #15036 | C26: a.covello@wustl.edu | D26: (973) 440-7049 | E26: Andrew Covello | F26: 7 Loantaka Lane N | K26: Nationwide Ship to School | N26: University Housing | P26: 45881 | Q26: 09:00 AM - 11:00 AM | U26: DON'T KNOW YET (put 'XXX' for room #) | V26: XXX | X26: 45881 | Y26: 09:00 AM - 11:00 AM | AE26: 45881 | AL26: {=IFERROR(IFS(XLOOKUP(B26, 'Kit Delivery Status'!$U:$U, 'Kit Delivery Status'!$K:$K) = "Complete", "DELIVERED", XLOOKUP(B26, 'Kit Delivery Status'!$U:$U, 'Kit Delivery Status'!$K:$K) = "Issue", "ISSUE"), "")}
A27: =HYPERLINK("https://utrucking.myshopify.com/admin/orders?query="&RIGHT(B27,LEN(B27)-1)) -> https://utrucking.myshopify.com/admin/orders?query=15039 | B27: #15039 | C27: a.plaxe@wustl.edu | D27: (917) 455-1134 | E27: Amanda Plaxe | F27: 214 West 85th St | K27: Nationwide Ship to School | N27: University Housing | P27: 45889 | Q27: 09:00 AM - 11:00 AM | U27: Eliot B | V27: 2103 | X27: 45889 | Y27: 09:00 AM - 11:00 AM | AE27: 45889 | AL27: {=IFERROR(IFS(XLOOKUP(B27, 'Kit Delivery Status'!$U:$U, 'Kit Delivery Status'!$K:$K) = "Complete", "DELIVERED", XLOOKUP(B27, 'Kit Delivery Status'!$U:$U, 'Kit Delivery Status'!$K:$K) = "Issue", "ISSUE"), "")}
A28: =HYPERLINK("https://utrucking.myshopify.com/admin/orders?query="&RIGHT(B28,LEN(B28)-1)) -> https://utrucking.myshopify.com/admin/orders?query=15055 | B28: #15055 | C28: anna.j.schwartz@wustl.edu | D28: (404) 345-7378 | E28: Anna Schwartz | F28: 4416 Saint Andrews Drive Northwest | K28: Nationwide Ship to School | N28: University Housing | P28: 45878 | Q28: 09:00 AM to 11:00 AM | U28: Village House | V28: 4071-a | X28: 45878 | Y28: 09:00 AM to 11:00 AM | AE28: 45878 | AL28: {=IFERROR(IFS(XLOOKUP(B28, 'Kit Delivery Status'!$U:$U, 'Kit Delivery Status'!$K:$K) = "Complete", "DELIVERED", XLOOKUP(B28, 'Kit Delivery Status'!$U:$U, 'Kit Delivery Status'!$K:$K) = "Issue", "ISSUE"), "")}
A29: =HYPERLINK("https://utrucking.myshopify.com/admin/orders?query="&RIGHT(B29,LEN(B29)-1)) -> https://utrucking.myshopify.com/admin/orders?query=15080 | B29: #15080 | C29: megcheung2016@gmail.com | D29: (914) 255-7538 | E29: Sohta Cheung-Naito | F29: 175 Underhill Rd | K29: Nationwide Ship to School | N29: University Housing | P29: 45883 | Q29: 10:00 AM - 12:00 PM | U29: Koenig | V29: 1117 | X29: 45883 | Y29: 10:00 AM - 12:00 PM | AE29: 45883 | AL29: {=IFERROR(IFS(XLOOKUP(B29, 'Kit Delivery Status'!$U:$U, 'Kit Delivery Status'!$K:$K) = "Complete", "DELIVERED", XLOOKUP(B29, 'Kit Delivery Status'!$U:$U, 'Kit Delivery Status'!$K:$K) = "Issue", "ISSUE"), "")}
A30: =HYPERLINK("https://utrucking.myshopify.com/admin/orders?query="&RIGHT(B30,LEN(B30)-1)) -> https://utrucking.myshopify.com/admin/orders?query=15081 | B30: #15081 | C30: 0 | D30: (1214) 336-9342 | E30: julie liberman | F30: 2404 WING POINT LN | K30: Nationwide Ship to School | N30: University Housing | P30: 45883 | Q30: 09:00 AM - 11:00 AM | U30: Umrath | V30: 3322 | X30: 45883 | Y30: 09:00 AM - 11:00 AM | AE30: 45883 | AL30: {=IFERROR(IFS(XLOOKUP(B30, 'Kit Delivery Status'!$U:$U, 'Kit Delivery Status'!$K:$K) = "Complete", "DELIVERED", XLOOKUP(B30, 'Kit Delivery Status'!$U:$U, 'Kit Delivery Status'!$K:$K) = "Issue", "ISSUE"), "")}
A31: =HYPERLINK("https://utrucking.myshopify.com/admin/orders?query="&RIGHT(B31,LEN(B31)-1)) -> https://utrucking.myshopify.com/admin/orders?query=15082 | B31: #15082 | C31: edwardcartonz@gmail.com | D31: (805) 637-5739 | E31: Maohua Zhang | F31: 775 Camino Del Sur | K31: Nationwide Ship to School | N31: Non-University Housing | P31: 45822 | Q31: 01:00 PM - 03:00 PM | X31: 45822 | Y31: 01:00 PM - 03:00 PM | AE31: 45822 | AL31: {=IFERROR(IFS(XLOOKUP(B31, 'Kit Delivery Status'!$U:$U, 'Kit Delivery Status'!$K:$K) = "Complete", "DELIVERED", XLOOKUP(B31, 'Kit Delivery Status'!$U:$U, 'Kit Delivery Status'!$K:$K) = "Issue", "ISSUE"), "")}
A32: =HYPERLINK("https://utrucking.myshopify.com/admin/orders?query="&RIGHT(B32,LEN(B32)-1)) -> https://utrucking.myshopify.com/admin/orders?query=15103 | B32: #15103 | C32: faier@wustl.edu | D32: (224) 578-2645 | E32: Sharon Faier | F32: 8182 South Saint Paul Way | K32: Nationwide Ship to School | N32: University Housing | P32: 45883 | Q32: 09:00 AM - 11:00 AM | U32: Myers | V32: 413 | X32: 45883 | Y32: 09:00 AM - 11:00 AM | AE32: 45883 | AL32: {=IFERROR(IFS(XLOOKUP(B32, 'Kit Delivery Status'!$U:$U, 'Kit Delivery Status'!$K:$K) = "Complete", "DELIVERED", XLOOKUP(B32, 'Kit Delivery Status'!$U:$U, 'Kit Delivery Status'!$K:$K) = "Issue", "ISSUE"), "")}
A33: =HYPERLINK("https://utrucking.myshopify.com/admin/orders?query="&RIGHT(B33,LEN(B33)-1)) -> https://utrucking.myshopify.com/admin/orders?query=15104 | B33: #15104 | C33: l.d.young@wustl.edu | D33: (949) 254-8160 | E33: Sandra Young | F33: 72 Cunningham | K33: Nationwide Ship to School | N33: University Housing | P33: 45883 | Q33: 09:00 AM - 11:00 AM | U33: Koenig | V33: I don't know yet | X33: 45883 | Y33: 09:00 AM - 11:00 AM | AE33: 45883 | AL33: {=IFERROR(IFS(XLOOKUP(B33, 'Kit Delivery Status'!$U:$U, 'Kit Delivery Status'!$K:$K) = "Complete", "DELIVERED", XLOOKUP(B33, 'Kit Delivery Status'!$U:$U, 'Kit Delivery Status'!$K:$K) = "Issue", "ISSUE"), "")}
A34: =HYPERLINK("https://utrucking.myshopify.com/admin/orders?query="&RIGHT(B34,LEN(B34)-1)) -> https://utrucking.myshopify.com/admin/orders?query=15128 | B34: #15128 | C34: bosques@wustl.edu | D34: (617) 999-8561 | E34: Gustavo Bosques | F34: 198 Overlook Rd | K34: Nationwide Ship to School | N34: University Housing | P34: 45882 | Q34: 03:00 PM - 05:00 PM | U34: DON'T KNOW YET (put 'XXX' for room #) | V34: xxx | X34: 45882 | Y34: 03:00 PM - 05:00 PM | AE34: 45882 | AL34: {=IFERROR(IFS(XLOOKUP(B34, 'Kit Delivery Status'!$U:$U, 'Kit Delivery Status'!$K:$K) = "Complete", "DELIVERED", XLOOKUP(B34, 'Kit Delivery Status'!$U:$U, 'Kit Delivery Status'!$K:$K) = "Issue", "ISSUE"), "")}
A35: =HYPERLINK("https://utrucking.myshopify.com/admin/orders?query="&RIGHT(B35,LEN(B35)-1)) -> https://utrucking.myshopify.com/admin/orders?query=15129 | B35: #15129 | C35: dina.bean@verizon.net | D35: (1917) 821-5981 | E35: Dina Bean | F35: 8 East 83rd Street | K35: Nationwide Ship to School | N35: University Housing | P35: 45882 | Q35: 10:00 AM - 12:00 PM | U35: Dardick | V35: 2210 | X35: 45882 | Y35: 10:00 AM - 12:00 PM | AE35: 45882 | AL35: {=IFERROR(IFS(XLOOKUP(B35, 'Kit Delivery Status'!$U:$U, 'Kit Delivery Status'!$K:$K) = "Complete", "DELIVERED", XLOOKUP(B35, 'Kit Delivery Status'!$U:$U, 'Kit Delivery Status'!$K:$K) = "Issue", "ISSUE"), "")}
A36: =HYPERLINK("https://utrucking.myshopify.com/admin/orders?query="&RIGHT(B36,LEN(B36)-1)) -> https://utrucking.myshopify.com/admin/orders?query=15134 | B36: #15134 | C36: r.l.shames@wustl.edu | D36: (1917) 603-4125 | E36: Rachel Shames | F36: 500 W End Ave | K36: Nationwide Ship to School | N36: University Housing | P36: 45882 | Q36: 11:00 AM - 01:00 PM | U36: Dardick | V36: 4402 | X36: 45882 | Y36: 11:00 AM - 01:00 PM | AE36: 45882 | AL36: {=IFERROR(IFS(XLOOKUP(B36, 'Kit Delivery Status'!$U:$U, 'Kit Delivery Status'!$K:$K) = "Complete", "DELIVERED", XLOOKUP(B36, 'Kit Delivery Status'!$U:$U, 'Kit Delivery Status'!$K:$K) = "Issue", "ISSUE"), "")}
A37: =HYPERLINK("https://utrucking.myshopify.com/admin/orders?query="&RIGHT(B37,LEN(B37)-1)) -> https://utrucking.myshopify.com/admin/orders?query=15137 | B37: #15137 | C37: b.cayden@wustl.edu | D37: (973) 715-4139 | E37: Sondra Barrison | F37: 115 Scott Drive | K37: Nationwide Ship to School | N37: University Housing | P37: 45889 | Q37: 12:00 PM - 02:00 PM | U37: 6645 University Drive | V37: 1E-A | X37: 45889 | Y37: 12:00 PM - 02:00 PM | AE37: 45889 | AL37: {=IFERROR(IFS(XLOOKUP(B37, 'Kit Delivery Status'!$U:$U, 'Kit Delivery Status'!$K:$K) = "Complete", "DELIVERED", XLOOKUP(B37, 'Kit Delivery Status'!$U:$U, 'Kit Delivery Status'!$K:$K) = "Issue", "ISSUE"), "")}
A38: =HYPERLINK("https://utrucking.myshopify.com/admin/orders?query="&RIGHT(B38,LEN(B38)-1)) -> https://utrucking.myshopify.com/admin/orders?query=15144 | B38: #15144 | C38: Maryraue@gmail.com | D38: (1703) 307-8619 | E38: Mary Raue | F38: 5810 Beech Ave | K38: Nationwide Ship to School | N38: University Housing | P38: 45881 | Q38: 09:00 AM - 11:00 AM | U38: DON'T KNOW YET (put 'XXX' for room #) | V38: XXX | X38: 45881 | Y38: 09:00 AM - 11:00 AM | AE38: 45881 | AL38: {=IFERROR(IFS(XLOOKUP(B38, 'Kit Delivery Status'!$U:$U, 'Kit Delivery Status'!$K:$K) = "Complete", "DELIVERED", XLOOKUP(B38, 'Kit Delivery Status'!$U:$U, 'Kit Delivery Status'!$K:$K) = "Issue", "ISSUE"), "")}
A39: =HYPERLINK("https://utrucking.myshopify.com/admin/orders?query="&RIGHT(B39,LEN(B39)-1)) -> https://utrucking.myshopify.com/admin/orders?query=15148 | B39: #15148 | C39: 0 | D39: (1202) 494-5966 | E39: Hillary Davidson | F39: 9513 Brooke Dr | K39: Nationwide Ship to School | N39: University Housing | O39: 3323 | P39: 45882 | Q39: 11:00 AM - 01:00 PM | U39: Umrath | V39: 3323 | X39: 45882 | Y39: 11:00 AM - 01:00 PM | AE39: 45882 | AL39: {=IFERROR(IFS(XLOOKUP(B39, 'Kit Delivery Status'!$U:$U, 'Kit Delivery Status'!$K:$K) = "Complete", "DELIVERED", XLOOKUP(B39, 'Kit Delivery Status'!$U:$U, 'Kit Delivery Status'!$K:$K) = "Issue", "ISSUE"), "")}
A40: =HYPERLINK("https://utrucking.myshopify.com/admin/orders?query="&RIGHT(B40,LEN(B40)-1)) -> https://utrucking.myshopify.com/admin/orders?query=15150 | B40: #15150 | C40: taliawest7@gmail.com | D40: (458) 256-5639 | E40: Talia West | F40: 4020 94th Ave NE | K40: Nationwide Ship to School | N40: University Housing | P40: 45880 | Q40: 09:00 AM - 11:00 AM | U40: Danforth | V40: 4428 | X40: 45880 | Y40: 09:00 AM - 11:00 AM | AE40: 45880 | AL40: {=IFERROR(IFS(XLOOKUP(B40, 'Kit Delivery Status'!$U:$U, 'Kit Delivery Status'!$K:$K) = "Complete", "DELIVERED", XLOOKUP(B40, 'Kit Delivery Status'!$U:$U, 'Kit Delivery Status'!$K:$K) = "Issue", "ISSUE"), "")}
A41: =HYPERLINK("https://utrucking.myshopify.com/admin/orders?query="&RIGHT(B41,LEN(B41)-1)) -> https://utrucking.myshopify.com/admin/orders?query=15151 | B41: #15151 | C41: biancah@wustl.edu | D41: (310) 963-6636 | E41: Bianca Hayutin | F41: 2212 Ashland Avenue | K41: Nationwide Ship to School | N41: University Housing | P41: 45882 | Q41: 09:00 AM - 11:00 AM | U41: Rutledge | V41: 432-B | X41: 45882 | Y41: 09:00 AM - 11:00 AM | AE41: 45882 | AL41: {=IFERROR(IFS(XLOOKUP(B41, 'Kit Delivery Status'!$U:$U, 'Kit Delivery Status'!$K:$K) = "Complete", "DELIVERED", XLOOKUP(B41, 'Kit Delivery Status'!$U:$U, 'Kit Delivery Status'!$K:$K) = "Issue", "ISSUE"), "")}
A42: =HYPERLINK("https://utrucking.myshopify.com/admin/orders?query="&RIGHT(B42,LEN(B42)-1)) -> https://utrucking.myshopify.com/admin/orders?query=15158 | B42: #15158 | C42: jadon.s@wustl.edu | D42: (1917) 612-7037 | E42: Jadon Schwartz | F42: 10 Pecan Valley Drive | K42: Nationwide Ship to School | N42: University Housing | P42: 45882 | Q42: 01:00 PM - 03:00 PM | U42: DON'T KNOW YET (put 'XXX' for room #) | V42: XXX | X42: 45882 | Y42: 01:00 PM - 03:00 PM | AE42: 45882 | AL42: {=IFERROR(IFS(XLOOKUP(B42, 'Kit Delivery Status'!$U:$U, 'Kit Delivery Status'!$K:$K) = "Complete", "DELIVERED", XLOOKUP(B42, 'Kit Delivery Status'!$U:$U, 'Kit Delivery Status'!$K:$K) = "Issue", "ISSUE"), "")}
A43: =HYPERLINK("https://utrucking.myshopify.com/admin/orders?query="&RIGHT(B43,LEN(B43)-1)) -> https://utrucking.myshopify.com/admin/orders?query=15163 | B43: #15163 | C43: rebeccaburack@gmail.com | D43: (617) 899-6835 | E43: Ethan Burack | F43: 76 Bellevue Street | K43: Nationwide Ship to School | N43: University Housing | P43: 45882 | Q43: 11:00 AM - 01:00 PM | U43: Dardick | V43: 4408 | X43: 45882 | Y43: 11:00 AM - 01:00 PM | AE43: 45882 | AL43: {=IFERROR(IFS(XLOOKUP(B43, 'Kit Delivery Status'!$U:$U, 'Kit Delivery Status'!$K:$K) = "Complete", "DELIVERED", XLOOKUP(B43, 'Kit Delivery Status'!$U:$U, 'Kit Delivery Status'!$K:$K) = "Issue", "ISSUE"), "")}
A44: =HYPERLINK("https://utrucking.myshopify.com/admin/orders?query="&RIGHT(B44,LEN(B44)-1)) -> https://utrucking.myshopify.com/admin/orders?query=15167 | B44: #15167 | C44: shahlasi@yahoo.com | D44: (781) 742-4837 | E44: Altan Marvi | F44: 200 Stoney Lea Rd | K44: Nationwide Ship to School | N44: University Housing | P44: 45883 | Q44: 10:00 AM - 12:00 PM | U44: Park | V44: 440 | X44: 45883 | Y44: 10:00 AM - 12:00 PM | AE44: 45883 | AL44: {=IFERROR(IFS(XLOOKUP(B44, 'Kit Delivery Status'!$U:$U, 'Kit Delivery Status'!$K:$K) = "Complete", "DELIVERED", XLOOKUP(B44, 'Kit Delivery Status'!$U:$U, 'Kit Delivery Status'!$K:$K) = "Issue", "ISSUE"), "")}
A45: =HYPERLINK("https://utrucking.myshopify.com/admin/orders?query="&RIGHT(B45,LEN(B45)-1)) -> https://utrucking.myshopify.com/admin/orders?query=15168 | B45: #15168 | C45: lily.comander@gmail.com | D45: (1617) 454-7962 | E45: Lily Comander | F45: 11 Hollywood Dr | K45: Nationwide Ship to School | N45: University Housing | P45: 45883 | Q45: 09:00 AM to 11:00 AM | U45: Dardick | V45: 3305 | X45: 45883 | Y45: 09:00 AM to 11:00 AM | AE45: 45883 | AL45: {=IFERROR(IFS(XLOOKUP(B45, 'Kit Delivery Status'!$U:$U, 'Kit Delivery Status'!$K:$K) = "Complete", "DELIVERED", XLOOKUP(B45, 'Kit Delivery Status'!$U:$U, 'Kit Delivery Status'!$K:$K) = "Issue", "ISSUE"), "")}
A46: =HYPERLINK("https://utrucking.myshopify.com/admin/orders?query="&RIGHT(B46,LEN(B46)-1)) -> https://utrucking.myshopify.com/admin/orders?query=15169 | B46: #15169 | C46: chung.j.d@wustl.edu | D46: (1781) 777-3568 | E46: Joshua chung | F46: 10 Burroughs Rd. | K46: Nationwide Ship to School | N46: University Housing | P46: 45882 | Q46: 11:00 AM to 01:00 PM | U46: Dardick | V46: 3319-b | X46: 45882 | Y46: 11:00 AM to 01:00 PM | AE46: 45882 | AL46: {=IFERROR(IFS(XLOOKUP(B46, 'Kit Delivery Status'!$U:$U, 'Kit Delivery Status'!$K:$K) = "Complete", "DELIVERED", XLOOKUP(B46, 'Kit Delivery Status'!$U:$U, 'Kit Delivery Status'!$K:$K) = "Issue", "ISSUE"), "")}
A47: =HYPERLINK("https://utrucking.myshopify.com/admin/orders?query="&RIGHT(B47,LEN(B47)-1)) -> https://utrucking.myshopify.com/admin/orders?query=15170 | B47: #15170 | C47: awmogul@gmail.com | D47: (415) 794-6556 | E47: Alexis Mogul | F47: 1719 Park Avenue | K47: Nationwide Ship to School | N47: University Housing | P47: 45882 | Q47: 09:00 AM - 11:00 AM | U47: Eliot A | V47: 3072A | X47: 45882 | Y47: 09:00 AM - 11:00 AM | AE47: 45882 | AL47: {=IFERROR(IFS(XLOOKUP(B47, 'Kit Delivery Status'!$U:$U, 'Kit Delivery Status'!$K:$K) = "Complete", "DELIVERED", XLOOKUP(B47, 'Kit Delivery Status'!$U:$U, 'Kit Delivery Status'!$K:$K) = "Issue", "ISSUE"), "")}
A48: =HYPERLINK("https://utrucking.myshopify.com/admin/orders?query="&RIGHT(B48,LEN(B48)-1)) -> https://utrucking.myshopify.com/admin/orders?query=15173 | B48: #15173 | C48: auster@wustl.edu | D48: (954) 702-9230 | E48: Samuel Auster | F48: 6820 Yellowstone Lane | K48: Nationwide Ship to School | N48: University Housing | P48: 45882 | Q48: 12:00 PM - 02:00 PM | U48: DON'T KNOW YET (put 'XXX' for room #) | V48: xxx | X48: 45882 | Y48: 12:00 PM - 02:00 PM | AE48: 45882 | AL48: {=IFERROR(IFS(XLOOKUP(B48, 'Kit Delivery Status'!$U:$U, 'Kit Delivery Status'!$K:$K) = "Complete", "DELIVERED", XLOOKUP(B48, 'Kit Delivery Status'!$U:$U, 'Kit Delivery Status'!$K:$K) = "Issue", "ISSUE"), "")}
A49: =HYPERLINK("https://utrucking.myshopify.com/admin/orders?query="&RIGHT(B49,LEN(B49)-1)) -> https://utrucking.myshopify.com/admin/orders?query=15179 | B49: #15179 | C49: dianagaffin@gmail.com | D49: (617) 285-5518 | E49: Eli Gaffin | F49: 51 Aldridge Rd | K49: Nationwide Ship to School | N49: University Housing | P49: 45882 | Q49: 12:00 PM - 02:00 PM | U49: Dardick | V49: 1105-b | X49: 45882 | Y49: 12:00 PM - 02:00 PM | AE49: 45882 | AL49: {=IFERROR(IFS(XLOOKUP(B49, 'Kit Delivery Status'!$U:$U, 'Kit Delivery Status'!$K:$K) = "Complete", "DELIVERED", XLOOKUP(B49, 'Kit Delivery Status'!$U:$U, 'Kit Delivery Status'!$K:$K) = "Issue", "ISSUE"), "")}
A50: =HYPERLINK("https://utrucking.myshopify.com/admin/orders?query="&RIGHT(B50,LEN(B50)-1)) -> https://utrucking.myshopify.com/admin/orders?query=15180 | B50: #15180 | C50: j.b.tajkef@wustl.edu | D50: (1818) 314-0867 | E50: Jack Tajkef | F50: 4434 Woodley Ave | K50: Nationwide Ship to School | N50: University Housing | P50: 45882 | Q50: 12:00 PM - 02:00 PM | U50: Dardick | V50: 2222 | X50: 45882 | Y50: 12:00 PM - 02:00 PM | AE50: 45882 | AL50: {=IFERROR(IFS(XLOOKUP(B50, 'Kit Delivery Status'!$U:$U, 'Kit Delivery Status'!$K:$K) = "Complete", "DELIVERED", XLOOKUP(B50, 'Kit Delivery Status'!$U:$U, 'Kit Delivery Status'!$K:$K) = "Issue", "ISSUE"), "")}
A51: =HYPERLINK("https://utrucking.myshopify.com/admin/orders?query="&RIGHT(B51,LEN(B51)-1)) -> https://utrucking.myshopify.com/admin/orders?query=15183 | B51: #15183 | C51: catherinegluckstein@gmail.com | D51: (206) 335-4627 | E51: Catherine Edwards | F51: 3221 E Morley Way | K51: Nationwide Ship to School | N51: University Housing | P51: 45869 | Q51: 10:00 AM - 12:00 PM | U51: Dauten | V51: 234A | X51: 45869 | Y51: 10:00 AM - 12:00 PM | AE51: 45869 | AL51: {=IFERROR(IFS(XLOOKUP(B51, 'Kit Delivery Status'!$U:$U, 'Kit Delivery Status'!$K:$K) = "Complete", "DELIVERED", XLOOKUP(B51, 'Kit Delivery Status'!$U:$U, 'Kit Delivery Status'!$K:$K) = "Issue", "ISSUE"), "")}
... A57: =HYPERLINK("https://utrucking.myshopify.com/admin/orders?query="&RIGHT(B57,LEN(B57)-1)) -> https://utrucking.myshopify.com/admin/orders?query=15206 | B57: #15206 | C57: rogers.z@wustl.edu | D57: (410) 484-1841 | E57: Zachary Rogers | F57: 3524 Barton Oaks Road | K57: Nationwide Ship to School | N57: University Housing | P57: 45882 | Q57: 12:00 PM - 02:00 PM | U57: Lee | V57: 301 - b | X57: 45882 | Y57: 12:00 PM - 02:00 PM | AE57: 45882 | AL57: {=IFERROR(IFS(XLOOKUP(B57, 'Kit Delivery Status'!$U:$U, 'Kit Delivery Status'!$K:$K) = "Complete", "DELIVERED", XLOOKUP(B57, 'Kit Delivery Status'!$U:$U, 'Kit Delivery Status'!$K:$K) = "Issue", "ISSUE"), "")}
A58: =HYPERLINK("https://utrucking.myshopify.com/admin/orders?query="&RIGHT(B58,LEN(B58)-1)) -> https://utrucking.myshopify.com/admin/orders?query=15207 | B58: #15207 | C58: pmstobaugh@gmail.com | D58: (1812) 449-0494 | E58: Jenna Stobaugh | F58: 4333 Wynbrooke Dr | K58: Nationwide Ship to School | P58: 45882 | Q58: 09:00 AM - 11:00 AM | X58: 45882 | Y58: 09:00 AM - 11:00 AM | AE58: 45882 | AL58: {=IFERROR(IFS(XLOOKUP(B58, 'Kit Delivery Status'!$U:$U, 'Kit Delivery Status'!$K:$K) = "Complete", "DELIVERED", XLOOKUP(B58, 'Kit Delivery Status'!$U:$U, 'Kit Delivery Status'!$K:$K) = "Issue", "ISSUE"), "")}
A59: =HYPERLINK("https://utrucking.myshopify.com/admin/orders?query="&RIGHT(B59,LEN(B59)-1)) -> https://utrucking.myshopify.com/admin/orders?query=15214 | B59: #15214 | C59: sobaqueen@hotmail.com | D59: (1502) 708-0350 | E59: Shannon Pankonin | F59: 6413 Regency Ln | K59: Nationwide Ship to School | N59: University Housing | P59: 45877 | Q59: 09:00 AM - 11:00 AM | U59: Lee | V59: 116 | X59: 45877 | Y59: 09:00 AM - 11:00 AM | AE59: 45877 | AL59: {=IFERROR(IFS(XLOOKUP(B59, 'Kit Delivery Status'!$U:$U, 'Kit Delivery Status'!$K:$K) = "Complete", "DELIVERED", XLOOKUP(B59, 'Kit Delivery Status'!$U:$U, 'Kit Delivery Status'!$K:$K) = "Issue", "ISSUE"), "")}
A60: =HYPERLINK("https://utrucking.myshopify.com/admin/orders?query="&RIGHT(B60,LEN(B60)-1)) -> https://utrucking.myshopify.com/admin/orders?query=14711 | B60: #14711 | C60: shrier@wustl.edu | D60: (917) 558-3799 | E60: Sienna Shrier | F60: 42 Danebury Downs | K60: Tri-State Area Home Pickups | N60: University Housing | P60: 45878 | Q60: 03:00 PM - 05:00 PM | U60: DON'T KNOW YET (put 'XXX' for room #) | V60: XXX | X60: 45878 | Y60: 03:00 PM - 05:00 PM | AE60: 45878 | AL60: {=IFERROR(IFS(XLOOKUP(B60, 'Kit Delivery Status'!$U:$U, 'Kit Delivery Status'!$K:$K) = "Complete", "DELIVERED", XLOOKUP(B60, 'Kit Delivery Status'!$U:$U, 'Kit Delivery Status'!$K:$K) = "Issue", "ISSUE"), "")}
A61: =HYPERLINK("https://utrucking.myshopify.com/admin/orders?query="&RIGHT(B61,LEN(B61)-1)) -> https://utrucking.myshopify.com/admin/orders?query=14341 | B61: #14341 | C61: a.rome@wustl.edu | D61: (1917) 828-0684 | E61: Isabella AVA Rome | F61: 63 Lilline Lane | K61: Tri-State Area Home Pickups | N61: University Housing | O61: 3302 | P61: 45878 | Q61: 09:00 AM - 11:00 AM | U61: Umrath | V61: 3302 | X61: 45878 | Y61: 09:00 AM - 11:00 AM | AE61: 45878 | AL61: {=IFERROR(IFS(XLOOKUP(B61, 'Kit Delivery Status'!$U:$U, 'Kit Delivery Status'!$K:$K) = "Complete", "DELIVERED", XLOOKUP(B61, 'Kit Delivery Status'!$U:$U, 'Kit Delivery Status'!$K:$K) = "Issue", "ISSUE"), "")}
A62: =HYPERLINK("https://utrucking.myshopify.com/admin/orders?query="&RIGHT(B62,LEN(B62)-1)) -> https://utrucking.myshopify.com/admin/orders?query=14098 | B62: #14098 | C62: benschwed9876@wustl.edu | D62: (1516) 998-5553 | E62: Benjamin Schwed | F62: 2806 Harbor Rd | K62: Tri-State Area Home Pickups | N62: University Housing | P62: 45883 | Q62: 09:00 AM - 11:00 AM | U62: Danforth | V62: 3304 | X62: 45883 | Y62: 09:00 AM - 11:00 AM | AE62: 45883 | AL62: {=IFERROR(IFS(XLOOKUP(B62, 'Kit Delivery Status'!$U:$U, 'Kit Delivery Status'!$K:$K) = "Complete", "DELIVERED", XLOOKUP(B62, 'Kit Delivery Status'!$U:$U, 'Kit Delivery Status'!$K:$K) = "Issue", "ISSUE"), "")}
A63: =HYPERLINK("https://utrucking.myshopify.com/admin/orders?query="&RIGHT(B63,LEN(B63)-1)) -> https://utrucking.myshopify.com/admin/orders?query=14346 | B63: #14346 | C63: prenner.s@wustl.edu | D63: (609) 240-6425 | E63: Rebecca Baumgold | F63: 61 Littlebrook Rd | K63: Tri-State Area Home Pickups | N63: Non-University Housing | P63: 45892 | Q63: 09:00 AM - 11:00 AM | R63: 6115 Waterman Street, St. Louis, MO | X63: 45892 | Y63: 09:00 AM - 11:00 AM | AA63: 6115 Waterman Street, St. Louis, MO | AE63: 45892 | AL63: {=IFERROR(IFS(XLOOKUP(B63, 'Kit Delivery Status'!$U:$U, 'Kit Delivery Status'!$K:$K) = "Complete", "DELIVERED", XLOOKUP(B63, 'Kit Delivery Status'!$U:$U, 'Kit Delivery Status'!$K:$K) = "Issue", "ISSUE"), "")}
A64: =HYPERLINK("https://utrucking.myshopify.com/admin/orders?query="&RIGHT(B64,LEN(B64)-1)) -> https://utrucking.myshopify.com/admin/orders?query=14567 | B64: #14567 | C64: e.r.schulman@wustl.edu | D64: (516) 606-3860 | E64: Eliza Schulman | F64: 4 Stonehenge Road | K64: Tri-State Area Home Pickups | N64: University Housing | P64: 45883 | Q64: 03:00 PM - 05:00 PM | U64: Rutledge | V64: 121 | X64: 45883 | Y64: 03:00 PM - 05:00 PM | AE64: 45883 | AL64: {=IFERROR(IFS(XLOOKUP(B64, 'Kit Delivery Status'!$U:$U, 'Kit Delivery Status'!$K:$K) = "Complete", "DELIVERED", XLOOKUP(B64, 'Kit Delivery Status'!$U:$U, 'Kit Delivery Status'!$K:$K) = "Issue", "ISSUE"), "")}
A65: =HYPERLINK("https://utrucking.myshopify.com/admin/orders?query="&RIGHT(B65,LEN(B65)-1)) -> https://utrucking.myshopify.com/admin/orders?query=14593 | B65: #14593 | C65: blanco.j@wustl.edu | D65: (917) 806-7198 | E65: James Blanco | F65: 22 St. Johns Place | K65: Tri-State Area Home Pickups | N65: University Housing | P65: 45877 | Q65: 09:00 AM to 11:00 AM | U65: Umrath | V65: 2215 | X65: 45877 | Y65: 09:00 AM to 11:00 AM | AE65: 45877 | AL65: {=IFERROR(IFS(XLOOKUP(B65, 'Kit Delivery Status'!$U:$U, 'Kit Delivery Status'!$K:$K) = "Complete", "DELIVERED", XLOOKUP(B65, 'Kit Delivery Status'!$U:$U, 'Kit Delivery Status'!$K:$K) = "Issue", "ISSUE"), "")}
A66: =HYPERLINK("https://utrucking.myshopify.com/admin/orders?query="&RIGHT(B66,LEN(B66)-1)) -> https://utrucking.myshopify.com/admin/orders?query=14853 | B66: #14853 | C66: g.juliette@wustl.edu | D66: (1917) 685-6265 | E66: Juliette Goodstein | F66: 160 E 65th St | K66: Tri-State Area Home Pickups | N66: University Housing | P66: 45878 | Q66: 12:00 PM - 02:00 PM | U66: Park | V66: 372 | X66: 45878 | Y66: 12:00 PM - 02:00 PM | AE66: 45878 | AL66: {=IFERROR(IFS(XLOOKUP(B66, 'Kit Delivery Status'!$U:$U, 'Kit Delivery Status'!$K:$K) = "Complete", "DELIVERED", XLOOKUP(B66, 'Kit Delivery Status'!$U:$U, 'Kit Delivery Status'!$K:$K) = "Issue", "ISSUE"), "")}
A67: =HYPERLINK("https://utrucking.myshopify.com/admin/orders?query="&RIGHT(B67,LEN(B67)-1)) -> https://utrucking.myshopify.com/admin/orders?query=15002 | B67: #15002 | C67: ljansveld9876@wustl.edu | D67: (1908) 502-1523 | E67: Luka Jansveld | F67: 411 Harrison Avenue | K67: Tri-State Area Home Pickups | N67: University Housing | P67: 45878 | Q67: 11:00 AM - 01:00 PM | U67: DON'T KNOW YET (put 'XXX' for room #) | V67: Xxx | X67: 45878 | Y67: 11:00 AM - 01:00 PM | AE67: 45878 | AL67: {=IFERROR(IFS(XLOOKUP(B67, 'Kit Delivery Status'!$U:$U, 'Kit Delivery Status'!$K:$K) = "Complete", "DELIVERED", XLOOKUP(B67, 'Kit Delivery Status'!$U:$U, 'Kit Delivery Status'!$K:$K) = "Issue", "ISSUE"), "")}
A68: =HYPERLINK("https://utrucking.myshopify.com/admin/orders?query="&RIGHT(B68,LEN(B68)-1)) -> https://utrucking.myshopify.com/admin/orders?query=15005 | B68: #15005 | C68: h.shaye@email.wustl.edu | D68: (201) 264-8488 | E68: Lauri Herman | F68: 72 Essex Street | K68: Tri-State Area Home Pickups | N68: University Housing | P68: 45878 | Q68: 09:00 AM - 11:00 AM | U68: Millbrook Bldg. 4 | V68: B-3C-A | X68: 45878 | Y68: 09:00 AM - 11:00 AM | AE68: 45878 | AL68: {=IFERROR(IFS(XLOOKUP(B68, 'Kit Delivery Status'!$U:$U, 'Kit Delivery Status'!$K:$K) = "Complete", "DELIVERED", XLOOKUP(B68, 'Kit Delivery Status'!$U:$U, 'Kit Delivery Status'!$K:$K) = "Issue", "ISSUE"), "")}
A69: =HYPERLINK("https://utrucking.myshopify.com/admin/orders?query="&RIGHT(B69,LEN(B69)-1)) -> https://utrucking.myshopify.com/admin/orders?query=15011 | B69: #15011 | C69: hametz@wustl.edu | D69: (914) 849-8141 | E69: Emily Hametz | F69: 41 Indian Hill Road | K69: Tri-State Area Home Pickups | N69: University Housing | P69: 45877 | Q69: 11:00 AM - 01:00 PM | U69: DON'T KNOW YET (put 'XXX' for room #) | V69: XXX | X69: 45877 | Y69: 11:00 AM - 01:00 PM | AE69: 45877 | AL69: {=IFERROR(IFS(XLOOKUP(B69, 'Kit Delivery Status'!$U:$U, 'Kit Delivery Status'!$K:$K) = "Complete", "DELIVERED", XLOOKUP(B69, 'Kit Delivery Status'!$U:$U, 'Kit Delivery Status'!$K:$K) = "Issue", "ISSUE"), "")}
A70: =HYPERLINK("https://utrucking.myshopify.com/admin/orders?query="&RIGHT(B70,LEN(B70)-1)) -> https://utrucking.myshopify.com/admin/orders?query=15028 | B70: #15028 | C70: k.m.ziwot@wustl.edu | D70: (908) 698-9314 | E70: Katherine Ziwot | F70: 21 Pickle Brook Road | K70: Tri-State Area Home Pickups | N70: University Housing | P70: 45877 | Q70: 12:00 PM - 02:00 PM | U70: Danforth | V70: 2212 | X70: 45877 | Y70: 12:00 PM - 02:00 PM | AE70: 45877 | AL70: {=IFERROR(IFS(XLOOKUP(B70, 'Kit Delivery Status'!$U:$U, 'Kit Delivery Status'!$K:$K) = "Complete", "DELIVERED", XLOOKUP(B70, 'Kit Delivery Status'!$U:$U, 'Kit Delivery Status'!$K:$K) = "Issue", "ISSUE"), "")}
A71: =HYPERLINK("https://utrucking.myshopify.com/admin/orders?query="&RIGHT(B71,LEN(B71)-1)) -> https://utrucking.myshopify.com/admin/orders?query=15029 | B71: #15029 | C71: k.i.rodriguez@wustl.edu | D71: (203) 571-8398 | E71: Kate Rodriguez | F71: 4 Concord Lane | K71: Tri-State Area Home Pickups | N71: University Housing | P71: 45877 | Q71: 09:00 AM to 11:00 AM | U71: Koenig | V71: 4410 | X71: 45877 | Y71: 09:00 AM to 11:00 AM | AE71: 45877 | AL71: {=IFERROR(IFS(XLOOKUP(B71, 'Kit Delivery Status'!$U:$U, 'Kit Delivery Status'!$K:$K) = "Complete", "DELIVERED", XLOOKUP(B71, 'Kit Delivery Status'!$U:$U, 'Kit Delivery Status'!$K:$K) = "Issue", "ISSUE"), "")}
A72: =HYPERLINK("https://utrucking.myshopify.com/admin/orders?query="&RIGHT(B72,LEN(B72)-1)) -> https://utrucking.myshopify.com/admin/orders?query=15040 | B72: #15040 | C72: modlinger.z@email.wustl.edu | D72: (917) 612-3196 | E72: Zachary Modlinger | F72: 1263 Sussex Road | K72: Tri-State Area Home Pickups | N72: University Housing | P72: 45883 | Q72: 10:00 AM - 12:00 PM | U72: Koenig | V72: 3304 | X72: 45883 | Y72: 10:00 AM - 12:00 PM | AE72: 45883 | AL72: {=IFERROR(IFS(XLOOKUP(B72, 'Kit Delivery Status'!$U:$U, 'Kit Delivery Status'!$K:$K) = "Complete", "DELIVERED", XLOOKUP(B72, 'Kit Delivery Status'!$U:$U, 'Kit Delivery Status'!$K:$K) = "Issue", "ISSUE"), "")}
A73: =HYPERLINK("https://utrucking.myshopify.com/admin/orders?query="&RIGHT(B73,LEN(B73)-1)) -> https://utrucking.myshopify.com/admin/orders?query=15073 | B73: #15073 | C73: amiller@milbank.com | D73: (1646) 334-9279 | E73: Atara miller | F73: 45 Longvue Avenue | K73: Tri-State Area Home Pickups | N73: Non-University Housing | P73: 45877 | Q73: 03:00 PM - 05:00 PM | R73: 45 Longvue Ave, New Rochelle, NY 10804 | X73: 45877 | Y73: 03:00 PM - 05:00 PM | AA73: 45 Longvue Ave, New Rochelle, NY 10804 | AE73: 45877 | AL73: {=IFERROR(IFS(XLOOKUP(B73, 'Kit Delivery Status'!$U:$U, 'Kit Delivery Status'!$K:$K) = "Complete", "DELIVERED", XLOOKUP(B73, 'Kit Delivery Status'!$U:$U, 'Kit Delivery Status'!$K:$K) = "Issue", "ISSUE"), "")}
A74: =HYPERLINK("https://utrucking.myshopify.com/admin/orders?query="&RIGHT(B74,LEN(B74)-1)) -> https://utrucking.myshopify.com/admin/orders?query=15074 | B74: #15074 | C74: n.samson@wustl.edu | D74: (917) 605-2406 | E74: Samson Nwobi | F74: 347 Hawthorne Avenue | K74: Tri-State Area Home Pickups | N74: University Housing | P74: 45874 | Q74: 11:00 AM to 01:00 PM | U74: DON'T KNOW YET (put 'XXX' for room #) | V74: XXX | X74: 45874 | Y74: 11:00 AM to 01:00 PM | AE74: 45874 | AL74: {=IFERROR(IFS(XLOOKUP(B74, 'Kit Delivery Status'!$U:$U, 'Kit Delivery Status'!$K:$K) = "Complete", "DELIVERED", XLOOKUP(B74, 'Kit Delivery Status'!$U:$U, 'Kit Delivery Status'!$K:$K) = "Issue", "ISSUE"), "")}
A75: =HYPERLINK("https://utrucking.myshopify.com/admin/orders?query="&RIGHT(B75,LEN(B75)-1)) -> https://utrucking.myshopify.com/admin/orders?query=15079 | B75: #15079 | C75: marnie0609@yahoo.com | D75: (1917) 612-9737 | E75: Marnie Rukin | F75: 10 Rockledge Rd | K75: Tri-State Area Home Pickups | N75: University Housing | O75: 2240 | P75: 45877 | Q75: 11:00 AM - 01:00 PM | U75: Umrath | V75: 2240 | X75: 45877 | Y75: 11:00 AM - 01:00 PM | AE75: 45877 | AL75: {=IFERROR(IFS(XLOOKUP(B75, 'Kit Delivery Status'!$U:$U, 'Kit Delivery Status'!$K:$K) = "Complete", "DELIVERED", XLOOKUP(B75, 'Kit Delivery Status'!$U:$U, 'Kit Delivery Status'!$K:$K) = "Issue", "ISSUE"), "")}
A76: =HYPERLINK("https://utrucking.myshopify.com/admin/orders?query="&RIGHT(B76,LEN(B76)-1)) -> https://utrucking.myshopify.com/admin/orders?query=15094 | B76: #15094 | C76: l.maddy@wustl.edu | D76: (203) 554-1142 | E76: Maddy Lee | F76: 36 Andrews Farm Road | K76: Tri-State Area Home Pickups | N76: University Housing | P76: 45877 | Q76: 11:00 AM - 01:00 PM | U76: Nemerov | V76: 4060 | X76: 45877 | Y76: 11:00 AM - 01:00 PM | AE76: 45877 | AL76: {=IFERROR(IFS(XLOOKUP(B76, 'Kit Delivery Status'!$U:$U, 'Kit Delivery Status'!$K:$K) = "Complete", "DELIVERED", XLOOKUP(B76, 'Kit Delivery Status'!$U:$U, 'Kit Delivery Status'!$K:$K) = "Issue", "ISSUE"), "")}
A77: =HYPERLINK("https://utrucking.myshopify.com/admin/orders?query="&RIGHT(B77,LEN(B77)-1)) -> https://utrucking.myshopify.com/admin/orders?query=15097 | B77: #15097 | C77: blumi@wustl.edu | D77: (516) 376-8942 | E77: Benjamin Lumi | F77: 48 Edgewood Road | K77: Tri-State Area Home Pickups | N77: University Housing | P77: 45878 | Q77: 09:00 AM - 11:00 AM | U77: DON'T KNOW YET (put 'XXX' for room #) | V77: XXX | X77: 45878 | Y77: 09:00 AM - 11:00 AM | AE77: 45878 | AL77: {=IFERROR(IFS(XLOOKUP(B77, 'Kit Delivery Status'!$U:$U, 'Kit Delivery Status'!$K:$K) = "Complete", "DELIVERED", XLOOKUP(B77, 'Kit Delivery Status'!$U:$U, 'Kit Delivery Status'!$K:$K) = "Issue", "ISSUE"), "")}
A78: =HYPERLINK("https://utrucking.myshopify.com/admin/orders?query="&RIGHT(B78,LEN(B78)-1)) -> https://utrucking.myshopify.com/admin/orders?query=15098 | B78: #15098 | C78: k.sammy@wustl.edu | D78: (973) 985-5672 | E78: Karin Kelner | F78: 9 Sailers Way | K78: Tri-State Area Home Pickups | N78: University Housing | P78: 45878 | Q78: 09:00 AM - 11:00 AM | U78: Loop Loft 6255 | V78: Apartment 411C | X78: 45878 | Y78: 09:00 AM - 11:00 AM | AE78: 45878 | AL78: {=IFERROR(IFS(XLOOKUP(B78, 'Kit Delivery Status'!$U:$U, 'Kit Delivery Status'!$K:$K) = "Complete", "DELIVERED", XLOOKUP(B78, 'Kit Delivery Status'!$U:$U, 'Kit Delivery Status'!$K:$K) = "Issue", "ISSUE"), "")}
A79: =HYPERLINK("https://utrucking.myshopify.com/admin/orders?query="&RIGHT(B79,LEN(B79)-1)) -> https://utrucking.myshopify.com/admin/orders?query=14588 | B79: #14588 | C79: j.rangaraj@wustl.edu | D79: (914) 400-5464 | E79: Jayant Rangaraj | F79: I don't know | K79: Tri-State Area Home Pickups | N79: Non-University Housing | P79: 45877 | Q79: 09:00 AM - 11:00 AM | R79: 14 Ridgecrest E, Scarsdale, NY 10583 | U79: Danforth | V79: 4419 | X79: 45877 | Y79: 09:00 AM - 11:00 AM | AA79: 14 Ridgecrest E, Scarsdale, NY 10583 | AE79: 45877 | AL79: {=IFERROR(IFS(XLOOKUP(B79, 'Kit Delivery Status'!$U:$U, 'Kit Delivery Status'!$K:$K) = "Complete", "DELIVERED", XLOOKUP(B79, 'Kit Delivery Status'!$U:$U, 'Kit Delivery Status'!$K:$K) = "Issue", "ISSUE"), "")}
A80: =HYPERLINK("https://utrucking.myshopify.com/admin/orders?query="&RIGHT(B80,LEN(B80)-1)) -> https://utrucking.myshopify.com/admin/orders?query=14849 | B80: #14849 | C80: c.a.mallah@wustl.edu | D80: (917) 921-7228 | E80: Lloyd Mallah | F80: 17 Birch Lane | K80: Tri-State Area Home Pickups | N80: Non-University Housing | P80: 45888 | Q80: 3:00 PM - 5:00 PM | R80: 6843 Kingsbury Blvd, University City, MO 63130 Apartment 1E | X80: 45888 | Y80: 3:00 PM - 5:00 PM | AA80: 6843 Kingsbury Blvd, University City, MO 63130 Apartment 1E | AE80: 45888 | AL80: {=IFERROR(IFS(XLOOKUP(B80, 'Kit Delivery Status'!$U:$U, 'Kit Delivery Status'!$K:$K) = "Complete", "DELIVERED", XLOOKUP(B80, 'Kit Delivery Status'!$U:$U, 'Kit Delivery Status'!$K:$K) = "Issue", "ISSUE"), "")}
A81: =HYPERLINK("https://utrucking.myshopify.com/admin/orders?query="&RIGHT(B81,LEN(B81)-1)) -> https://utrucking.myshopify.com/admin/orders?query=15111 | B81: #15111 | C81: alexsaltzman@hotmail.com | D81: (646) 245-8563 | E81: Sophie Saltzman | F81: 212 Legend Drive | K81: Tri-State Area Home Pickups | N81: University Housing | P81: 45877 | Q81: 09:00 AM - 11:00 AM | U81: Umrath | V81: XXX | X81: 45877 | Y81: 09:00 AM - 11:00 AM | AE81: 45877 | AL81: {=IFERROR(IFS(XLOOKUP(B81, 'Kit Delivery Status'!$U:$U, 'Kit Delivery Status'!$K:$K) = "Complete", "DELIVERED", XLOOKUP(B81, 'Kit Delivery Status'!$U:$U, 'Kit Delivery Status'!$K:$K) = "Issue", "ISSUE"), "")}
A82: =HYPERLINK("https://utrucking.myshopify.com/admin/orders?query="&RIGHT(B82,LEN(B82)-1)) -> https://utrucking.myshopify.com/admin/orders?query=15114 | B82: #15114 | C82: glassj@washu.edu | D82: (914) 432-6482 | E82: Jonah Glass | F82: 29 Guion Street | K82: Tri-State Area Home Pickups | N82: University Housing | P82: 45882 | Q82: 12:00 PM - 02:00 PM | U82: Dauten | V82: 242-b | X82: 45882 | Y82: 12:00 PM - 02:00 PM | AE82: 45882 | AL82: {=IFERROR(IFS(XLOOKUP(B82, 'Kit Delivery Status'!$U:$U, 'Kit Delivery Status'!$K:$K) = "Complete", "DELIVERED", XLOOKUP(B82, 'Kit Delivery Status'!$U:$U, 'Kit Delivery Status'!$K:$K) = "Issue", "ISSUE"), "")}
A83: =HYPERLINK("https://utrucking.myshopify.com/admin/orders?query="&RIGHT(B83,LEN(B83)-1)) -> https://utrucking.myshopify.com/admin/orders?query=15116 | B83: #15116 | C83: amiyahl@wustl.edu | D83: (1347) 557-6359 | E83: Claudia Louis | F83: 1325 Jerome Ave | K83: Tri-State Area Home Pickups | N83: University Housing | P83: 45882 | Q83: 09:00 AM - 11:00 AM | U83: Koenig | V83: 4402 | X83: 45882 | Y83: 09:00 AM - 11:00 AM | AE83: 45882 | AL83: {=IFERROR(IFS(XLOOKUP(B83, 'Kit Delivery Status'!$U:$U, 'Kit Delivery Status'!$K:$K) = "Complete", "DELIVERED", XLOOKUP(B83, 'Kit Delivery Status'!$U:$U, 'Kit Delivery Status'!$K:$K) = "Issue", "ISSUE"), "")}
A84: =HYPERLINK("https://utrucking.myshopify.com/admin/orders?query="&RIGHT(B84,LEN(B84)-1)) -> https://utrucking.myshopify.com/admin/orders?query=15118 | B84: #15118 | C84: kelly.s.g@wustl.edu | D84: (908) 514-9191 | E84: Sarah Kelly | F84: 19 Rotary Lane | K84: Tri-State Area Home Pickups | N84: University Housing | P84: 45890 | Q84: 09:00 AM - 11:00 AM | U84: Zetcher | V84: 2214-a | X84: 45890 | Y84: 09:00 AM - 11:00 AM | AE84: 45890 | AL84: {=IFERROR(IFS(XLOOKUP(B84, 'Kit Delivery Status'!$U:$U, 'Kit Delivery Status'!$K:$K) = "Complete", "DELIVERED", XLOOKUP(B84, 'Kit Delivery Status'!$U:$U, 'Kit Delivery Status'!$K:$K) = "Issue", "ISSUE"), "")}
A85: =HYPERLINK("https://utrucking.myshopify.com/admin/orders?query="&RIGHT(B85,LEN(B85)-1)) -> https://utrucking.myshopify.com/admin/orders?query=15124 | B85: #15124 | C85: j.g.kershner@wustl.edu | D85: (917) 566-0907 | E85: Jackie Kershner | F85: 12 Elm Road | K85: Tri-State Area Home Pickups | N85: University Housing | O85: 4402 | P85: 45882 | Q85: 09:00 AM - 11:00 AM | U85: Dardick | V85: 4402 | X85: 45882 | Y85: 09:00 AM - 11:00 AM | AE85: 45882 | AL85: {=IFERROR(IFS(XLOOKUP(B85, 'Kit Delivery Status'!$U:$U, 'Kit Delivery Status'!$K:$K) = "Complete", "DELIVERED", XLOOKUP(B85, 'Kit Delivery Status'!$U:$U, 'Kit Delivery Status'!$K:$K) = "Issue", "ISSUE"), "")}
A86: =HYPERLINK("https://utrucking.myshopify.com/admin/orders?query="&RIGHT(B86,LEN(B86)-1)) -> https://utrucking.myshopify.com/admin/orders?query=15139 | B86: #15139 | C86: slovinlauren@gmail.com | D86: (1203) 913-6275 | E86: Lauren Slovin | F86: 21 Midwood Dr | K86: Tri-State Area Home Pickups | N86: University Housing | P86: 45882 | Q86: 09:00 AM - 11:00 AM | U86: Lien | V86: 3310 | X86: 45882 | Y86: 09:00 AM - 11:00 AM | AE86: 45882 | AL86: {=IFERROR(IFS(XLOOKUP(B86, 'Kit Delivery Status'!$U:$U, 'Kit Delivery Status'!$K:$K) = "Complete", "DELIVERED", XLOOKUP(B86, 'Kit Delivery Status'!$U:$U, 'Kit Delivery Status'!$K:$K) = "Issue", "ISSUE"), "")}
A87: =HYPERLINK("https://utrucking.myshopify.com/admin/orders?query="&RIGHT(B87,LEN(B87)-1)) -> https://utrucking.myshopify.com/admin/orders?query=15141 | B87: #15141 | C87: hplattus@gmail.com | D87: (917) 664-5613 | E87: Hilary Plattus | F87: 111 Inverness Rd | K87: Tri-State Area Home Pickups | N87: University Housing | P87: 45877 | Q87: 03:00 PM - 05:00 PM | U87: House 4 (Theta Xi) | V87: Second floor | X87: 45877 | Y87: 03:00 PM - 05:00 PM | AE87: 45877 | AL87: {=IFERROR(IFS(XLOOKUP(B87, 'Kit Delivery Status'!$U:$U, 'Kit Delivery Status'!$K:$K) = "Complete", "DELIVERED", XLOOKUP(B87, 'Kit Delivery Status'!$U:$U, 'Kit Delivery Status'!$K:$K) = "Issue", "ISSUE"), "")}
A88: =HYPERLINK("https://utrucking.myshopify.com/admin/orders?query="&RIGHT(B88,LEN(B88)-1)) -> https://utrucking.myshopify.com/admin/orders?query=15161 | B88: #15161 | C88: h.linsky@wustl.edu | D88: (917) 214-1935 | E88: Hayden Linsky | F88: 68 Severn Street | K88: Tri-State Area Home Pickups | N88: University Housing | O88: 3320 | P88: 45882 | Q88: 09:00 AM - 11:00 AM | U88: Danforth | V88: 3320 | X88: 45882 | Y88: 09:00 AM - 11:00 AM | AE88: 45882 | AL88: {=IFERROR(IFS(XLOOKUP(B88, 'Kit Delivery Status'!$U:$U, 'Kit Delivery Status'!$K:$K) = "Complete", "DELIVERED", XLOOKUP(B88, 'Kit Delivery Status'!$U:$U, 'Kit Delivery Status'!$K:$K) = "Issue", "ISSUE"), "")}
A89: =HYPERLINK("https://utrucking.myshopify.com/admin/orders?query="&RIGHT(B89,LEN(B89)-1)) -> https://utrucking.myshopify.com/admin/orders?query=15162 | B89: #15162 | C89: i.linsky@wustl.edu | D89: (917) 214-1935 | E89: hilary linsky | F89: 6 kenwood drive | K89: Tri-State Area Home Pickups | N89: University Housing | O89: 3320 | P89: 45882 | Q89: 09:00 AM - 11:00 AM | U89: Danforth | V89: 3320 | X89: 45882 | Y89: 09:00 AM - 11:00 AM | AE89: 45882 | AL89: {=IFERROR(IFS(XLOOKUP(B89, 'Kit Delivery Status'!$U:$U, 'Kit Delivery Status'!$K:$K) = "Complete", "DELIVERED", XLOOKUP(B89, 'Kit Delivery Status'!$U:$U, 'Kit Delivery Status'!$K:$K) = "Issue", "ISSUE"), "")}
A90: =HYPERLINK("https://utrucking.myshopify.com/admin/orders?query="&RIGHT(B90,LEN(B90)-1)) -> https://utrucking.myshopify.com/admin/orders?query=15165 | B90: #15165 | C90: lisamichelekern@gmail.com | D90: (917) 696-8178 | E90: Lisa Kern | F90: 11 Country Club Drive | K90: Tri-State Area Home Pickups | N90: University Housing | P90: 45882 | Q90: 09:00 AM - 11:00 AM | U90: DON'T KNOW YET (put 'XXX' for room #) | V90: XXX | X90: 45882 | Y90: 09:00 AM - 11:00 AM | AE90: 45882 | AL90: {=IFERROR(IFS(XLOOKUP(B90, 'Kit Delivery Status'!$U:$U, 'Kit Delivery Status'!$K:$K) = "Complete", "DELIVERED", XLOOKUP(B90, 'Kit Delivery Status'!$U:$U, 'Kit Delivery Status'!$K:$K) = "Issue", "ISSUE"), "")}
A91: =HYPERLINK("https://utrucking.myshopify.com/admin/orders?query="&RIGHT(B91,LEN(B91)-1)) -> https://utrucking.myshopify.com/admin/orders?query=15138 | B91: #15138 | C91: elianasalzberg@gmail.com | D91: (917) 733-0027 | E91: Ellie Salzberg | F91: University Housing(TBD) | K91: Tri-State Area Home Pickups | N91: University Housing | O91: 422 | P91: 45882 | Q91: 09:00 AM - 11:00 AM | U91: Dauten | V91: 422 | X91: 45882 | Y91: 09:00 AM - 11:00 AM | AE91: 45882 | AL91: {=IFERROR(IFS(XLOOKUP(B91, 'Kit Delivery Status'!$U:$U, 'Kit Delivery Status'!$K:$K) = "Complete", "DELIVERED", XLOOKUP(B91, 'Kit Delivery Status'!$U:$U, 'Kit Delivery Status'!$K:$K) = "Issue", "ISSUE"), "")}
A92: =HYPERLINK("https://utrucking.myshopify.com/admin/orders?query="&RIGHT(B92,LEN(B92)-1)) -> https://utrucking.myshopify.com/admin/orders?query=15181 | B92: #15181 | C92: ladden@wustl.edu | D92: (917) 273-2413 | E92: Matthew Ladden | F92: 6515 Wydown Boulevard | K92: Tri-State Area Home Pickups | N92: University Housing | P92: 45882 | Q92: 12:00 PM - 02:00 PM | U92: Eliot A | V92: 1033 | X92: 45882 | Y92: 12:00 PM - 02:00 PM | AE92: 45882 | AL92: {=IFERROR(IFS(XLOOKUP(B92, 'Kit Delivery Status'!$U:$U, 'Kit Delivery Status'!$K:$K) = "Complete", "DELIVERED", XLOOKUP(B92, 'Kit Delivery Status'!$U:$U, 'Kit Delivery Status'!$K:$K) = "Issue", "ISSUE"), "")}
A93: =HYPERLINK("https://utrucking.myshopify.com/admin/orders?query="&RIGHT(B93,LEN(B93)-1)) -> https://utrucking.myshopify.com/admin/orders?query=15191 | B93: #15191 | C93: cynthiamillinger@gmail.com | D93: (609) 647-3833 | E93: Cynthia Millinger | F93: 11 Wilson Way S | K93: Tri-State Area Home Pickups | N93: University Housing | P93: 45883 | Q93: 11:00 AM - 01:00 PM | U93: House 5 (Hamsini) | V93: 302-a | X93: 45883 | Y93: 11:00 AM - 01:00 PM | AE93: 45883 | AL93: {=IFERROR(IFS(XLOOKUP(B93, 'Kit Delivery Status'!$U:$U, 'Kit Delivery Status'!$K:$K) = "Complete", "DELIVERED", XLOOKUP(B93, 'Kit Delivery Status'!$U:$U, 'Kit Delivery Status'!$K:$K) = "Issue", "ISSUE"), "")}
A94: =HYPERLINK("https://utrucking.myshopify.com/admin/orders?query="&RIGHT(B94,LEN(B94)-1)) -> https://utrucking.myshopify.com/admin/orders?query=15192 | B94: #15192 | C94: q.sam@wustl.edu | E94: Sandy Quentzel | F94: 379 Throop Avenue | K94: Tri-State Area Home Pickups | N94: University Housing | P94: 45882 | Q94: 10:00 AM - 12:00 PM | U94: Dardick | V94: 2218 | X94: 45882 | Y94: 10:00 AM - 12:00 PM | AE94: 45882 | AL94: {=IFERROR(IFS(XLOOKUP(B94, 'Kit Delivery Status'!$U:$U, 'Kit Delivery Status'!$K:$K) = "Complete", "DELIVERED", XLOOKUP(B94, 'Kit Delivery Status'!$U:$U, 'Kit Delivery Status'!$K:$K) = "Issue", "ISSUE"), "")}
A95: =HYPERLINK("https://utrucking.myshopify.com/admin/orders?query="&RIGHT(B95,LEN(B95)-1)) -> https://utrucking.myshopify.com/admin/orders?query=15198 | B95: #15198 | C95: r.mia@wustl.edu | D95: (914) 610-8725 | E95: Mia Reisman | F95: 329 Stanley Avenue | K95: Tri-State Area Home Pickups | N95: University Housing | P95: 45882 | Q95: 09:00 AM - 11:00 AM | U95: Danforth | V95: 4422 - b | X95: 45882 | Y95: 09:00 AM - 11:00 AM | AE95: 45882 | AL95: {=IFERROR(IFS(XLOOKUP(B95, 'Kit Delivery Status'!$U:$U, 'Kit Delivery Status'!$K:$K) = "Complete", "DELIVERED", XLOOKUP(B95, 'Kit Delivery Status'!$U:$U, 'Kit Delivery Status'!$K:$K) = "Issue", "ISSUE"), "")}
A96: =HYPERLINK("https://utrucking.myshopify.com/admin/orders?query="&RIGHT(B96,LEN(B96)-1)) -> https://utrucking.myshopify.com/admin/orders?query=15200 | B96: #15200 | C96: j.g.sebag@wustl.edu | D96: (1917) 373-1714 | E96: jordan sebag | F96: 1700 Bay Boulevard | K96: Tri-State Area Home Pickups | N96: University Housing | P96: 45889 | Q96: 09:00 AM - 11:00 AM | U96: Village East | V96: 1111 | X96: 45889 | Y96: 09:00 AM - 11:00 AM | AE96: 45889 | AL96: {=IFERROR(IFS(XLOOKUP(B96, 'Kit Delivery Status'!$U:$U, 'Kit Delivery Status'!$K:$K) = "Complete", "DELIVERED", XLOOKUP(B96, 'Kit Delivery Status'!$U:$U, 'Kit Delivery Status'!$K:$K) = "Issue", "ISSUE"), "")}
A97: =HYPERLINK("https://utrucking.myshopify.com/admin/orders?query="&RIGHT(B97,LEN(B97)-1)) -> https://utrucking.myshopify.com/admin/orders?query=15212 | B97: #15212 | C97: leia.karczmer@gmail.com | D97: (646) 745-6120 | E97: Leia Karczmer | F97: 200 East End Ave, Apt 15J | K97: Tri-State Area Home Pickups | N97: University Housing | P97: 45882 | Q97: 09:00 AM - 11:00 AM | U97: Danforth | V97: 2221 | X97: 45882 | Y97: 09:00 AM - 11:00 AM | AE97: 45882 | AL97: {=IFERROR(IFS(XLOOKUP(B97, 'Kit Delivery Status'!$U:$U, 'Kit Delivery Status'!$K:$K) = "Complete", "DELIVERED", XLOOKUP(B97, 'Kit Delivery Status'!$U:$U, 'Kit Delivery Status'!$K:$K) = "Issue", "ISSUE"), "")}
A98: =HYPERLINK("https://utrucking.myshopify.com/admin/orders?query="&RIGHT(B98,LEN(B98)-1)) -> https://utrucking.myshopify.com/admin/orders?query=15213 | B98: #15213 | C98: addison.j.steinberg@wustl.edu | D98: (1917) 828-0780 | E98: Addison Steinberg | F98: 1045 Park Avenue | K98: Tri-State Area Home Pickups | N98: University Housing | P98: 45883 | Q98: 01:00 PM - 03:00 PM | U98: Millbrook Bldg. 3 | V98: 303A-a | X98: 45883 | Y98: 01:00 PM - 03:00 PM | AE98: 45883 | AL98: {=IFERROR(IFS(XLOOKUP(B98, 'Kit Delivery Status'!$U:$U, 'Kit Delivery Status'!$K:$K) = "Complete", "DELIVERED", XLOOKUP(B98, 'Kit Delivery Status'!$U:$U, 'Kit Delivery Status'!$K:$K) = "Issue", "ISSUE"), "")}
A99: =HYPERLINK("https://utrucking.myshopify.com/admin/orders?query="&RIGHT(B99,LEN(B99)-1)) -> https://utrucking.myshopify.com/admin/orders?query=14235 | B99: #14235 | C99: s.venkat@wustl.edu | D99: 5016766640 | E99: Sairisheeth Venkat | K99: Storage Item Return | N99: University Housing | O99: 2021-a | P99: 45891 | Q99: 10:00 AM - 12:00 PM | U99: Shepley | V99: 2021-a | X99: 45891 | Y99: 10:00 AM - 12:00 PM | AL99: {=IFERROR(IFS(XLOOKUP(B99, 'Kit Delivery Status'!$U:$U, 'Kit Delivery Status'!$K:$K) = "Complete", "DELIVERED", XLOOKUP(B99, 'Kit Delivery Status'!$U:$U, 'Kit Delivery Status'!$K:$K) = "Issue", "ISSUE"), "")}
A100: =HYPERLINK("https://utrucking.myshopify.com/admin/orders?query="&RIGHT(B100,LEN(B100)-1)) -> https://utrucking.myshopify.com/admin/orders?query=14235 | B100: #14235 | C100: s.venkat@wustl.edu | D100: 5016766640 | E100: Sairisheeth Venkat | K100: Appliance Rental | L100: Microwave Rental,Chef's Fridge Rental | AL100: {=IFERROR(IFS(XLOOKUP(B100, 'Kit Delivery Status'!$U:$U, 'Kit Delivery Status'!$K:$K) = "Complete", "DELIVERED", XLOOKUP(B100, 'Kit Delivery Status'!$U:$U, 'Kit Delivery Status'!$K:$K) = "Issue", "ISSUE"), "")}
A101: =HYPERLINK("https://utrucking.myshopify.com/admin/orders?query="&RIGHT(B101,LEN(B101)-1)) -> https://utrucking.myshopify.com/admin/orders?query=14296 | B101: #14296 | C101: h.violet@wustl.edu | D101: 5033339851 | E101: Violet Holah | K101: Appliance Rental | L101: Chef's Fridge Rental | N101: University Housing | O101: 201G - a | P101: 45883 | Q101: 09:00 AM - 11:00 AM | U101: Millbrook Bldg. 3 | V101: 201G - a | X101: 45883 | Y101: 09:00 AM - 11:00 AM | AL101: {=IFERROR(IFS(XLOOKUP(B101, 'Kit Delivery Status'!$U:$U, 'Kit Delivery Status'!$K:$K) = "Complete", "DELIVERED", XLOOKUP(B101, 'Kit Delivery Status'!$U:$U, 'Kit Delivery Status'!$K:$K) = "Issue", "ISSUE"), "")}
A102: =HYPERLINK("https://utrucking.myshopify.com/admin/orders?query="&RIGHT(B102,LEN(B102)-1)) -> https://utrucking.myshopify.com/admin/orders?query=14342 | B102: #14342 | C102: a.rome@wustl.edu | D102: 5513021447 | E102: Isabella (Ava) Rome | K102: Appliance Rental | L102: Double-Door Mini Fridge | N102: University Housing | O102: 3302 | P102: 45886 | Q102: 09:00 AM - 11:00 AM | U102: Umrath | V102: 3302 | X102: 45886 | Y102: 09:00 AM - 11:00 AM | AL102: {=IFERROR(IFS(XLOOKUP(B102, 'Kit Delivery Status'!$U:$U, 'Kit Delivery Status'!$K:$K) = "Complete", "DELIVERED", XLOOKUP(B102, 'Kit Delivery Status'!$U:$U, 'Kit Delivery Status'!$K:$K) = "Issue", "ISSUE"), "")}
A103: =HYPERLINK("https://utrucking.myshopify.com/admin/orders?query="&RIGHT(B103,LEN(B103)-1)) -> https://utrucking.myshopify.com/admin/orders?query=14366 | B103: #14366 | C103: k.swathi@wustl.edu | D103: 5084146973 | E103: Swathi Kannan | K103: Appliance Rental | L103: Double-Door Mini Fridge + Microwave | N103: University Housing | O103: 3023 | P103: 45888 | Q103: 02:00 PM - 04:00 PM | U103: Wheeler | V103: 3023 | X103: 45888 | Y103: 02:00 PM - 04:00 PM | AI103: Please make sure microwave and fridge are cleaned! | AL103: {=IFERROR(IFS(XLOOKUP(B103, 'Kit Delivery Status'!$U:$U, 'Kit Delivery Status'!$K:$K) = "Complete", "DELIVERED", XLOOKUP(B103, 'Kit Delivery Status'!$U:$U, 'Kit Delivery Status'!$K:$K) = "Issue", "ISSUE"), "")}
A104: =HYPERLINK("https://utrucking.myshopify.com/admin/orders?query="&RIGHT(B104,LEN(B104)-1)) -> https://utrucking.myshopify.com/admin/orders?query=14589 | B104: #14589 | C104: c.a.rosariocalderon@wustl.edu | D104: 7872362080 | E104: Camila Rosario | K104: Appliance Rental | L104: Microwave Rental,Chef's Fridge Rental | N104: University Housing | O104: 1062 | P104: 45891 | Q104: 10:00 AM - 12:00 PM | U104: Eliot B | V104: 1062 | X104: 45891 | Y104: 10:00 AM - 12:00 PM | AI104: Elliot B Suite #1060 Room Assigned #1062 | AL104: {=IFERROR(IFS(XLOOKUP(B104, 'Kit Delivery Status'!$U:$U, 'Kit Delivery Status'!$K:$K) = "Complete", "DELIVERED", XLOOKUP(B104, 'Kit Delivery Status'!$U:$U, 'Kit Delivery Status'!$K:$K) = "Issue", "ISSUE"), "")}
A105: =HYPERLINK("https://utrucking.myshopify.com/admin/orders?query="&RIGHT(B105,LEN(B105)-1)) -> https://utrucking.myshopify.com/admin/orders?query=14652 | B105: #14652 | C105: a.dalen@wustl.edu | D105: 5402078205 | E105: Dalen Ainsworth | K105: Storage Item Return | N105: University Housing | O105: 3301 | P105: 45877 | Q105: 09:00 AM to 11:00 AM | U105: Koenig | V105: 3301 | X105: 45877 | Y105: 09:00 AM to 11:00 AM | AI105: I am moving back in on May 11th to another dorm on WashU campus because I will be serving as a summer Conference Assistant. | AL105: {=IFERROR(IFS(XLOOKUP(B105, 'Kit Delivery Status'!$U:$U, 'Kit Delivery Status'!$K:$K) = "Complete", "DELIVERED", XLOOKUP(B105, 'Kit Delivery Status'!$U:$U, 'Kit Delivery Status'!$K:$K) = "Issue", "ISSUE"), "")}
...

Sheet Filtered MAIN - TEMP
A1: Order URL | B1: Order Name | C1: Email | D1: Phone | E1: Shipping Name | F1: Address | G1: City | H1: State/Province | I1: Zip/Postal Code | J1: Country | K1: Product Name | L1: Product SKU | M1: Product Price | N1: Delivery Location | O1: Room Number | P1: Delivery Date | Q1: Delivery Time | R1: Non-University Housing Address | S1: Location Type | T1: Delivery Location | U1: Building | V1: Room Number | W1: Address | X1: Delivery Date | Y1: Delivery Time | Z1: Insurance | AA1: Non-University Housing Address | AB1: Location Type | AC1: Ship From Address | AD1: Pickup Address | AE1: Pickup Date | AF1: Pickup Time | AG1: Pickup Location | AH1: Ship To Address
A2: https://utrucking.com/admin/orders/5897677144252 | B2: #15216 | C2: emeralda@wustl.edu | E2: Emeralda Jin | F2: 12110 Cameron Drive Duluth United States | G2: Duluth | H2: Georgia | I2: 30097 | J2: United States | K2: Storage Item Return | M2: 1 | N2: University Housing | O2: 141 | P2: 45890 | Q2: 11:00 AM - 01:00 PM | S2: University Housing | T2: University Housing | U2: Mudd | V2: 141 | X2: 45877 | AB2: University Housing
A3: https://utrucking.com/admin/orders/5897705062588 | B3: #15217 | C3: a.hermann@wustl.edu | E3: Andrew Hermann | F3: 1070 Park Avenue Apt. 4B New York United States | G3: New York | H3: New York | I3: 10128-1000 | J3: United States | K3: Tri-State Area Home Pickups | M3: 49 | O3: 2210-A | P3: 45877 | S3: University Housing | T3: University Housing | U3: Dardick | V3: 2210-A | X3: 45877 | Z3: $100 per item [Included] | AB3: University Housing
A4: https://utrucking.com/admin/orders/5897863135420 | B4: #15221 | C4: aiaccino29@yahoo.com | E4: Lauren Iaccino | F4: 6252 Penfield Avenue Woodland Hills United States | G4: Woodland Hills | H4: California | I4: 91367 | J4: United States | K4: Nationwide Ship to School | L4: Nationwide Ship to School | M4: 49 | O4: 312-a | P4: 45877 | S4: University Housing | T4: University Housing | U4: Park | V4: 312-a | X4: 45877 | AB4: University Housing
A5: https://utrucking.com/admin/orders/5898283614396 | B5: #15225 | C5: eiram777@comcast.net | E5: Marie Skwirblies | F5: 428 Fairway Dr Bartlett United States | G5: Bartlett | H5: Illinois | I5: 60103 | J5: United States | K5: Appliance Rental | L5: Double-Door Mini Fridge | M5: 145 | O5: 3134 | P5: 45877 | U5: Village House | V5: 3134 | X5: 45877
A6: https://utrucking.com/admin/orders/5898324410556 | B6: #15226 | C6: g.r.garcia@wustl.edu | E6: Gabriella Garcia | F6: 1426 Canyon Rim Dr NE Albuquerque United States | G6: Albuquerque | H6: New Mexico | I6: 87112 | J6: United States | K6: Nationwide Ship to School | L6: Nationwide Ship to School | M6: 49 | N6: University Housing | O6: 203 | P6: 45883 | Q6: 09:00 AM to 11:00 AM | T6: University Housing | U6: Eliot A | V6: 203 | X6: 45883 | Y6: 09:00 AM to 11:00 AM
A7: https://utrucking.com/admin/orders/5898432577724 | B7: #15227 | C7: ecarrott@hotmail.com | E7: Elizabeth Minnigh | F7: 3854 N Upland St Arlington United States | G7: Arlington | H7: Virginia | I7: 22207 | J7: United States | K7: Nationwide Ship to School | L7: Nationwide Ship to School | M7: 49 | N7: University Housing | O7: 4402 | P7: 45883 | Q7: 09:00 AM to 11:00 AM | T7: University Housing | U7: Danforth | V7: 4402 | X7: 45883 | Y7: 09:00 AM to 11:00 AM
A8: https://utrucking.com/admin/orders/5898465345724 | B8: #15228 | C8: cyung@wustl.edu | E8: Casey Yung | F8: 18 Warford Terrace Orinda United States | G8: Orinda | H8: California | I8: 94563 | J8: United States | K8: Nationwide Ship to School | L8: Nationwide Ship to School | M8: 49 | N8: University Housing | O8: 441 | P8: 45883 | Q8: 09:00 AM to 11:00 AM | T8: University Housing | U8: Park | V8: 441 | X8: 45883 | Y8: 09:00 AM to 11:00 AM
A9: https://utrucking.com/admin/orders/5898488905916 | B9: #15229 | C9: acaitlin@wustl.edu | E9: Caitlin Alfaro | F9: 28 Black Pine Lane Lumberton United States | G9: Lumberton | H9: New Jersey | I9: 8048 | J9: United States | K9: Nationwide Ship to School | L9: Nationwide Ship to School | M9: 49 | N9: University Housing | O9: 104C-b | P9: 45883 | Q9: 09:00 AM to 11:00 AM | T9: University Housing | U9: Millbrook Bldg. 2 | V9: 104C-b | X9: 45883 | Y9: 09:00 AM to 11:00 AM
A10: https://utrucking.com/admin/orders/5898491166908 | B10: #15230 | C10: acaitlin@wustl.edu | E10: Caitlin Alfaro | F10: 28 Black Pine Lane Lumberton United States | G10: Lumberton | H10: New Jersey | I10: 8048 | J10: United States | K10: Storage Item Return | M10: 1 | N10: University Housing | O10: 104C-b | P10: 45883 | Q10: 09:00 AM to 11:00 AM | T10: University Housing | U10: Millbrook Bldg. 2 | V10: 104C-b | X10: 45883 | Y10: 09:00 AM to 11:00 AM
A11: https://utrucking.com/admin/orders/5898525311164 | B11: #15232 | C11: m.h.ryu@wustl.edu | E11: Maya Ryu | F11: 4914 41st Street Northwest Washington United States | G11: Washington | H11: District of Columbia | I11: 20016 | J11: United States | K11: Appliance Rental | L11: Double-Door Mini Fridge | M11: 145 | O11: 201A - a | P11: 45883 | U11: Millbrook Bldg. 3 | V11: 201A - a | X11: 45883
A12: https://utrucking.com/admin/orders/5898994155708 | B12: #15236 | C12: a.kalbag@wustl.edu | E12: Arjun Kalbag | F12: 152 East 87th Street New York United States | G12: New York | H12: Connecticut | I12: 6880 | J12: United States | K12: Appliance Rental | L12: Double-Door Mini Fridge + Microwave | M12: 210 | O12: 3341 | P12: 45885 | U12: Umrath | V12: 3341 | X12: 45885
A13: https://utrucking.com/admin/orders/5899120771260 | B13: #15237 | D13: =12059223707 -> 12059223707 | E13: Olivia Vanlandingham | F13: 309 Le Jeune Way Birmingham United States | G13: Birmingham | H13: Alabama | I13: 35209 | J13: United States | K13: Appliance Rental | L13: Double-Door Mini Fridge | M13: 145 | O13: 380 | P13: 45875 | U13: Mudd | V13: 380 | X13: 45875
A14: https://utrucking.com/admin/orders/5899149574332 | B14: #15239 | C14: f.perez@wustl.edu | E14: Francisco Perez | F14: 4747 N Kenneth Ave Apt 3 Chicago United States | G14: Chicago | H14: Illinois | I14: 60630 | J14: United States | K14: Storage Item Return | M14: 1 | N14: University Housing | O14: 110 | P14: 45883 | Q14: 09:00 AM to 11:00 AM | T14: University Housing | U14: House 5 (Hamsini) | V14: 110 | X14: 45883 | Y14: 09:00 AM to 11:00 AM
A15: https://utrucking.com/admin/orders/5899278713020 | B15: #15242 | C15: samanthar@wustl.edu | D15: 3124809444 | E15: Jonathan Rosenberg | G15: Highland Park | H15: Illinois | I15: 60035 | J15: United States | K15: Appliance Rental | L15: Double-Door Mini Fridge + Microwave | M15: 210 | O15: 3321 | P15: 45883 | U15: Danforth | V15: 3321 | X15: 45883
A16: https://utrucking.com/admin/orders/5899279007932 | B16: #15243 | C16: washko@wustl.edu | D16: 8573600811 | E16: William Washko | G16: West Roxbury | H16: Massachusetts | I16: 2132 | J16: United States | K16: Nationwide Ship to School | L16: Nationwide Ship to School | M16: 49 | N16: University Housing | O16: 1084 - a | P16: 45883 | Q16: 09:00 AM to 11:00 AM | T16: University Housing | U16: Eliot A | V16: 1084 - a | X16: 45883 | Y16: 09:00 AM to 11:00 AM
A17: https://utrucking.com/admin/orders/5899315642556 | B17: #15244 | D17: 9788061822 | E17: Emily Kobelski | G17: Andover | H17: Massachusetts | I17: 1810 | J17: United States | K17: Storage Item Return | M17: 1 | N17: University Housing | O17: 4160 | P17: 45890 | Q17: 09:00 AM to 11:00 AM | T17: University Housing | U17: Village House | V17: 4160 | X17: 45890 | Y17: 09:00 AM to 11:00 AM
A18: https://utrucking.com/admin/orders/5899375313084 | B18: #15245 | D18: 6504683885 | E18: jackie shurslep | G18: Larchmont | H18: New York | I18: 10538 | J18: United States | K18: Appliance Rental | L18: Double-Door Mini Fridge | M18: 145 | O18: 1116 | P18: 45883 | U18: Lien | V18: 1116 | X18: 45883
A19: https://utrucking.com/admin/orders/5899380981948 | B19: #15246 | C19: h.serene@wustl.edu | D19: 6788767305 | E19: Erica Harris | G19: Lawrenceville | H19: Georgia | I19: 30043 | J19: United States | K19: Storage Item Return | M19: 1 | N19: University Housing | O19: 210 | P19: 45891 | Q19: 09:00 AM to 11:00 AM | T19: University Housing | U19: House 1 (Alpha Delta Phi) | V19: 210 | X19: 45891 | Y19: 09:00 AM to 11:00 AM
A20: https://utrucking.com/admin/orders/5899380981948 | B20: #15246 | C20: h.serene@wustl.edu | D20: 6788767305 | E20: Erica Harris | G20: Lawrenceville | H20: Georgia | I20: 30043 | J20: United States | K20: Appliance Rental | L20: Double-Door Mini Fridge + Microwave | M20: 210 | O20: 210 | P20: 45883 | U20: House 1 (Alpha Delta Phi) | V20: 210 | X20: 45883
A21: https://utrucking.com/admin/orders/5899398512828 | B21: #15247 | C21: atticks@wustl.edu | D21: 14104994906 | E21: Andrea Atticks | G21: Cockeysville | H21: Maryland | I21: 21030-1724 | J21: United States | K21: Appliance Rental | L21: Double-Door Mini Fridge + Microwave | M21: 210 | O21: 1112 | P21: 45883 | U21: Koenig | V21: 1112 | X21: 45883
A22: https://utrucking.com/admin/orders/5899539480764 | B22: #15248 | C22: marci_sherman@hotmail.com | E22: Marci Rosenblatt | G22: Lafayette | H22: Missouri | I22: 94549 | J22: United States | K22: Nationwide Ship to School | L22: Nationwide Ship to School | M22: 49 | N22: University Housing | O22: 441b | P22: 45883 | Q22: 09:00 AM to 11:00 AM | T22: University Housing | U22: Park | V22: 441b | X22: 45883 | Y22: 09:00 AM to 11:00 AM
A23: https://utrucking.com/admin/orders/5899755684028 | B23: #15250 | C23: mhwtan@gmail.com | D23: 3106061350 | E23: Tan 18 Misty Acres Rd | G23: United States | H23: California | I23: 90274 | J23: United States | K23: Appliance Rental | L23: Double-Door Mini Fridge | M23: 145 | O23: 2208 | P23: 45883 | U23: Dardick | V23: 2208 | X23: 45883
A24: https://utrucking.com/admin/orders/5899777736892 | B24: #15251 | C24: g.lanzillo@wustl.edu | D24: 3022334790 | E24: Gemma Lanzillo | G24: Stafford | H24: Virginia | I24: 22554 | J24: United States | K24: Storage Item Return | M24: 1 | N24: University Housing | O24: 2052-a | P24: 45883 | Q24: 09:00 AM to 11:00 AM | T24: University Housing | U24: Shepley | V24: 2052-a | X24: 45883 | Y24: 09:00 AM to 11:00 AM
A25: https://utrucking.com/admin/orders/5899791564988 | B25: #15252 | C25: fike@wustl.edu | D25: 7737441350 | E25: Lisa Fike | G25: Plainfield | H25: Illinois | I25: 60585 | J25: United States | K25: Appliance Rental | L25: Double-Door Mini Fridge | M25: 145 | O25: 4032 | P25: 45883 | U25: Wheeler | V25: 4032 | X25: 45883
A26: https://utrucking.com/admin/orders/5899837145276 | B26: #15253 | C26: lisapetlak@hotmail.com | D26: 13103673106 | E26: Lisa Petlak | G26: Los Angeles | H26: California | I26: 90035-3218 | J26: United States | K26: Appliance Rental | L26: Double-Door Mini Fridge + Microwave | M26: 210 | O26: 3305 | P26: 45883 | U26: Dardick | V26: 3305 | X26: 45883
A27: https://utrucking.com/admin/orders/5900006424764 | B27: #15254 | D27: 7033109100 | E27: Emily Pocrass | F27: 1870 Patrick Henry Drive | G27: Arlington | H27: Virginia | I27: 22205 | J27: United States | K27: Appliance Rental | L27: Double-Door Mini Fridge + Microwave | M27: 210 | O27: 232 | P27: 45883 | U27: Umrath | V27: 232 | X27: 45883
A28: https://utrucking.com/admin/orders/5900080283836 | B28: #15255 | C28: lorieclassner@gmail.com | D28: 3107019782 | E28: Ethan Lassner | F28: 13548 Valley Vista Boulevard | G28: Sherman Oaks | H28: California | I28: 91423 | J28: United States | K28: Appliance Rental | L28: Double-Door Mini Fridge + Microwave | M28: 210 | O28: 1082-a | P28: 45883 | U28: Eliot A | V28: 1082-a | X28: 45883
A29: https://utrucking.com/admin/orders/5900080283836 | B29: #15255 | C29: lorieclassner@gmail.com | D29: 3107019782 | E29: Ethan Lassner | F29: 13548 Valley Vista Boulevard | G29: Sherman Oaks | H29: California | I29: 91423 | J29: United States | K29: Nationwide Ship to School | L29: Nationwide Ship to School | M29: 49 | N29: University Housing | O29: 1082-a | P29: 45883 | Q29: 09:00 AM to 11:00 AM | T29: University Housing | U29: Eliot A | V29: 1082-a | X29: 45883 | Y29: 09:00 AM to 11:00 AM
A30: https://utrucking.com/admin/orders/5900083265724 | B30: #15256 | C30: b.e.veiel@wustl.edu | D30: 4102586632 | E30: Lori Veiel | F30: 448 Arundel Beach Road | G30: Severna Park | H30: Maryland | I30: 21146 | J30: United States | K30: Appliance Rental | L30: Double-Door Mini Fridge | M30: 145 | O30: 3373-a | P30: 45883 | U30: Liggett | V30: 3373-a | X30: 45883
A31: https://utrucking.com/admin/orders/5900089852092 | B31: #15257 | C31: hgrossman05@gmail.com | D31: 12013100288 | E31: Harrison Grossman | F31: 17019 Brookwood Dr | G31: Boca Raton | H31: Florida | I31: 33496 | J31: United States | K31: Storage Item Return | M31: 1 | N31: Non-University Housing | P31: 45871 | Q31: 11:00 AM to 01:00 PM | T31: Non-University Housing | X31: 45871 | Y31: 11:00 AM to 01:00 PM | AA31: 100 N Kingshighway Blvd St Louis MO 63108
A32: https://utrucking.com/admin/orders/5900123701436 | B32: #15259 | C32: katiemeggers@gmail.com | D32: 17148848990 | E32: Julie Meggers | F32: 1815 Port Ashley Place | G32: Newport Beach | H32: California | I32: 92660-5337 | J32: United States | K32: Nationwide Ship to School | L32: Nationwide Ship to School | M32: 49 | N32: University Housing | O32: L230-a | P32: 45883 | Q32: 09:00 AM to 11:00 AM | T32: University Housing | U32: Umrath | V32: L230-a | X32: 45883 | Y32: 09:00 AM to 11:00 AM
A33: https://utrucking.com/admin/orders/5900123734204 | B33: #15260 | C33: j.todfield118@gmail.com | D33: 19178821115 | E33: Jamie pastrano | F33: 70 Little West StApt 24F | G33: New York | H33: New York | I33: 10004 | J33: United States | K33: Tri-State Area Home Pickups | M33: 49 | N33: University Housing | O33: 3309-a | P33: 45883 | T33: University Housing | U33: Dardick | V33: 3309-a | X33: 45883 | Z33: $100 per item [Included]
A34: https://utrucking.com/admin/orders/5900186910908 | B34: #15263 | C34: allisonstern@hotmail.com | D34: 3102463451 | E34: Allison Samek | F34: 498 South Spalding Drive | G34: Beverly Hills | H34: California | I34: 90212 | J34: United States | K34: Appliance Rental | L34: Double-Door Mini Fridge + Microwave | M34: 210 | O34: 219A | P34: 45883 | U34: Lee | V34: 219A | X34: 45883
A35: https://utrucking.com/admin/orders/5900228886716 | B35: #15264 | C35: chanel7557@yahoo.com | D35: 3123440050 | E35: Chanel Bell | F35: 705 McCardle Drive | G35: West Chester | H35: Pennsylvania | I35: 19380 | J35: United States | K35: Appliance Rental | L35: Microwave Only | M35: 65 | O35: 2220 | P35: 45883 | U35: Lien | V35: 2220 | X35: 45883
A36: https://utrucking.com/admin/orders/5900252807356 | B36: #15265 | C36: walkerfamilycinco@yahoo.com | D36: 9193338112 | E36: Layla Walker | F36: 1900 Fieldstone Way | G36: Frederick | H36: Maryland | I36: 21702 | J36: United States | K36: Nationwide Ship to School | L36: Nationwide Ship to School | M36: 49 | N36: University Housing | O36: 491A | P36: 45883 | Q36: 09:00 AM to 11:00 AM | T36: University Housing | U36: Park | V36: 491A | X36: 45883 | Y36: 09:00 AM to 11:00 AM
A37: https://utrucking.com/admin/orders/5900316573884 | B37: #15266 | C37: p.rex@wustl.edu | D37: 2242163846 | E37: Rex Paster | F37: 305 Grove Street | G37: Glencoe | H37: Illinois | I37: 60022 | J37: United States | K37: Appliance Rental | L37: Standard Mini Fridge | M37: 115 | O37: 3339 | P37: 45852 | U37: Umrath | V37: 3339 | X37: 45852
A38: https://utrucking.com/admin/orders/5900318474428 | B38: #15267 | D38: 9177707102 | E38: stacey zoland | F38: 9 foxhall place | G38: scarsdale | H38: New York | I38: 10583 | J38: United States | K38: Appliance Rental | L38: Double-Door Mini Fridge + Microwave | M38: 210 | O38: 133-a | P38: 45883 | U38: Dauten | V38: 133-a | X38: 45883
A39: https://utrucking.com/admin/orders/5900342067388 | B39: #15268 | C39: d.mingyue@wustl.edu | D39: 13144377750 | E39: Mingyue Ding | F39: 6985 Snow Way Drive | G39: St. Louis | H39: Missouri | I39: 63130 | J39: United States | K39: Storage Item Return | M39: 1 | N39: University Housing | O39: 209 - a | P39: 45883 | Q39: 09:00 AM to 11:00 AM | T39: University Housing | U39: House 1 (Alpha Delta Phi) | V39: 209 - a | X39: 45883 | Y39: 09:00 AM to 11:00 AM
A40: https://utrucking.com/admin/orders/5900610175164 | B40: #15269 | C40: sophia.hasan@icloud.com | D40: 7082505700 | E40: Sophia Hasan | F40: 111 Singletree Road | G40: Orland Park | H40: Illinois | I40: 60467 | J40: United States | K40: Nationwide Ship to School | L40: Nationwide Ship to School | M40: 49 | N40: University Housing | O40: 309 | P40: 45883 | Q40: 09:00 AM to 11:00 AM | T40: University Housing | U40: Lee | V40: 309 | X40: 45883 | Y40: 09:00 AM to 11:00 AM
A41: https://utrucking.com/admin/orders/5900653166780 | B41: #15270 | C41: rwsolovy@yahoo.com | D41: 3016516144 | E41: Rebecca Solovy | F41: 4504 Windsor Lane | G41: Bethesda | H41: Maryland | I41: 20814 | J41: United States | K41: Appliance Rental | L41: Double-Door Mini Fridge + Microwave | M41: 210 | O41: 1236-b | P41: 45883 | U41: Umrath | V41: 1236-b | X41: 45883
A42: https://utrucking.com/admin/orders/5900679708860 | B42: #15271 | D42: 19179005487 | E42: Jara Shapiro | F42: 6322 Alcott Road | G42: Bethesda | H42: Maryland | I42: 20817 | J42: United States | K42: Nationwide Ship to School | L42: Nationwide Ship to School | M42: 49 | N42: Non-University Housing | P42: 45877 | Q42: 09:00 AM to 11:00 AM | T42: Non-University Housing | X42: 45877 | Y42: 09:00 AM to 11:00 AM | AA42: 7024 Forsyth Blvd, Apt 1E- Back room
A43: https://utrucking.com/admin/orders/5900705693884 | B43: #15272 | D43: 17812235035 | E43: Emily Perlis | F43: 609 Braeburn Ln | G43: Penn Valley | H43: Pennsylvania | I43: 19072 | J43: United States | K43: Appliance Rental | L43: Standard Mini Fridge | M43: 115 | O43: 414 | P43: 45883 | U43: Dauten | V43: 414 | X43: 45883
A44: https://utrucking.com/admin/orders/5900706185404 | B44: #15273 | D44: 3475702616 | E44: Natalie Glassie | F44: 6235 Southwood Avenue | G44: St. Louis | H44: Missouri | I44: 63105 | J44: United States | K44: Tri-State Area Home Pickups | M44: 49 | N44: Non-University Housing | P44: 45879 | Q44: 09:00 AM to 11:00 AM | T44: Non-University Housing | X44: 45879 | Y44: 09:00 AM to 11:00 AM | Z44: $100 per item [Included]
A45: https://utrucking.com/admin/orders/5900738887868 | B45: #15274 | D45: 19175922703 | E45: Samantha Jacknis | F45: 79 High Street | G45: East Williston County | H45: New York | I45: 11596 | J45: United States | K45: Tri-State Area Home Pickups | M45: 49 | N45: University Housing | O45: 232A | P45: 45883 | T45: University Housing | U45: Hitzeman | V45: 232A | X45: 45883 | Z45: $100 per item [Included]
A46: https://utrucking.com/admin/orders/5900755337404 | B46: #15275 | C46: orbucho2006@gmail.com | D46: 9177326364 | E46: Olivia Orbuch | F46: 1723 s corning street | G46: Los Angles | H46: California | I46: 90035 | J46: United States | K46: Storage Item Return | M46: 1 | N46: ﻿﻿ Non-University Housing | P46: 45875 | Q46: 12:00 PM to 02:00 PM | R46: 7036 Forsyth Blvd | T46: Non-University Housing | X46: 45875 | Y46: 12:00 PM to 02:00 PM | AA46: 7036 Forsyth Blvd | AB46: Non-University Housing
A47: https://utrucking.com/admin/orders/5900791414972 | B47: #15276 | C47: g.kogan@wustl.edu | D47: 19146026240 | E47: Gabrielle Kogan | F47: 39 Orchard Hill Rd | G47: Katonah | H47: New York | I47: 10536 | J47: United States | K47: Appliance Rental | L47: Double-Door Mini Fridge + Microwave | M47: 210 | N47: ﻿﻿ | O47: 321 | P47: 45876 | U47: Beaumont | V47: 321 | X47: 45876
A48: https://utrucking.com/admin/orders/5900791414972 | B48: #15276 | C48: g.kogan@wustl.edu | D48: 19146026240 | E48: Gabrielle Kogan | F48: 39 Orchard Hill Rd | G48: Katonah | H48: New York | I48: 10536 | J48: United States | K48: Storage Item Return | M48: 1 | N48: ﻿﻿ University Housing | O48: 321 | P48: 45876 | Q48: 09:00 AM to 11:00 AM | T48: University Housing | U48: Beaumont | V48: 321 | X48: 45876 | Y48: 09:00 AM to 11:00 AM | AB48: University Housing
A49: https://utrucking.com/admin/orders/5900814680252 | B49: #15277 | D49: 9179217228 | E49: lloyd mallah | F49: 17 Birch Lane | G49: Rye Brook | H49: New York | I49: 10573 | J49: United States | K49: Storage Item Return | M49: 1 | N49: ﻿﻿ Non-University Housing | P49: 45888 | Q49: 03:00 PM to 05:00 PM | R49: 6843 Kingsbury Blvd Apartment 1E St. Louis, MO 63130 | T49: Non-University Housing | X49: 45888 | Y49: 03:00 PM to 05:00 PM | AA49: 6843 Kingsbury Blvd Apartment 1E St. Louis, MO 63130 | AB49: Non-University Housing
A50: https://utrucking.com/admin/orders/5900867436732 | B50: #15278 | C50: rebeccaburack@gmail.com | D50: 16178996835 | E50: Rebecca Burack | F50: 76 Bellevue Street | G50: Newton | H50: Massachusetts | I50: 2458 | J50: United States | K50: Appliance Rental | L50: Double-Door Mini Fridge | M50: 145 | N50: ﻿﻿ | O50: 4408 | P50: 45882 | U50: Dardick | V50: 4408 | X50: 45882
A51: https://utrucking.com/admin/orders/5900873597116 | B51: #15279 | D51: 3476344188 | E51: Lindsay Fauntleroy | F51: 423 River Mews Ln | G51: Edgewater | H51: New Jersey | I51: 7020 | J51: United States | K51: Nationwide Ship to School | L51: Nationwide Ship to School | M51: 49 | N51: ﻿﻿ University Housing | O51: XXX | P51: 45883 | Q51: 09:00 AM to 11:00 AM | T51: University Housing | U51: DON'T KNOW YET (put 'XXX' for room #) | V51: XXX | X51: 45883 | Y51: 09:00 AM to 11:00 AM | AB51: University Housing
A52: https://utrucking.com/admin/orders/5900916162748 | B52: #15280 | D52: 19175848891 | E52: Daria Reznikova | F52: 35 West 71st Street | G52: New York | H52: New York | I52: 10023 | J52: United States | K52: Tri-State Area Home Pickups | M52: 49 | N52: ﻿﻿ University Housing | O52: 222A | P52: 45883 | T52: University Housing | U52: Hitzeman | V52: 222A | X52: 45883 | Z52: $100 per item [Included] | AB52: University Housing
A53: https://utrucking.com/admin/orders/5900932972732 | B53: #15281 | D53: 7817086694 | E53: Abigail Carlo | F53: 27 Salisbury Drive | G53: Westwood | H53: Massachusetts | I53: 2090 | J53: United States | K53: Nationwide Ship to School | L53: Nationwide Ship to School | M53: 49 | N53: ﻿﻿ University Housing | O53: 424B | P53: 45883 | Q53: 09:00 AM to 11:00 AM | T53: University Housing | U53: Hurd | V53: 424B | X53: 45883 | Y53: 09:00 AM to 11:00 AM | AB53: University Housing | AC53: Abigail Carlo, 27 Salisbury Drive, Westwood, MA 02090
A54: https://utrucking.com/admin/orders/5900954435772 | B54: #15282 | D54: 6467348680 | E54: Leah Shandler | F54: 271 Fox Meadow Rd | G54: Scarsdale | H54: New York | I54: 10583 | J54: United States | K54: Appliance Rental | L54: Double-Door Mini Fridge + Microwave | M54: 210 | N54: ﻿﻿ | O54: 232-b | P54: 45883 | U54: Hitzeman | V54: 232-b | X54: 45883
A55: https://utrucking.com/admin/orders/5900954435772 | B55: #15282 | D55: 6467348680 | E55: Leah Shandler | F55: 271 Fox Meadow Rd | G55: Scarsdale | H55: New York | I55: 10583 | J55: United States | K55: Tri-State Area Home Pickups | M55: 49 | N55: ﻿﻿ University Housing | O55: 232-b | P55: 45883 | T55: University Housing | U55: Hitzeman | V55: 232-b | X55: 45883 | Z55: $100 per item [Included] | AB55: University Housing
A56: https://utrucking.com/admin/orders/5900996706492 | B56: #15283 | C56: susanschober@comcast.net | D56: 3128041544 | E56: Susan Schober | F56: 1714 Asbury Avenue | G56: Evanston | H56: Illinois | I56: 60201 | J56: United States | K56: Appliance Rental | L56: Double-Door Mini Fridge + Microwave | M56: 210 | N56: ﻿﻿ | O56: 2234 | P56: 45883 | U56: Umrath | V56: 2234 | X56: 45883
A57: https://utrucking.com/admin/orders/5901001392316 | B57: #15284 | C57: talykaplan@gmail.com | D57: 2014077071 | E57: Taly Kaplan | F57: 18 Rene Drive | G57: Marlboro | H57: New Jersey | I57: 7746 | J57: United States | K57: Appliance Rental | L57: Double-Door Mini Fridge + Microwave | M57: 210 | N57: ﻿﻿ | O57: 3081 | P57: 45852 | U57: House 21 (Alpha Epsilon Pi) | V57: 3081 | X57: 45852
A58: https://utrucking.com/admin/orders/5901019447484 | B58: #15285 | C58: phweinberg@yahoo.com | D58: 19173480983 | E58: Philip Weinberg | F58: 12 Annette Way Jericho, NY | G58: Jericho | H58: New York | I58: 11753 | J58: United States | K58: Tri-State Area Home Pickups | M58: 49 | N58: ﻿﻿ University Housing | O58: 3160 A | P58: 45887 | T58: University Housing | U58: Zetcher | V58: 3160 A | X58: 45887 | Z58: $100 per item [Included] | AB58: University Housing
A59: https://utrucking.com/admin/orders/5901064863932 | B59: #15286 | C59: freedman.g@wustl.edu | D59: 3109229448 | E59: Gabriel Freedman | F59: 526 North Saltair Avenue | G59: Los Angeles | H59: California | I59: 90049 | J59: United States | K59: Storage Item Return | M59: 1 | N59: ﻿﻿ University Housing | O59: 305 | P59: 45883 | Q59: 09:00 AM to 11:00 AM | T59: University Housing | U59: House 6 (Sigma Alpha Epsilon) | V59: 305 | X59: 45883 | Y59: 09:00 AM to 11:00 AM | AB59: University Housing
A60: https://utrucking.com/admin/orders/5901173391548 | B60: #15287 | C60: gabiphillips06@gmail.com | D60: 5038100524 | E60: Elizabeth Phillips | F60: 6136 SW Luradel St | G60: Portland | H60: Oregon | I60: 97219 | J60: United States | K60: Appliance Rental | L60: Double-Door Mini Fridge + Microwave | M60: 210 | N60: ﻿﻿ | O60: 142 | P60: 45883 | U60: Hitzeman | V60: 142 | X60: 45883
A61: https://utrucking.com/admin/orders/5901478101180 | B61: #15288 | C61: sophia.hasan@icloud.com | D61: 17082505700 | E61: Sophia Hasan | F61: 111 Singletree Road | G61: Orland Park | H61: Illinois | I61: 60467 | J61: United States | K61: Appliance Rental | L61: Double-Door Mini Fridge + Microwave | M61: 210 | N61: ﻿﻿ | O61: 309 | P61: 45883 | U61: Lee | V61: 309 | X61: 45883
A62: https://utrucking.com/admin/orders/5901515456700 | B62: #15289 | C62: n.samson@wustl.edu | D62: 9176052406 | E62: Arthur Nwobi | F62: 347 Hawthorne Avenue | G62: Newark | H62: New Jersey | I62: 7112 | J62: United States | K62: Appliance Rental | L62: Standard Mini Fridge | M62: 115 | N62: ﻿﻿ | O62: 111 | P62: 45852 | U62: Hurd | V62: 111 | X62: 45852
A63: https://utrucking.com/admin/orders/5901577748668 | B63: #15290 | D63: 7046920035 | E63: Cherie Sidhu | F63: 1420 Stone Gate Dr | G63: Shelby | H63: North Carolina | I63: 28150 | J63: United States | K63: Storage Item Return | M63: 1 | N63: ﻿﻿ University Housing | O63: 3053 | P63: 45876 | Q63: 01:00 PM to 03:00 PM | T63: University Housing | U63: Nemerov | V63: 3053 | X63: 45876 | Y63: 01:00 PM to 03:00 PM | AB63: University Housing
A64: https://utrucking.com/admin/orders/5901603799228 | B64: #15291 | C64: talykaplan@gmail.com | D64: 12014077071 | E64: Taly Kaplan | F64: 18 Rene Drive | G64: Marlboro | H64: New Jersey | I64: 7746 | J64: United States | K64: Storage Item Return | M64: 1 | N64: ﻿﻿ University Housing | O64: 3081 | P64: 45883 | Q64: 12:00 PM to 02:00 PM | T64: University Housing | U64: House 21 (Alpha Epsilon Pi) | V64: 3081 | X64: 45883 | Y64: 12:00 PM to 02:00 PM | AB64: University Housing
A65: https://utrucking.com/admin/orders/5901666615484 | B65: #15292 | D65: 6176595918 | E65: Barbara Hirsch | F65: 12 Hamilton Rd | G65: Wellesley | H65: Massachusetts | I65: 2482 | J65: United States | K65: Appliance Rental | L65: Standard Mini Fridge + Microwave | M65: 180 | N65: ﻿﻿ | O65: 2207 | P65: 45883 | U65: Dardick | V65: 2207 | X65: 45883
A66: https://utrucking.com/admin/orders/5901762691260 | B66: #15293 | D66: 6463198706 | E66: Ian Shurslep | G66: Larchmont | H66: New York | I66: 10538 | J66: United States | K66: Storage Item Return | M66: 1 | N66: University Housing | O66: 304C (Moving in on 17th) | P66: 45882 | Q66: 11:00 AM to 01:00 PM | S66: University Housing | T66: University Housing | U66: Millbrook Bldg. 4 | V66: 304C (Moving in on 17th) | X66: 45882 | Y66: 11:00 AM to 01:00 PM | AB66: University Housing
A67: https://utrucking.com/admin/orders/5901819445436 | B67: #15294 | C67: jamesopollack@gmail.com | D67: 19176897822 | E67: James Pollack | G67: New York | H67: New York | I67: 10025 | J67: United States | K67: Appliance Rental | L67: Double-Door Mini Fridge + Microwave | M67: 210 | O67: 3104 | P67: 45883 | U67: Wheeler | V67: 3104 | X67: 45883
A68: https://utrucking.com/admin/orders/5901819445436 | B68: #15294 | C68: jamesopollack@gmail.com | D68: 19176897822 | E68: James Pollack | G68: New York | H68: New York | I68: 10025 | J68: United States | K68: Tri-State Area Home Pickups | M68: 49 | N68: University Housing | O68: 3104 | P68: 45883 | S68: University Housing | T68: University Housing | U68: Wheeler | V68: 3104 | X68: 45883 | Z68: $100 per item [Included] | AB68: University Housing
A69: https://utrucking.com/admin/orders/5901823344828 | B69: #15295 | C69: abergel@wustl.edu | D69: 8622122755 | E69: Noa Abergel | G69: Livingston | H69: New Jersey | I69: 7039 | J69: United States | K69: Tri-State Area Home Pickups | M69: 49 | N69: University Housing | O69: 4427-b | P69: 45883 | S69: University Housing | T69: University Housing | U69: Danforth | V69: 4427-b | X69: 45883 | Z69: $100 per item [Included] | AB69: University Housing
A70: https://utrucking.com/admin/orders/5902055866556 | B70: #15296 | C70: jungmin.yu@gmail.com | D70: 6502247807 | E70: Jungmin Yu | G70: Los Altos | H70: California | I70: 94022 | J70: United States | K70: Appliance Rental | L70: Standard Mini Fridge | M70: 115 | O70: 4405-a | P70: 45883 | U70: Koenig | V70: 4405-a | X70: 45883
A71: https://utrucking.com/admin/orders/5902234190012 | B71: #15297 | C71: ethannus07@gmail.com | D71: 9176131752 | E71: Ethan Nus | G71: Hewlett | H71: New York | I71: 11557 | J71: United States | K71: Tri-State Area Home Pickups | M71: 49 | N71: University Housing | O71: 4428 | P71: 45883 | S71: University Housing | T71: University Housing | U71: Umrath | V71: 4428 | X71: 45883 | Z71: $100 per item [Included] | AB71: University Housing
A72: https://utrucking.com/admin/orders/5902261616828 | B72: #15298 | D72: 9143296359 | E72: Sydney Starkey | G72: Sleepy Hollow | H72: New York | I72: 10591 | J72: United States | K72: Tri-State Area Home Pickups | M72: 49 | N72: University Housing | O72: 124 B | P72: 45883 | S72: University Housing | T72: University Housing | U72: Rutledge | V72: 124 B | X72: 45883 | Z72: $100 per item [Included] | AB72: University Housing
A73: https://utrucking.com/admin/orders/5902266269884 | B73: #15299 | D73: 16787360144 | E73: Michael Menis | G73: Dunwody | H73: Georgia | I73: 30338 | J73: United States | K73: Nationwide Ship to School | L73: Nationwide Ship to School | M73: 49 | N73: University Housing | O73: XXX | P73: 45883 | Q73: 11:00 AM to 01:00 PM | S73: University Housing | T73: University Housing | U73: Dardick | V73: XXX | X73: 45883 | Y73: 11:00 AM to 01:00 PM | AB73: University Housing | AC73: 5267 Lakesprings Dr Dunwoody GA, 30338
A74: https://utrucking.com/admin/orders/5902278230204 | B74: #15300 | C74: tylero87@icloud.com | D74: 5169455306 | E74: Tyler Osit | G74: Roslyn | H74: New York | I74: 11576 | J74: United States | K74: Appliance Rental | L74: Double-Door Mini Fridge + Microwave | M74: 210 | O74: 241 a | P74: 45883 | U74: Rutledge | V74: 241 a | X74: 45883
A75: https://utrucking.com/admin/orders/5902278230204 | B75: #15300 | C75: tylero87@icloud.com | D75: 5169455306 | E75: Tyler Osit | G75: Roslyn | H75: New York | I75: 11576 | J75: United States | K75: Tri-State Area Home Pickups | M75: 49 | N75: University Housing | O75: 241 a | P75: 45883 | S75: University Housing | T75: University Housing | U75: Rutledge | V75: 241 a | X75: 45883 | Z75: $100 per item [Included] | AB75: University Housing | AD75: 46 Flamingo Road Roslyn New York
A76: https://utrucking.com/admin/orders/5902403600572 | B76: #15302 | C76: jenrussellpdx@gmail.com | D76: 15033604485 | E76: Jen Russell | F76: 4239 NW Twilight Terrace | G76: Portland | H76: Oregon | I76: 97229 | J76: United States | K76: Nationwide Ship to School | L76: Nationwide Ship to School | M76: 49 | N76: University Housing | O76: xxx | P76: 45883 | Q76: 09:00 AM to 11:00 AM | S76: University Housing | T76: University Housing | U76: DON'T KNOW YET (put 'XXX' for room #) | V76: xxx | X76: 45883 | Y76: 09:00 AM to 11:00 AM | AB76: University Housing | AC76: 4239 NW Twilight Terrace Portland OR 97229
A77: https://utrucking.com/admin/orders/5902510555324 | B77: #15303 | C77: jshurslep@gmail.com | D77: 6504683885 | E77: jackie Shurslep | F77: 34 Beach Ave | G77: Larchmont | H77: New York | I77: 10538-4002 | J77: United States | K77: Tri-State Area Home Pickups | M77: 49 | N77: University Housing | O77: 1116 | P77: 45883 | S77: University Housing | T77: University Housing | U77: Lien | V77: 1116 | X77: 45883 | Z77: $100 per item [Included] | AB77: University Housing | AD77: 34 beach avenue larchmont, ny 10538
A78: https://utrucking.com/admin/orders/5902522712252 | B78: #15304 | C78: brigidomatt@gmail.com | D78: 4087698958 | E78: Matthew Brigido | F78: 1059 Reed Avenue | G78: Sunnyvale | H78: California | I78: 94086 | J78: United States | K78: Nationwide Ship to School | L78: Nationwide Ship to School | M78: 49 | N78: University Housing | O78: 306C | P78: 45883 | Q78: 09:00 AM to 11:00 AM | S78: University Housing | T78: University Housing | U78: Loop Loft 6263 | V78: 306C | X78: 45883 | Y78: 09:00 AM to 11:00 AM | AB78: University Housing | AC78: 1059 Reed Ave. Apt. 18, Sunnyvale, CA, 94086
A79: https://utrucking.com/admin/orders/5902640742588 | B79: #15307 | C79: rubinshulie@gmail.com | D79: 9176737555 | E79: Shulie Hochstadt | G79: Englewood | H79: New Jersey | I79: 7631 | J79: United States | K79: Tri-State Area Home Pickups | M79: 49 | N79: University Housing | O79: 2222 | P79: 45883 | S79: University Housing | T79: University Housing | U79: Dardick | V79: 2222 | X79: 45883 | Z79: $100 per item [Included] | AB79: University Housing | AD79: 127 Walnut Street Englewood NJ 07631
A80: https://utrucking.com/admin/orders/5902691008700 | B80: #15308 | C80: rickyudell@wustl.edu | D80: 2152871001 | E80: Michael Yudell | G80: Scottsdale | H80: Arizona | I80: 85258 | J80: United States | K80: Appliance Rental | L80: Double-Door Mini Fridge | M80: 145 | O80: 331 | P80: 45883 | U80: Myers | V80: 331 | X80: 45883
A81: https://utrucking.com/admin/orders/5902695235772 | B81: #15309 | C81: ndecherney@gmail.com | D81: 6504749188 | E81: Natalie DeCherney | G81: Portola Valley | H81: California | I81: 94028 | J81: United States | K81: Appliance Rental | L81: Double-Door Mini Fridge + Microwave | M81: 210 | O81: 1239 | P81: 45883 | U81: Umrath | V81: 1239 | X81: 45883
A82: https://utrucking.com/admin/orders/5902760837308 | B82: #15310 | C82: savannahmck06@gmail.com | D82: 17013502434 | E82: savannah mckay | G82: Devils Lake | H82: North Dakota | I82: 58301 | J82: United States | K82: Nationwide Ship to School | L82: Nationwide Ship to School | M82: 49 | N82: University Housing | O82: 1238a | P82: 45883 | Q82: 09:00 AM to 11:00 AM | S82: University Housing | T82: University Housing | U82: Umrath | V82: 1238a | X82: 45883 | Y82: 09:00 AM to 11:00 AM | AB82: University Housing | AC82: 407 Walford Avenue Devils Lake ND 58301
A83: https://utrucking.com/admin/orders/5902817329340 | B83: #15311 | C83: navelisingh123@gmail.com | D83: 6504005711 | E83: Naveli Singh | G83: Los Altos Hills | H83: California | I83: 94024 | J83: United States | K83: Appliance Rental | L83: Double-Door Mini Fridge + Microwave | M83: 210 | O83: 481 | P83: 45883 | U83: Park | V83: 481 | X83: 45883
A84: https://utrucking.com/admin/orders/5902876213436 | B84: #15312 | C84: ricardo_balazs@hotmail.com | D84: 4155399004 | E84: Zak Balazs | G84: San Francisco | H84: California | I84: 94114 | J84: United States | K84: Nationwide Ship to School | L84: Nationwide Ship to School | M84: 49 | N84: University Housing | O84: 3304-A | P84: 45883 | Q84: 09:00 AM to 11:00 AM | S84: University Housing | T84: University Housing | U84: Danforth | V84: 3304-A | X84: 45883 | Y84: 09:00 AM to 11:00 AM | AB84: University Housing | AC84: 4660 19th Street San Francisco, CA 94114
A85: https://utrucking.com/admin/orders/5903142879420 | B85: #15313 | C85: a.gittleman@icloud.com | D85: 2154352030 | E85: Reese Gittleman | G85: Lafayette HIll | H85: Pennsylvania | I85: 19444 | J85: United States | K85: Nationwide Ship to School | L85: Nationwide Ship to School | M85: 49 | N85: University Housing | O85: 112-b | P85: 45883 | Q85: 09:00 AM to 11:00 AM | S85: University Housing | T85: University Housing | U85: Hitzeman | V85: 112-b | X85: 45883 | Y85: 09:00 AM to 11:00 AM | AB85: University Housing | AC85: 682 Cherrydale Drive, Lafayette Hill, PA 19444
A86: https://utrucking.com/admin/orders/5903255830716 | B86: #15314 | C86: suri@kasirer.nyc | D86: 9178484128 | E86: Suri Kasirer | G86: New York | H86: New York | I86: 10023 | J86: United States | K86: Tri-State Area Home Pickups | M86: 49 | N86: University Housing | O86: Lee-212-b | P86: 45852 | S86: University Housing | T86: University Housing | U86: Lee | V86: Lee-212-b | X86: 45852 | Z86: $100 per item [Included] | AB86: University Housing | AD86: 150 Columbus Ave, NY, NY 10023
A87: https://utrucking.com/admin/orders/5903311896764 | B87: #15315 | C87: shan.knisely@gmail.com | D87: 15126995645 | E87: Ashton Knisely | G87: Austin | H87: Texas | I87: 78731 | J87: United States | K87: Nationwide Ship to School | L87: Nationwide Ship to School | M87: 49 | N87: University Housing | O87: 314 -B | P87: 45883 | Q87: 09:00 AM to 11:00 AM | S87: University Housing | T87: University Housing | U87: Rutledge | V87: 314 -B | X87: 45883 | Y87: 09:00 AM to 11:00 AM | AB87: University Housing | AC87: 7801 Heathercrest Circle Austin, Tx. 78731
A88: https://utrucking.com/admin/orders/5903455486140 | B88: #15316 | C88: Jksand2025@gmail.com | D88: 9192687045 | E88: Jaden Sanders | G88: Wendell | H88: North Carolina | I88: 27591 | J88: United States | K88: Nationwide Ship to School | L88: Nationwide Ship to School | M88: 49 | N88: University Housing | O88: 4423 - a | P88: 45883 | Q88: 09:00 AM to 11:00 AM | S88: University Housing | T88: University Housing | U88: Dardick | V88: 4423 - a | X88: 45883 | Y88: 09:00 AM to 11:00 AM | AB88: University Housing | AC88: 1737 Iron Mill Dr. Wendell, NC 27591
A89: https://utrucking.com/admin/orders/5903479177404 | B89: #15317 | C89: rpallera@comcast.net | D89: 19014977219 | E89: Robyn Pallera | G89: collierville | H89: Tennessee | I89: 38017-4136 | J89: United States | K89: Appliance Rental | L89: Double-Door Mini Fridge | M89: 145 | O89: N/A | P89: 45883 | U89: Myers | V89: N/A | X89: 45883
A90: https://utrucking.com/admin/orders/5903479177404 | B90: #15317 | C90: rpallera@comcast.net | D90: 19014977219 | E90: Robyn Pallera | G90: collierville | H90: Tennessee | I90: 38017-4136 | J90: United States | K90: Nationwide Ship to School | L90: Nationwide Ship to School | M90: 49 | N90: University Housing | O90: N/A | P90: 45883 | Q90: 09:00 AM to 11:00 AM | S90: University Housing | T90: University Housing | U90: Myers | V90: N/A | X90: 45883 | Y90: 09:00 AM to 11:00 AM | AB90: University Housing | AC90: Campbell Pallera 140 JAMERSON FARM RD Collierville, TN 38017
A91: https://utrucking.com/admin/orders/5903657599164 | B91: #15318 | C91: k.i.rodriguez@wustl.edu | D91: 4752832419 | E91: Kate Rodriguez | G91: Westport | H91: Connecticut | I91: 6880 | J91: United States | K91: Appliance Rental | L91: Double-Door Mini Fridge + Microwave | M91: 210 | O91: 4410 | P91: 45883 | U91: Koenig | V91: 4410 | X91: 45883
A92: https://utrucking.com/admin/orders/5903703638204 | B92: #15319 | C92: joline@wustl.edu | D92: 3462218260 | E92: Joline Sun | G92: Houston | H92: Texas | I92: 77057 | J92: United States | K92: Storage Item Return | M92: 1 | N92: University Housing | O92: 2053-a | P92: 45883 | Q92: 01:00 PM to 03:00 PM | S92: University Housing | T92: University Housing | U92: Shepley | V92: 2053-a | X92: 45883 | Y92: 01:00 PM to 03:00 PM | AB92: University Housing
A93: https://utrucking.com/admin/orders/5903737815228 | B93: #15320 | C93: embrownlawprof@gmail.com | D93: 7862013823 | E93: Eleanor Browm | G93: Enfield | H93: New Hampshire | I93: 3748 | J93: United States | K93: Tri-State Area Home Pickups | M93: 49 | N93: University Housing | O93: xxx | P93: 45882 | S93: University Housing | T93: University Housing | U93: DON'T KNOW YET (put 'XXX' for room #) | V93: xxx | X93: 45882 | Z93: $100 per item [Included] | AB93: University Housing | AD93: 72 Barlow Street Canaan CT 06018
A94: https://utrucking.com/admin/orders/5903766323388 | B94: #15321 | D94: 13016029939 | E94: MANIKA BATRA | G94: ROCKVILLE | H94: Maryland | I94: 20853-3234 | J94: United States | K94: Nationwide Ship to School | L94: Nationwide Ship to School | M94: 49 | N94: University Housing | O94: 431-a | P94: 45883 | Q94: 09:00 AM to 11:00 AM | S94: University Housing | T94: University Housing | U94: Dauten | V94: 431-a | X94: 45883 | Y94: 09:00 AM to 11:00 AM | AB94: University Housing | AC94: 4001 Thistlebridge Way Rockville, MD 20853
A95: https://utrucking.com/admin/orders/5903767109820 | B95: #15322 | C95: k.nayeon@wustl.edu | D95: 6503092445 | E95: Nayeon Kim | G95: Los Altos | H95: California | I95: 94024 | J95: United States | K95: Storage Item Return | M95: 1 | N95: University Housing | O95: 3154 | P95: 45883 | Q95: 10:00 AM to 12:00 PM | S95: University Housing | T95: University Housing | U95: Zetcher | V95: 3154 | X95: 45883 | Y95: 10:00 AM to 12:00 PM | AB95: University Housing
A96: https://utrucking.com/admin/orders/5903780315324 | B96: #15323 | D96: 7732945882 | E96: Karen Ebroon | G96: Deerfield | H96: Illinois | I96: 60015 | J96: United States | K96: Appliance Rental | L96: Standard Mini Fridge | M96: 115 | O96: 3329 | P96: 45883 | U96: Lien | V96: 3329 | X96: 45883
A97: https://utrucking.com/admin/orders/5903819833532 | B97: #15324 | C97: mabeleonurrutia@gmail.com | D97: 4707319605 | E97: Maria Leon | G97: Suwanee | H97: Georgia | I97: 30024 | J97: United States | K97: Storage Item Return | M97: 1 | N97: University Housing | O97: 1054-A | P97: 45875 | Q97: 09:00 AM to 11:00 AM | S97: University Housing | T97: University Housing | U97: Eliot B | V97: 1054-A | X97: 45875 | Y97: 09:00 AM to 11:00 AM | AB97: University Housing
A98: https://utrucking.com/admin/orders/5903890022588 | B98: #15325 | C98: katiefung11@gmail.com | D98: 6282134584 | E98: Katie Fung | G98: Redwood City | H98: California | I98: 94065 | J98: United States | K98: Appliance Rental | L98: Double-Door Mini Fridge + Microwave | M98: 210 | O98: 392 | P98: 45883 | U98: Park | V98: 392 | X98: 45883
A99: https://utrucking.com/admin/orders/5903995863228 | B99: #15326 | C99: f.lucy@wustl.edu | D99: 7743620993 | E99: Lucy Forman | G99: Walpole | H99: Massachusetts | I99: 2081 | J99: United States | K99: Nationwide Ship to School | L99: Nationwide Ship to School | M99: 49 | N99: University Housing | O99: 3328 | P99: 45883 | Q99: 09:00 AM to 11:00 AM | S99: University Housing | T99: University Housing | U99: Lien | V99: 3328 | X99: 45883 | Y99: 09:00 AM to 11:00 AM | AB99: University Housing | AC99: 16 Starlight Dr Walpole, MA 02081
A100: https://utrucking.com/admin/orders/5904080044220 | B100: #15327 | D100: 19148865868 | E100: Emma Lichtman | F100: 6643 Kingsbury Blvd University City, MO 63130 Apt. 3E | G100: New Rochelle | H100: New York | I100: 10804 | J100: United States | K100: Tri-State Area Home Pickups | M100: 49 | N100: Non-University Housing | P100: 45869 | Q100: 09:00 AM to 11:00 AM | R100: 6643 Kingsbury Blvd University City, MO 63130 Apt. 3E | S100: Non-University Housing | T100: Non-University Housing | W100: 6643 Kingsbury Blvd University City, MO 63130 Apt. 3E | X100: 45869 | Y100: 09:00 AM to 11:00 AM | Z100: $100 per item [Included] | AA100: 6643 Kingsbury Blvd University City, MO 63130 Apt. 3E | AB100: Non-University Housing | AD100: 80 Pryer Terrace New Rochelle, NY 10804
...

Sheet TEST
A1: Order URL | B1: Order Name | C1: Email | D1: Shipping Name | E1: Address | F1: City | G1: State/Province | H1: Zip | I1: Country | J1: Product Name | K1: Product SKU | L1: Product Price | M1: Pickup Date | N1: Pickup Time | O1: Pickup Location | P1: Building | Q1: Room Number | R1: Off-Campus Address | S1: Delivery Location | T1: Delivery Date | U1: Delivery Time | V1: Ship From Address | W1: Move Date | X1: Move Type | Y1: Moving from address or location_copy | Z1: Moving to address or location | AA1: Note | AB1: Insurance | AC1: Pickup Address | AD1: Location Type | AE1: Non-University Housing Address
A2: https://utrucking.com/admin/orders/5900755337404 | B2: #15275 | C2: orbucho2006@gmail.com | J2: Storage Item Return | L2: 1 | R2: 7036 Forsyth Blvd | S2: Non-University Housing | T2: 45875 | U2: 12:00 PM to 02:00 PM
A3: https://utrucking.com/admin/orders/5900755337404 | B3: #15275 | C3: orbucho2006@gmail.com | D3: Olivia Orbuch | E3: 1723 s corning street | F3: Los Angles | G3: California | H3: 90035 | I3: United States | J3: Storage Item Return | L3: 1 | R3: 7036 Forsyth Blvd | S3: Non-University Housing | T3: 45875 | U3: 12:00 PM to 02:00 PM

Sheet Order Edits
A1: Order # | B1: Change Type | C1: New Date | D1: New Time | E1: New Room | F1: New Building | G1: New Off-Campus Adress | H1: Notes | I1: Edited on MAIN? | J1: Edited Shopify Note? | K1: Reported On | L1: Edited on | M1: Edited By
A2: #15222 | B2: Date, Room, Building | C2: 45884 | E2: 412 | F2: Dauten | I2: TRUE | J2: TRUE | L2: 45853 | M2: Ahmed
A3: #15223 | B3: Date, Room, Building | C3: 45885 | E3: 3304 | F3: Koenig | I3: TRUE | J3: TRUE | L3: 45853 | M3: Ahmed
A4: #15224 | B4: Date, Room, Building | C4: 45884 | E4: 4421 | F4: Dardick | I4: TRUE | J4: TRUE | L4: 45853 | M4: Ahmed
A5: #15261 | B5: Date, Room, Building | C5: 45884 | E5: 3310 | F5: Koenig | I5: TRUE | J5: TRUE | L5: 45853 | M5: Ahmed
A6: #15262 | B6: Room, Building | E6: 2224 | F6: Lien | I6: TRUE | J6: TRUE | L6: 45853 | M6: Ahmed
A7: #15266 | B7: Date | C7: 45883 | I7: TRUE | J7: TRUE | L7: 45853 | M7: Ahmed
A8: #15284 | B8: Date | C8: 45883 | I8: TRUE | J8: TRUE | L8: 45853 | M8: Ahmed
A9: #15327 | B9: Date, Time | C9: 45888 | D9: 45911 | H9: wants delivery on August 19th, 9-11am | I9: TRUE | J9: TRUE | L9: 45853 | M9: Ahmed
A10: #15339 | B10: Date | C10: 45883 | I10: TRUE | J10: TRUE | L10: 45853 | M10: Ahmed
A11: #15363 | B11: Service-Note | H11: switched from tsa to nsts | I11: TRUE | J11: TRUE | L11: 45859 | M11: Ahmed
A12: #15338 | B12: Service-Note | H12: removed nsts from order, using tsa (although tsa never showed up on this sheet) | I12: TRUE | J12: TRUE | L12: 45859 | M12: Ahmed
A13: #15391 | B13: Date | C13: 45883 | I13: TRUE | J13: TRUE | L13: 45859 | M13: Ahmed
A14: #15071 | B14: Room, Building | E14: 3309 | F14: Umrath | I14: TRUE | J14: TRUE | L14: 45859 | M14: Ahmed
A15: #15433 | B15: Cancelled | H15: canceled their order | I15: TRUE | J15: TRUE
A16: #14983 | B16: Room, Building | E16: 4427 | F16: Danforth | I16: TRUE | J16: TRUE | K16: 45857 | L16: 45859 | M16: Ahmed
A17: #14171 | B17: Room, Building | E17: 3331 | F17: Lien | I17: TRUE | J17: TRUE | K17: 45857 | L17: 45859 | M17: Ahmed
A18: #15064 | B18: Date, Room, Building, Product | C18: 45891 | E18: 3062 | F18: Gregg | H18: not on main, add to main, SWITCH TO CHEF SIZE FRIDGE | I18: TRUE | J18: TRUE | K18: 45858 | L18: 45859 | M18: Ahmed
A19: #15327 | B19: date, time | C19: 45888 | D19: 45942 | I19: TRUE | J19: TRUE | K19: 45859
A20: #15548 | B20: date | C20: 45881 | I20: TRUE | J20: TRUE | K20: 45859 | L20: 45860 | M20: Ahmed
A21: #15574 | B21: Date | C21: 45860 | H21: Switch spec ops to 7/22 since calendar wouldn't let me select earlier than 7/23 | I21: TRUE | J21: TRUE | K21: 45859 | L21: 45860 | M21: Ahmed
A22: #14853 | B22: room, building | E22: 372 | F22: Park | I22: TRUE | J22: TRUE | L22: 45863 | M22: Ahmed
A23: #15114 | B23: room, building | E23: 242-b | F23: Dauten | I23: TRUE | J23: TRUE | L23: 45863 | M23: Ahmed
A24: #15133 | B24: room, building | E24: L-237 | F24: Umrath | I24: TRUE | J24: TRUE | L24: 45863 | M24: Ahmed
A25: #15550 | B25: date | C25: 45890 | I25: TRUE | J25: TRUE | L25: 45863 | M25: Ahmed
A26: #15581 | B26: date, time | C26: 45887 | D26: 45911 | I26: TRUE | J26: TRUE | L26: 45863 | M26: Ahmed
A27: #15271 | B27: date | C27: 45876 | I27: TRUE | J27: TRUE | L27: 45863 | M27: Ahmed
A28: #14588 | B28: room, building | E28: 4419 | F28: Danforth | I28: TRUE | J28: TRUE | L28: 45863 | M28: Ahmed
A29: #15582 | B29: date, time | C29: 45891 | D29: 45941 | I29: TRUE | J29: TRUE | L29: 45863 | M29: Ahmed
A30: #15103 | B30: room, building | E30: 413 | F30: Myers | I30: TRUE | J30: TRUE | L30: 45863 | M30: Ahmed
A31: #15704 | B31: service note | H31: switch to tri-state home pickup | I31: TRUE | J31: TRUE | L31: 45863 | M31: Ahmed
A32: #15711 | B32: cancelled | H32: canceled their order | I32: TRUE | J32: TRUE | L32: 45863 | M32: Ahmed
A33: #15539 | B33: room, building | E33: 3319 | F33: Danforth | I33: TRUE | J33: TRUE | L33: 45865 | M33: Ahmed
A34: #15148 | B34: room, building | E34: 3323 | F34: Umrath | I34: TRUE | J34: TRUE | L34: 45865 | M34: Ahmed
A35: #14996 | B35: re-add and edit housing | E35: 3301 | F35: Koenig | H35: Double Door mini fridge (order was fulfilled after summer delivery, need to make sure it is re-added and housing is changed to koenig) | I35: TRUE | J35: TRUE | L35: 45865 | M35: Ahmed
A36: #14341 | B36: room, building | E36: 3302 | F36: Umrath | I36: TRUE | J36: TRUE | L36: 45865 | M36: Ahmed
A37: #14342 | B37: room, building | E37: 3302 | F37: Umrath | I37: TRUE | J37: TRUE | L37: 45865 | M37: Ahmed
A38: #15079 | B38: room, building | E38: 2240 | F38: Umrath | I38: TRUE | J38: TRUE | L38: 45865 | M38: Ahmed
A39: #15487 | B39: service note | H39: cancel microwave, keep fridge | I39: TRUE | J39: TRUE | L39: 45865 | M39: Ahmed
A40: #15514 | B40: date, room, building | C40: 45891 | E40: 1051 | F40: Lopata | I40: TRUE | J40: TRUE | L40: 45865 | M40: Ahmed
A41: #15268 | B41: building | F41: House 1 | I41: TRUE | J41: TRUE | L41: 45865 | M41: Ahmed
A42: #15472 | B42: building | F42: House 3 (Alpha Delta Phi) | I42: TRUE | J42: TRUE | L42: 45865 | M42: Ahmed
A43: #15600 | B43: building | F43: House 1 | I43: TRUE | J43: TRUE | L43: 45865 | M43: Ahmed
A44: #15588 | B44: building | F44: House 3 (Alpha Delta Phi) | I44: TRUE | J44: TRUE | L44: 45865 | M44: Ahmed
A45: #15670 | B45: off campus address, date, time | C45: 45889 | D45: 45660 | G45: 740 Westgate #3N | I45: TRUE | J45: TRUE | L45: 45867 | M45: Ahmed
A46: #15161 | B46: room, building | E46: 3320 | F46: Danforth | I46: TRUE | J46: TRUE | L46: 45867 | M46: Ahmed
A47: #15162 | B47: room, building | E47: 3320 | F47: Danforth | I47: TRUE | J47: TRUE | L47: 45867 | M47: Ahmed
A48: #14478 | B48: add to MAIN, SIR, room, building, date, time | C48: 45893 | D48: 45692 | G48: 6105 Delmar BIvd. Apt 515 | H48: add storage item return order to main,make sure it shows up on SIR | I48: TRUE | J48: TRUE | L48: 45869 | M48: Ahmed
A49: #15151 | B49: room, building | E49: 432-b | F49: Rutledge | I49: TRUE | J49: TRUE | L49: 45869 | M49: Ahmed
A50: #15738 | B50: date, time, note | C50: 45892 | D50: 5 | H50: flight landing at 5, please leave outside building if we can't delay the delivery until 6 or so | I50: TRUE | J50: TRUE | L50: 45869 | M50: Ahmed
A51: #15355 | B51: room | E51: 2053 | I51: TRUE | J51: TRUE | L51: 45869 | M51: Ahmed
A52: #15138 | B52: room, building | E52: 422 | F52: Dauten | I52: TRUE | J52: TRUE | L52: 45869 | M52: Ahmed
A53: #15525 | B53: building | F53: Lopata | I53: TRUE | J53: TRUE | L53: 45869 | M53: Ahmed
A54: #15902 | B54: date, time | C54: 45891 | D54: 45911 | I54: TRUE | J54: TRUE | L54: 45869 | M54: Ahmed
A55: #15365 | B55: date | C55: 45891 | D55: 3-4p | E55: Yian Sun | F55: Residential Home | G55: Zetcher | I55: TRUE | J55: TRUE | L55: 45869 | M55: Ahmed
A56: #15346 | B56: room | E56: 3312 | I56: TRUE | J56: TRUE | L56: 45869 | M56: Ahmed
A57: #15823 | B57: room | E57: 323-a | I57: TRUE | J57: TRUE | L57: 45869 | M57: Ahmed
A58: #15041 | B58: room, building | E58: 2224 | F58: Lien | I58: TRUE | J58: TRUE | L58: 45869 | M58: Ahmed
A59: #15633 | B59: room, building | E59: 2224 | F59: Lien | I59: TRUE | J59: TRUE | L59: 45869 | M59: Ahmed
A60: #15139 | B60: service | H60: switch to double door mini-fridge+micro | I60: TRUE | J60: TRUE | L60: 45869 | M60: Ahmed
A61: #15317 | B61: room, building | E61: 413-b | F61: Myers | I61: TRUE | J61: TRUE | L61: 45869 | M61: Ahmed
A62: #15159 | B62: room, building | E62: 1109-a | F62: Koenig | I62: TRUE | J62: TRUE | L62: 45869 | M62: Ahmed
A63: #15257 | B63: time | D63: 45911 | I63: TRUE | J63: TRUE | L63: 45869 | M63: Ahmed
A64: #15760 | B64: room, building | E64: 322A | F64: Hurd | I64: TRUE | J64: TRUE | L64: 45869 | M64: Ahmed
A65: #15129 | B65: room, building | E65: 2210 | F65: Dardick | I65: TRUE | J65: TRUE | L65: 45869 | M65: Ahmed
A66: #15957 | B66: room, building | E66: 1173 | F66: Liggett | I66: TRUE | J66: TRUE | L66: 45869 | M66: Ahmed
A67: #15653 | B67: room | E67: 422 | I67: TRUE | J67: TRUE | L67: 45872 | M67: Ahmed
A68: #15958 | B68: off campus address | G68: 6105 Delmar Blvd, Apt 523, St. Louis MO 63112 (Everly On The Loop) | I68: TRUE | J68: TRUE | L68: 45872 | M68: Ahmed
A69: #15806 | B69: room, building | E69: 2216-a | F69: Koenig | I69: TRUE | J69: TRUE | L69: 45872 | M69: Ahmed
A70: #15988 | B70: notes | H70: Cara Satyr - sophomore | I70: TRUE | J70: TRUE | L70: 45872 | M70: Ahmed
A71: #15989 | B71: notes | H71: Jonah Satyr - senior | I71: TRUE | J71: TRUE | L71: 45872 | M71: Ahmed
A72: #15597 | B72: room | E72: 3330 | I72: TRUE | J72: TRUE | L72: 45872 | M72: Ahmed
A73: #15124 | B73: room, building | E73: 4402 | F73: Dardick | I73: TRUE | J73: TRUE | L73: 45873 | M73: Ahmed
A74: #15124 | B74: room, building | E74: 4402 | F74: Dardick | I74: TRUE | J74: TRUE | L74: 45873 | M74: Ahmed
A75: #15123 | B75: room, building | E75: 244 | F75: Rutledge | I75: TRUE | J75: TRUE | L75: 45873 | M75: Ahmed
A76: #15418 | B76: room, building | E76: 1107 | F76: Koenig | I76: TRUE | J76: TRUE | L76: 45873 | M76: Ahmed
A77: #15597 | B77: room, building | E77: 3330 | F77: Lien | I77: TRUE | J77: TRUE | L77: 45874 | M77: Ahmed
A78: #15946 | B78: date, time | C78: 45877 | D78: 10am-12pm | I78: TRUE | J78: TRUE | L78: 45874 | M78: Ahmed
A79: #16020 | B79: off campus address | G79: 750 Kingsland Ave Apt 2S, University City, MO 63130 | I79: TRUE | J79: TRUE | L79: 45874 | M79: Ahmed
A80: #15299 | B80: room, building | E80: 2204 | F80: Dardick | I80: TRUE | J80: TRUE | L80: 45875 | M80: Ahmed
A81: #15690 | B81: room, building | E81: 2102 | F81: Eliot A | I81: TRUE | J81: TRUE | L81: 45875 | M81: Ahmed
A82: #15134 | B82: room, building | E82: 4402 | F82: Dardick | I82: TRUE | J82: TRUE | L82: 45876 | M82: Ahmed
A83: #13918 | B83: date, time | C83: 45889 | D83: 12-2pm | I83: TRUE | J83: TRUE | L83: 45877 | M83: Ahmed
A84: #16028 | B84: service - needs summer storage | H84: needs summer storage | I84: TRUE | J84: TRUE | L84: 45879 | M84: Ahmed
A85: #16174 | B85: room, building | E85: 3073 | F85: Zetcher | I85: TRUE | J85: TRUE | L85: 45879 | M85: Ahmed
A86: #16169 | B86: date | C86: 45878 | I86: TRUE | J86: TRUE | L86: 45879 | M86: Ahmed
A87: #15650 | B87: date, time | C87: 45894 | D87: 9-11am | I87: TRUE | J87: TRUE | L87: 45879 | M87: Ahmed
A88: #15279 | B88: room, building | E88: 306 | F88: Lee | I88: TRUE | J88: TRUE | L88: 45879 | M88: Ahmed
A89: #15482 | B89: date, time, off campus address | C89: 45891 | D89: 10-12pm | G89: 6603 University Drive | I89: TRUE | J89: TRUE | L89: 45880 | M89: Ahmed
A90: #16191 | B90: room, building | E90: 3124 | F90: Village House | I90: TRUE | J90: TRUE | L90: 45881 | M90: Ahmed
A91: #16248 | B91: room, building | E91: 3124 | F91: Village House | I91: TRUE | J91: TRUE | L91: 45881 | M91: Ahmed
A92: #16255 | B92: add exact address | G92: 16712 Chesterfield Farms Drive, Chesterfield MO 63005 | I92: TRUE | J92: TRUE | L92: 45881 | M92: Ahmed
A93: #16279 | B93: notes | H93: Contact: Mark Bethel | (312) 952-3233 | I93: TRUE | J93: TRUE | L93: 45882 | M93: Ahmed
A94: #16203 | B94: date, time | C94: 45888 | D94: 3-5pm | I94: TRUE | J94: TRUE | L94: 45883 | M94: Ahmed
A95: #15965 | B95: date, time | C95: 45890 | D95: 3-5pm | I95: TRUE | J95: TRUE | L95: 45883 | M95: Ahmed
A96: #15955 | B96: date, time, off campus address | C96: 45891 | D96: 1-3pm | G96: 6632 Washington Ave, Apt 3N, St. Louis MO | I96: TRUE | J96: TRUE | L96: 45888 | M96: Ahmed
A97: #15965 | B97: date, time | C97: 45891 | D97: 3-5pm | I97: TRUE | J97: TRUE | L97: 45888 | M97: Ahmed
A98: #15981 | B98: date, time, off campus address | C98: 45890 | D98: 3-5pm | G98: 6666 Washington Ave, Univeristy City, MO | I98: TRUE | J98: TRUE | L98: 45888 | M98: Ahmed
A99: #16417 | B99: off campus address | G99: same address, just unit 605 and not 611 | I99: TRUE | J99: TRUE | L99: 45888 | M99: Ahmed
A100: #16203 | B100: date, time | C100: 45890 | D100: 10-12pm | I100: TRUE | J100: TRUE | L100: 45888 | M100: Ahmed
...

Sheet Kit Delivery Status
A1: =IFERROR(__xludf.DUMMYFUNCTION("IMPORTRANGE(""1x5MQbsCFMJX5eafA6uoFF0nU4qfvCaK-2EyZNPs__kM"", ""'Kit History'!A:Z"")"),"ID") -> ID | B1: =IFERROR(__xludf.DUMMYFUNCTION("""COMPUTED_VALUE"""),"Date") -> Date | C1: =IFERROR(__xludf.DUMMYFUNCTION("""COMPUTED_VALUE"""),"Mode") -> Mode | D1: =IFERROR(__xludf.DUMMYFUNCTION("""COMPUTED_VALUE"""),"Truck") -> Truck | E1: =IFERROR(__xludf.DUMMYFUNCTION("""COMPUTED_VALUE"""),"Building") -> Building | F1: =IFERROR(__xludf.DUMMYFUNCTION("""COMPUTED_VALUE"""),"Room") -> Room | G1: =IFERROR(__xludf.DUMMYFUNCTION("""COMPUTED_VALUE"""),"Student") -> Student | H1: =IFERROR(__xludf.DUMMYFUNCTION("""COMPUTED_VALUE"""),"Phone") -> Phone | I1: =IFERROR(__xludf.DUMMYFUNCTION("""COMPUTED_VALUE"""),"Time Slot") -> Time Slot | J1: =IFERROR(__xludf.DUMMYFUNCTION("""COMPUTED_VALUE"""),"Kits") -> Kits | K1: =IFERROR(__xludf.DUMMYFUNCTION("""COMPUTED_VALUE"""),"Status") -> Status | L1: =IFERROR(__xludf.DUMMYFUNCTION("""COMPUTED_VALUE"""),"Mover Notes") -> Mover Notes | M1: =IFERROR(__xludf.DUMMYFUNCTION("""COMPUTED_VALUE"""),"Completed At") -> Completed At | N1: =IFERROR(__xludf.DUMMYFUNCTION("""COMPUTED_VALUE"""),"Sort Order") -> Sort Order | O1: =IFERROR(__xludf.DUMMYFUNCTION("""COMPUTED_VALUE"""),"Address") -> Address | P1: =IFERROR(__xludf.DUMMYFUNCTION("""COMPUTED_VALUE"""),"Service") -> Service | Q1: =IFERROR(__xludf.DUMMYFUNCTION("""COMPUTED_VALUE"""),"Customer Note") -> Customer Note | R1: =IFERROR(__xludf.DUMMYFUNCTION("""COMPUTED_VALUE"""),"Product") -> Product | S1: =IFERROR(__xludf.DUMMYFUNCTION("""COMPUTED_VALUE"""),"Photos") -> Photos | T1: =IFERROR(__xludf.DUMMYFUNCTION("""COMPUTED_VALUE"""),"Archived On") -> Archived On | U1: =IFERROR(__xludf.DUMMYFUNCTION("""COMPUTED_VALUE"""),"Order Number") -> Order Number
A2: =IFERROR(__xludf.DUMMYFUNCTION("""COMPUTED_VALUE"""),"KIT-#17764") -> KIT-#17764 | B2: =IFERROR(__xludf.DUMMYFUNCTION("""COMPUTED_VALUE"""),46139.0) -> 46139 | C2: =IFERROR(__xludf.DUMMYFUNCTION("""COMPUTED_VALUE"""),"Kit Delivery") -> Kit Delivery | D2: =IFERROR(__xludf.DUMMYFUNCTION("""COMPUTED_VALUE"""),1.0) -> 1 | E2: =IFERROR(__xludf.DUMMYFUNCTION("""COMPUTED_VALUE"""),"Off-Campus") -> Off-Campus | G2: =IFERROR(__xludf.DUMMYFUNCTION("""COMPUTED_VALUE"""),"Yujin He") -> Yujin He | H2: =IFERROR(__xludf.DUMMYFUNCTION("""COMPUTED_VALUE"""),3.144377856E9) -> 3144377856 | I2: =IFERROR(__xludf.DUMMYFUNCTION("""COMPUTED_VALUE"""),"12PM-2PM") -> 12PM-2PM | J2: =IFERROR(__xludf.DUMMYFUNCTION("""COMPUTED_VALUE"""),0.0) -> 0 | K2: =IFERROR(__xludf.DUMMYFUNCTION("""COMPUTED_VALUE"""),"Complete") -> Complete | L2: =IFERROR(__xludf.DUMMYFUNCTION("""COMPUTED_VALUE"""),"no kit") -> no kit | N2: =IFERROR(__xludf.DUMMYFUNCTION("""COMPUTED_VALUE"""),228.0) -> 228 | O2: =IFERROR(__xludf.DUMMYFUNCTION("""COMPUTED_VALUE"""),"605 Leland Ave, University City, MO, 63130; University Squares Apartment") -> 605 Leland Ave, University City, MO, 63130; University Squares Apartment | P2: =IFERROR(__xludf.DUMMYFUNCTION("""COMPUTED_VALUE"""),"Kit Delivery") -> Kit Delivery | T2: =IFERROR(__xludf.DUMMYFUNCTION("""COMPUTED_VALUE"""),46137.738217592596) -> 46137.738
A3: =IFERROR(__xludf.DUMMYFUNCTION("""COMPUTED_VALUE"""),"KIT-#17350") -> KIT-#17350 | B3: =IFERROR(__xludf.DUMMYFUNCTION("""COMPUTED_VALUE"""),46140.0) -> 46140 | C3: =IFERROR(__xludf.DUMMYFUNCTION("""COMPUTED_VALUE"""),"Kit Delivery") -> Kit Delivery | D3: =IFERROR(__xludf.DUMMYFUNCTION("""COMPUTED_VALUE"""),1.0) -> 1 | E3: =IFERROR(__xludf.DUMMYFUNCTION("""COMPUTED_VALUE"""),"LL6300") -> LL6300 | F3: =IFERROR(__xludf.DUMMYFUNCTION("""COMPUTED_VALUE"""),"304C") -> 304C | G3: =IFERROR(__xludf.DUMMYFUNCTION("""COMPUTED_VALUE"""),"Nena Tesinsky") -> Nena Tesinsky | H3: =IFERROR(__xludf.DUMMYFUNCTION("""COMPUTED_VALUE"""),9.195618234E9) -> 9195618234 | I3: =IFERROR(__xludf.DUMMYFUNCTION("""COMPUTED_VALUE"""),"3PM-5PM") -> 3PM-5PM | J3: =IFERROR(__xludf.DUMMYFUNCTION("""COMPUTED_VALUE"""),0.0) -> 0 | K3: =IFERROR(__xludf.DUMMYFUNCTION("""COMPUTED_VALUE"""),"Complete") -> Complete | N3: =IFERROR(__xludf.DUMMYFUNCTION("""COMPUTED_VALUE"""),37.0) -> 37 | P3: =IFERROR(__xludf.DUMMYFUNCTION("""COMPUTED_VALUE"""),"Kit Delivery") -> Kit Delivery | S3: =IFERROR(__xludf.DUMMYFUNCTION("""COMPUTED_VALUE"""),46122.53804398148) -> 46122.538
A4: =IFERROR(__xludf.DUMMYFUNCTION("""COMPUTED_VALUE"""),"KIT-#17765") -> KIT-#17765 | B4: =IFERROR(__xludf.DUMMYFUNCTION("""COMPUTED_VALUE"""),46143.0) -> 46143 | C4: =IFERROR(__xludf.DUMMYFUNCTION("""COMPUTED_VALUE"""),"Kit Delivery") -> Kit Delivery | D4: =IFERROR(__xludf.DUMMYFUNCTION("""COMPUTED_VALUE"""),1.0) -> 1 | E4: =IFERROR(__xludf.DUMMYFUNCTION("""COMPUTED_VALUE"""),"Park") -> Park | F4: =IFERROR(__xludf.DUMMYFUNCTION("""COMPUTED_VALUE"""),162.0) -> 162 | G4: =IFERROR(__xludf.DUMMYFUNCTION("""COMPUTED_VALUE"""),"Casey Ference") -> Casey Ference | H4: =IFERROR(__xludf.DUMMYFUNCTION("""COMPUTED_VALUE"""),"(917) 733-1526") -> (917) 733-1526 | I4: =IFERROR(__xludf.DUMMYFUNCTION("""COMPUTED_VALUE"""),"9AM-11AM") -> 9AM-11AM | J4: =IFERROR(__xludf.DUMMYFUNCTION("""COMPUTED_VALUE"""),0.0) -> 0 | K4: =IFERROR(__xludf.DUMMYFUNCTION("""COMPUTED_VALUE"""),"Complete") -> Complete | L4: =IFERROR(__xludf.DUMMYFUNCTION("""COMPUTED_VALUE"""),"no kit") -> no kit | N4: =IFERROR(__xludf.DUMMYFUNCTION("""COMPUTED_VALUE"""),49.0) -> 49 | O4: =IFERROR(__xludf.DUMMYFUNCTION("""COMPUTED_VALUE"""),"8 John Street Demarest, NJ 07627") -> 8 John Street Demarest, NJ 07627 | P4: =IFERROR(__xludf.DUMMYFUNCTION("""COMPUTED_VALUE"""),"Kit Delivery") -> Kit Delivery | T4: =IFERROR(__xludf.DUMMYFUNCTION("""COMPUTED_VALUE"""),46137.738217592596) -> 46137.738
A5: =IFERROR(__xludf.DUMMYFUNCTION("""COMPUTED_VALUE"""),"KIT-#17767") -> KIT-#17767 | B5: =IFERROR(__xludf.DUMMYFUNCTION("""COMPUTED_VALUE"""),46143.0) -> 46143 | C5: =IFERROR(__xludf.DUMMYFUNCTION("""COMPUTED_VALUE"""),"Kit Delivery") -> Kit Delivery | D5: =IFERROR(__xludf.DUMMYFUNCTION("""COMPUTED_VALUE"""),2.0) -> 2 | E5: =IFERROR(__xludf.DUMMYFUNCTION("""COMPUTED_VALUE"""),"Umrath") -> Umrath | F5: =IFERROR(__xludf.DUMMYFUNCTION("""COMPUTED_VALUE"""),"L239") -> L239 | G5: =IFERROR(__xludf.DUMMYFUNCTION("""COMPUTED_VALUE"""),"Mia Galpern") -> Mia Galpern | H5: =IFERROR(__xludf.DUMMYFUNCTION("""COMPUTED_VALUE"""),9.177155789E9) -> 9177155789 | I5: =IFERROR(__xludf.DUMMYFUNCTION("""COMPUTED_VALUE"""),"10AM-12PM") -> 10AM-12PM | J5: =IFERROR(__xludf.DUMMYFUNCTION("""COMPUTED_VALUE"""),0.0) -> 0 | K5: =IFERROR(__xludf.DUMMYFUNCTION("""COMPUTED_VALUE"""),"Complete") -> Complete | N5: =IFERROR(__xludf.DUMMYFUNCTION("""COMPUTED_VALUE"""),85.0) -> 85 | O5: =IFERROR(__xludf.DUMMYFUNCTION("""COMPUTED_VALUE"""),"66 Leonard street 9b New York, NY 10013") -> 66 Leonard street 9b New York, NY 10013 | P5: =IFERROR(__xludf.DUMMYFUNCTION("""COMPUTED_VALUE"""),"Kit Delivery") -> Kit Delivery | T5: =IFERROR(__xludf.DUMMYFUNCTION("""COMPUTED_VALUE"""),46138.009050925924) -> 46138.009
A6: =IFERROR(__xludf.DUMMYFUNCTION("""COMPUTED_VALUE"""),"KIT-#17508") -> KIT-#17508 | B6: =IFERROR(__xludf.DUMMYFUNCTION("""COMPUTED_VALUE"""),46144.0) -> 46144 | C6: =IFERROR(__xludf.DUMMYFUNCTION("""COMPUTED_VALUE"""),"Kit Delivery") -> Kit Delivery | D6: =IFERROR(__xludf.DUMMYFUNCTION("""COMPUTED_VALUE"""),3.0) -> 3 | E6: =IFERROR(__xludf.DUMMYFUNCTION("""COMPUTED_VALUE"""),"Koenig") -> Koenig | F6: =IFERROR(__xludf.DUMMYFUNCTION("""COMPUTED_VALUE"""),4413.0) -> 4413 | G6: =IFERROR(__xludf.DUMMYFUNCTION("""COMPUTED_VALUE"""),"Ava Virmani") -> Ava Virmani | H6: =IFERROR(__xludf.DUMMYFUNCTION("""COMPUTED_VALUE"""),3.123998535E9) -> 3123998535 | I6: =IFERROR(__xludf.DUMMYFUNCTION("""COMPUTED_VALUE"""),"2PM-4PM") -> 2PM-4PM | J6: =IFERROR(__xludf.DUMMYFUNCTION("""COMPUTED_VALUE"""),0.0) -> 0 | K6: =IFERROR(__xludf.DUMMYFUNCTION("""COMPUTED_VALUE"""),"Complete") -> Complete | L6: =IFERROR(__xludf.DUMMYFUNCTION("""COMPUTED_VALUE"""),"No kit, don't SMS") -> No kit, don't SMS | M6: =IFERROR(__xludf.DUMMYFUNCTION("""COMPUTED_VALUE"""),46130.421076388884) -> 46130.421 | N6: =IFERROR(__xludf.DUMMYFUNCTION("""COMPUTED_VALUE"""),212.0) -> 212 | P6: =IFERROR(__xludf.DUMMYFUNCTION("""COMPUTED_VALUE"""),"Kit Delivery") -> Kit Delivery | S6: =IFERROR(__xludf.DUMMYFUNCTION("""COMPUTED_VALUE"""),"Dispatch_Images/KIT--17508.Photos.150618.jpg") -> Dispatch_Images/KIT--17508.Photos.150618.jpg | T6: =IFERROR(__xludf.DUMMYFUNCTION("""COMPUTED_VALUE"""),46130.42574074074) -> 46130.426
A7: =IFERROR(__xludf.DUMMYFUNCTION("""COMPUTED_VALUE"""),"KIT-#18101") -> KIT-#18101 | B7: =IFERROR(__xludf.DUMMYFUNCTION("""COMPUTED_VALUE"""),46144.0) -> 46144 | C7: =IFERROR(__xludf.DUMMYFUNCTION("""COMPUTED_VALUE"""),"Kit Delivery") -> Kit Delivery | D7: =IFERROR(__xludf.DUMMYFUNCTION("""COMPUTED_VALUE"""),2.0) -> 2 | E7: =IFERROR(__xludf.DUMMYFUNCTION("""COMPUTED_VALUE"""),"Eliot B") -> Eliot B | F7: =IFERROR(__xludf.DUMMYFUNCTION("""COMPUTED_VALUE"""),3060.0) -> 3060 | G7: =IFERROR(__xludf.DUMMYFUNCTION("""COMPUTED_VALUE"""),"Juliet Quisenberry") -> Juliet Quisenberry | H7: =IFERROR(__xludf.DUMMYFUNCTION("""COMPUTED_VALUE"""),5.124612236E9) -> 5124612236 | I7: =IFERROR(__xludf.DUMMYFUNCTION("""COMPUTED_VALUE"""),"9AM-11AM") -> 9AM-11AM | J7: =IFERROR(__xludf.DUMMYFUNCTION("""COMPUTED_VALUE"""),0.0) -> 0 | K7: =IFERROR(__xludf.DUMMYFUNCTION("""COMPUTED_VALUE"""),"Complete") -> Complete | N7: =IFERROR(__xludf.DUMMYFUNCTION("""COMPUTED_VALUE"""),33.0) -> 33 | P7: =IFERROR(__xludf.DUMMYFUNCTION("""COMPUTED_VALUE"""),"Kit Delivery") -> Kit Delivery | T7: =IFERROR(__xludf.DUMMYFUNCTION("""COMPUTED_VALUE"""),46142.69212962963) -> 46142.692
A8: =IFERROR(__xludf.DUMMYFUNCTION("""COMPUTED_VALUE"""),"KIT-#18079") -> KIT-#18079 | B8: =IFERROR(__xludf.DUMMYFUNCTION("""COMPUTED_VALUE"""),46144.0) -> 46144 | C8: =IFERROR(__xludf.DUMMYFUNCTION("""COMPUTED_VALUE"""),"Kit Delivery") -> Kit Delivery | D8: =IFERROR(__xludf.DUMMYFUNCTION("""COMPUTED_VALUE"""),2.0) -> 2 | E8: =IFERROR(__xludf.DUMMYFUNCTION("""COMPUTED_VALUE"""),"Park") -> Park | F8: =IFERROR(__xludf.DUMMYFUNCTION("""COMPUTED_VALUE"""),162.0) -> 162 | G8: =IFERROR(__xludf.DUMMYFUNCTION("""COMPUTED_VALUE"""),"Casey Ference") -> Casey Ference | H8: =IFERROR(__xludf.DUMMYFUNCTION("""COMPUTED_VALUE"""),9.17414012E9) -> 9174140120 | I8: =IFERROR(__xludf.DUMMYFUNCTION("""COMPUTED_VALUE"""),"9AM-11AM") -> 9AM-11AM | J8: =IFERROR(__xludf.DUMMYFUNCTION("""COMPUTED_VALUE"""),0.0) -> 0 | K8: =IFERROR(__xludf.DUMMYFUNCTION("""COMPUTED_VALUE"""),"Complete") -> Complete | N8: =IFERROR(__xludf.DUMMYFUNCTION("""COMPUTED_VALUE"""),39.0) -> 39 | P8: =IFERROR(__xludf.DUMMYFUNCTION("""COMPUTED_VALUE"""),"Kit Delivery") -> Kit Delivery | T8: =IFERROR(__xludf.DUMMYFUNCTION("""COMPUTED_VALUE"""),46142.69212962963) -> 46142.692
A9: =IFERROR(__xludf.DUMMYFUNCTION("""COMPUTED_VALUE"""),"KIT-#17495") -> KIT-#17495 | B9: =IFERROR(__xludf.DUMMYFUNCTION("""COMPUTED_VALUE"""),46146.0) -> 46146 | C9: =IFERROR(__xludf.DUMMYFUNCTION("""COMPUTED_VALUE"""),"Kit Delivery") -> Kit Delivery | D9: =IFERROR(__xludf.DUMMYFUNCTION("""COMPUTED_VALUE"""),2.0) -> 2 | E9: =IFERROR(__xludf.DUMMYFUNCTION("""COMPUTED_VALUE"""),"Park") -> Park | F9: =IFERROR(__xludf.DUMMYFUNCTION("""COMPUTED_VALUE"""),191.0) -> 191 | G9: =IFERROR(__xludf.DUMMYFUNCTION("""COMPUTED_VALUE"""),"Yanyu Yao") -> Yanyu Yao | H9: =IFERROR(__xludf.DUMMYFUNCTION("""COMPUTED_VALUE"""),3.142034028E9) -> 3142034028 | I9: =IFERROR(__xludf.DUMMYFUNCTION("""COMPUTED_VALUE"""),"1PM-3PM") -> 1PM-3PM | J9: =IFERROR(__xludf.DUMMYFUNCTION("""COMPUTED_VALUE"""),0.0) -> 0 | K9: =IFERROR(__xludf.DUMMYFUNCTION("""COMPUTED_VALUE"""),"Complete") -> Complete | N9: =IFERROR(__xludf.DUMMYFUNCTION("""COMPUTED_VALUE"""),62.0) -> 62 | P9: =IFERROR(__xludf.DUMMYFUNCTION("""COMPUTED_VALUE"""),"Kit Delivery") -> Kit Delivery | T9: =IFERROR(__xludf.DUMMYFUNCTION("""COMPUTED_VALUE"""),46130.474340277775) -> 46130.474
A10: =IFERROR(__xludf.DUMMYFUNCTION("""COMPUTED_VALUE"""),"KIT-#18095") -> KIT-#18095 | B10: =IFERROR(__xludf.DUMMYFUNCTION("""COMPUTED_VALUE"""),46146.0) -> 46146 | C10: =IFERROR(__xludf.DUMMYFUNCTION("""COMPUTED_VALUE"""),"Kit Delivery") -> Kit Delivery | D10: =IFERROR(__xludf.DUMMYFUNCTION("""COMPUTED_VALUE"""),2.0) -> 2 | E10: =IFERROR(__xludf.DUMMYFUNCTION("""COMPUTED_VALUE"""),"Park") -> Park | F10: =IFERROR(__xludf.DUMMYFUNCTION("""COMPUTED_VALUE"""),291.0) -> 291 | G10: =IFERROR(__xludf.DUMMYFUNCTION("""COMPUTED_VALUE"""),"Miranda Pineda") -> Miranda Pineda | H10: =IFERROR(__xludf.DUMMYFUNCTION("""COMPUTED_VALUE"""),4.845877048E9) -> 4845877048 | I10: =IFERROR(__xludf.DUMMYFUNCTION("""COMPUTED_VALUE"""),"1PM-3PM") -> 1PM-3PM | J10: =IFERROR(__xludf.DUMMYFUNCTION("""COMPUTED_VALUE"""),0.0) -> 0 | K10: =IFERROR(__xludf.DUMMYFUNCTION("""COMPUTED_VALUE"""),"Complete") -> Complete | N10: =IFERROR(__xludf.DUMMYFUNCTION("""COMPUTED_VALUE"""),42.0) -> 42 | P10: =IFERROR(__xludf.DUMMYFUNCTION("""COMPUTED_VALUE"""),"Kit Delivery") -> Kit Delivery | Q10: =IFERROR(__xludf.DUMMYFUNCTION("""COMPUTED_VALUE"""),"double door mini fridge") -> double door mini fridge | T10: =IFERROR(__xludf.DUMMYFUNCTION("""COMPUTED_VALUE"""),46142.69212962963) -> 46142.692
A11: =IFERROR(__xludf.DUMMYFUNCTION("""COMPUTED_VALUE"""),"KIT-#18090") -> KIT-#18090 | B11: =IFERROR(__xludf.DUMMYFUNCTION("""COMPUTED_VALUE"""),46146.0) -> 46146 | C11: =IFERROR(__xludf.DUMMYFUNCTION("""COMPUTED_VALUE"""),"Kit Delivery") -> Kit Delivery | D11: =IFERROR(__xludf.DUMMYFUNCTION("""COMPUTED_VALUE"""),2.0) -> 2 | E11: =IFERROR(__xludf.DUMMYFUNCTION("""COMPUTED_VALUE"""),"Lopata") -> Lopata | F11: =IFERROR(__xludf.DUMMYFUNCTION("""COMPUTED_VALUE"""),3022.0) -> 3022 | G11: =IFERROR(__xludf.DUMMYFUNCTION("""COMPUTED_VALUE"""),"Estelle Rosenblatt") -> Estelle Rosenblatt | H11: =IFERROR(__xludf.DUMMYFUNCTION("""COMPUTED_VALUE"""),8.476916696E9) -> 8476916696 | I11: =IFERROR(__xludf.DUMMYFUNCTION("""COMPUTED_VALUE"""),"11AM-1PM") -> 11AM-1PM | J11: =IFERROR(__xludf.DUMMYFUNCTION("""COMPUTED_VALUE"""),0.0) -> 0 | K11: =IFERROR(__xludf.DUMMYFUNCTION("""COMPUTED_VALUE"""),"Complete") -> Complete | N11: =IFERROR(__xludf.DUMMYFUNCTION("""COMPUTED_VALUE"""),118.0) -> 118 | O11: =IFERROR(__xludf.DUMMYFUNCTION("""COMPUTED_VALUE"""),"2248 Egandale Rd") -> 2248 Egandale Rd | P11: =IFERROR(__xludf.DUMMYFUNCTION("""COMPUTED_VALUE"""),"Kit Delivery") -> Kit Delivery | T11: =IFERROR(__xludf.DUMMYFUNCTION("""COMPUTED_VALUE"""),46142.69212962963) -> 46142.692
A12: =IFERROR(__xludf.DUMMYFUNCTION("""COMPUTED_VALUE"""),"KIT-#17282") -> KIT-#17282 | B12: =IFERROR(__xludf.DUMMYFUNCTION("""COMPUTED_VALUE"""),46146.0) -> 46146 | C12: =IFERROR(__xludf.DUMMYFUNCTION("""COMPUTED_VALUE"""),"Kit Delivery") -> Kit Delivery | D12: =IFERROR(__xludf.DUMMYFUNCTION("""COMPUTED_VALUE"""),1.0) -> 1 | E12: =IFERROR(__xludf.DUMMYFUNCTION("""COMPUTED_VALUE"""),"Dauten") -> Dauten | F12: =IFERROR(__xludf.DUMMYFUNCTION("""COMPUTED_VALUE"""),"242-b") -> 242-b | G12: =IFERROR(__xludf.DUMMYFUNCTION("""COMPUTED_VALUE"""),"Jonah Glass") -> Jonah Glass | H12: =IFERROR(__xludf.DUMMYFUNCTION("""COMPUTED_VALUE"""),9.144326482E9) -> 9144326482 | I12: =IFERROR(__xludf.DUMMYFUNCTION("""COMPUTED_VALUE"""),"11AM-1PM") -> 11AM-1PM | J12: =IFERROR(__xludf.DUMMYFUNCTION("""COMPUTED_VALUE"""),0.0) -> 0 | K12: =IFERROR(__xludf.DUMMYFUNCTION("""COMPUTED_VALUE"""),"Complete") -> Complete | M12: =IFERROR(__xludf.DUMMYFUNCTION("""COMPUTED_VALUE"""),46123.674791666665) -> 46123.675 | N12: =IFERROR(__xludf.DUMMYFUNCTION("""COMPUTED_VALUE"""),82.0) -> 82 | P12: =IFERROR(__xludf.DUMMYFUNCTION("""COMPUTED_VALUE"""),"Kit Delivery") -> Kit Delivery | S12: =IFERROR(__xludf.DUMMYFUNCTION("""COMPUTED_VALUE"""),46123.70133101852) -> 46123.701
A13: =IFERROR(__xludf.DUMMYFUNCTION("""COMPUTED_VALUE"""),"KIT-#17624") -> KIT-#17624 | B13: =IFERROR(__xludf.DUMMYFUNCTION("""COMPUTED_VALUE"""),46147.0) -> 46147 | C13: =IFERROR(__xludf.DUMMYFUNCTION("""COMPUTED_VALUE"""),"Kit Delivery") -> Kit Delivery | D13: =IFERROR(__xludf.DUMMYFUNCTION("""COMPUTED_VALUE"""),2.0) -> 2 | E13: =IFERROR(__xludf.DUMMYFUNCTION("""COMPUTED_VALUE"""),"Park") -> Park | F13: =IFERROR(__xludf.DUMMYFUNCTION("""COMPUTED_VALUE"""),441.0) -> 441 | G13: =IFERROR(__xludf.DUMMYFUNCTION("""COMPUTED_VALUE"""),"Casey Yung") -> Casey Yung | H13: =IFERROR(__xludf.DUMMYFUNCTION("""COMPUTED_VALUE"""),4.153078559E9) -> 4153078559 | I13: =IFERROR(__xludf.DUMMYFUNCTION("""COMPUTED_VALUE"""),"3PM-5PM") -> 3PM-5PM | J13: =IFERROR(__xludf.DUMMYFUNCTION("""COMPUTED_VALUE"""),0.0) -> 0 | K13: =IFERROR(__xludf.DUMMYFUNCTION("""COMPUTED_VALUE"""),"Complete") -> Complete | L13: =IFERROR(__xludf.DUMMYFUNCTION("""COMPUTED_VALUE"""),"0 kits") -> 0 kits | N13: =IFERROR(__xludf.DUMMYFUNCTION("""COMPUTED_VALUE"""),80.0) -> 80 | O13: =IFERROR(__xludf.DUMMYFUNCTION("""COMPUTED_VALUE"""),"18 Warford Ter, Orinda, CA 94563") -> 18 Warford Ter, Orinda, CA 94563 | P13: =IFERROR(__xludf.DUMMYFUNCTION("""COMPUTED_VALUE"""),"Kit Delivery") -> Kit Delivery | Q13: =IFERROR(__xludf.DUMMYFUNCTION("""COMPUTED_VALUE"""),"I already received a kit for summer storage but need some shipping labels for shipping 1-2 boxes home") -> I already received a kit for summer storage but need some shipping labels for shipping 1-2 boxes home | T13: =IFERROR(__xludf.DUMMYFUNCTION("""COMPUTED_VALUE"""),46134.6340625) -> 46134.634
A14: =IFERROR(__xludf.DUMMYFUNCTION("""COMPUTED_VALUE"""),"KIT-#18183") -> KIT-#18183 | B14: =IFERROR(__xludf.DUMMYFUNCTION("""COMPUTED_VALUE"""),46148.0) -> 46148 | C14: =IFERROR(__xludf.DUMMYFUNCTION("""COMPUTED_VALUE"""),"Kit Delivery") -> Kit Delivery | D14: =IFERROR(__xludf.DUMMYFUNCTION("""COMPUTED_VALUE"""),2.0) -> 2 | E14: =IFERROR(__xludf.DUMMYFUNCTION("""COMPUTED_VALUE"""),"Rutledge") -> Rutledge | F14: =IFERROR(__xludf.DUMMYFUNCTION("""COMPUTED_VALUE"""),211.0) -> 211 | G14: =IFERROR(__xludf.DUMMYFUNCTION("""COMPUTED_VALUE"""),"Yuxuan Xu") -> Yuxuan Xu | H14: =IFERROR(__xludf.DUMMYFUNCTION("""COMPUTED_VALUE"""),3.1429609E9) -> 3142960900 | I14: =IFERROR(__xludf.DUMMYFUNCTION("""COMPUTED_VALUE"""),"3PM-5PM") -> 3PM-5PM | J14: =IFERROR(__xludf.DUMMYFUNCTION("""COMPUTED_VALUE"""),0.0) -> 0 | K14: =IFERROR(__xludf.DUMMYFUNCTION("""COMPUTED_VALUE"""),"Complete") -> Complete | L14: =IFERROR(__xludf.DUMMYFUNCTION("""COMPUTED_VALUE"""),"0 kits") -> 0 kits | M14: =IFERROR(__xludf.DUMMYFUNCTION("""COMPUTED_VALUE"""),46145.5777662037) -> 46145.578 | N14: =IFERROR(__xludf.DUMMYFUNCTION("""COMPUTED_VALUE"""),11.0) -> 11 | P14: =IFERROR(__xludf.DUMMYFUNCTION("""COMPUTED_VALUE"""),"Kit Delivery") -> Kit Delivery | S14: =IFERROR(__xludf.DUMMYFUNCTION("""COMPUTED_VALUE"""),"Dispatch_Images/KIT--18183.Photos.185155.jpg") -> Dispatch_Images/KIT--18183.Photos.185155.jpg | T14: =IFERROR(__xludf.DUMMYFUNCTION("""COMPUTED_VALUE"""),46145.58099537037) -> 46145.581
A15: =IFERROR(__xludf.DUMMYFUNCTION("""COMPUTED_VALUE"""),"KIT-#17417") -> KIT-#17417 | B15: =IFERROR(__xludf.DUMMYFUNCTION("""COMPUTED_VALUE"""),46149.0) -> 46149 | C15: =IFERROR(__xludf.DUMMYFUNCTION("""COMPUTED_VALUE"""),"Kit Delivery") -> Kit Delivery | D15: =IFERROR(__xludf.DUMMYFUNCTION("""COMPUTED_VALUE"""),1.0) -> 1 | E15: =IFERROR(__xludf.DUMMYFUNCTION("""COMPUTED_VALUE"""),"Shanedling") -> Shanedling | F15: =IFERROR(__xludf.DUMMYFUNCTION("""COMPUTED_VALUE"""),433.0) -> 433 | G15: =IFERROR(__xludf.DUMMYFUNCTION("""COMPUTED_VALUE"""),"Zachary Bergman") -> Zachary Bergman | H15: =IFERROR(__xludf.DUMMYFUNCTION("""COMPUTED_VALUE"""),6.787839777E9) -> 6787839777 | I15: =IFERROR(__xludf.DUMMYFUNCTION("""COMPUTED_VALUE"""),"1PM-3PM") -> 1PM-3PM | J15: =IFERROR(__xludf.DUMMYFUNCTION("""COMPUTED_VALUE"""),0.0) -> 0 | K15: =IFERROR(__xludf.DUMMYFUNCTION("""COMPUTED_VALUE"""),"Complete") -> Complete | N15: =IFERROR(__xludf.DUMMYFUNCTION("""COMPUTED_VALUE"""),116.0) -> 116 | P15: =IFERROR(__xludf.DUMMYFUNCTION("""COMPUTED_VALUE"""),"Kit Delivery") -> Kit Delivery | T15: =IFERROR(__xludf.DUMMYFUNCTION("""COMPUTED_VALUE"""),46130.474340277775) -> 46130.474
A16: =IFERROR(__xludf.DUMMYFUNCTION("""COMPUTED_VALUE"""),"KIT-#18122") -> KIT-#18122 | B16: =IFERROR(__xludf.DUMMYFUNCTION("""COMPUTED_VALUE"""),46150.0) -> 46150 | C16: =IFERROR(__xludf.DUMMYFUNCTION("""COMPUTED_VALUE"""),"Kit Delivery") -> Kit Delivery | D16: =IFERROR(__xludf.DUMMYFUNCTION("""COMPUTED_VALUE"""),2.0) -> 2 | E16: =IFERROR(__xludf.DUMMYFUNCTION("""COMPUTED_VALUE"""),"House 1") -> House 1 | F16: =IFERROR(__xludf.DUMMYFUNCTION("""COMPUTED_VALUE"""),117.0) -> 117 | G16: =IFERROR(__xludf.DUMMYFUNCTION("""COMPUTED_VALUE"""),"Hao") -> Hao | H16: =IFERROR(__xludf.DUMMYFUNCTION("""COMPUTED_VALUE"""),6.46203634E9) -> 6462036340 | I16: =IFERROR(__xludf.DUMMYFUNCTION("""COMPUTED_VALUE"""),"9AM-11AM") -> 9AM-11AM | J16: =IFERROR(__xludf.DUMMYFUNCTION("""COMPUTED_VALUE"""),0.0) -> 0 | K16: =IFERROR(__xludf.DUMMYFUNCTION("""COMPUTED_VALUE"""),"Complete") -> Complete | L16: =IFERROR(__xludf.DUMMYFUNCTION("""COMPUTED_VALUE"""),"0 kits") -> 0 kits | M16: =IFERROR(__xludf.DUMMYFUNCTION("""COMPUTED_VALUE"""),46145.57760416667) -> 46145.578 | N16: =IFERROR(__xludf.DUMMYFUNCTION("""COMPUTED_VALUE"""),36.0) -> 36 | P16: =IFERROR(__xludf.DUMMYFUNCTION("""COMPUTED_VALUE"""),"Kit Delivery") -> Kit Delivery | S16: =IFERROR(__xludf.DUMMYFUNCTION("""COMPUTED_VALUE"""),"Dispatch_Images/KIT--18122.Photos.185141.jpg") -> Dispatch_Images/KIT--18122.Photos.185141.jpg | T16: =IFERROR(__xludf.DUMMYFUNCTION("""COMPUTED_VALUE"""),46145.58099537037) -> 46145.581
A17: =IFERROR(__xludf.DUMMYFUNCTION("""COMPUTED_VALUE"""),"KIT-#17074") -> KIT-#17074 | B17: =IFERROR(__xludf.DUMMYFUNCTION("""COMPUTED_VALUE"""),46151.0) -> 46151 | C17: =IFERROR(__xludf.DUMMYFUNCTION("""COMPUTED_VALUE"""),"Kit Delivery") -> Kit Delivery | D17: =IFERROR(__xludf.DUMMYFUNCTION("""COMPUTED_VALUE"""),2.0) -> 2 | E17: =IFERROR(__xludf.DUMMYFUNCTION("""COMPUTED_VALUE"""),"Umrath") -> Umrath | F17: =IFERROR(__xludf.DUMMYFUNCTION("""COMPUTED_VALUE"""),4403.0) -> 4403 | G17: =IFERROR(__xludf.DUMMYFUNCTION("""COMPUTED_VALUE"""),"Allison Pearl") -> Allison Pearl | H17: =IFERROR(__xludf.DUMMYFUNCTION("""COMPUTED_VALUE"""),6.163282714E9) -> 6163282714 | I17: =IFERROR(__xludf.DUMMYFUNCTION("""COMPUTED_VALUE"""),"10AM-12PM") -> 10AM-12PM | J17: =IFERROR(__xludf.DUMMYFUNCTION("""COMPUTED_VALUE"""),0.0) -> 0 | K17: =IFERROR(__xludf.DUMMYFUNCTION("""COMPUTED_VALUE"""),"Complete") -> Complete | M17: =IFERROR(__xludf.DUMMYFUNCTION("""COMPUTED_VALUE"""),46129.890555555554) -> 46129.891 | N17: =IFERROR(__xludf.DUMMYFUNCTION("""COMPUTED_VALUE"""),174.0) -> 174 | P17: =IFERROR(__xludf.DUMMYFUNCTION("""COMPUTED_VALUE"""),"Kit Delivery") -> Kit Delivery | S17: =IFERROR(__xludf.DUMMYFUNCTION("""COMPUTED_VALUE"""),"Dispatch_Images/KIT--17074.Photos.022221.jpg") -> Dispatch_Images/KIT--17074.Photos.022221.jpg | T17: =IFERROR(__xludf.DUMMYFUNCTION("""COMPUTED_VALUE"""),46129.89100694445) -> 46129.891
A18: =IFERROR(__xludf.DUMMYFUNCTION("""COMPUTED_VALUE"""),"KIT-#17101") -> KIT-#17101 | B18: =IFERROR(__xludf.DUMMYFUNCTION("""COMPUTED_VALUE"""),46158.0) -> 46158 | C18: =IFERROR(__xludf.DUMMYFUNCTION("""COMPUTED_VALUE"""),"Kit Delivery") -> Kit Delivery | D18: =IFERROR(__xludf.DUMMYFUNCTION("""COMPUTED_VALUE"""),2.0) -> 2 | E18: =IFERROR(__xludf.DUMMYFUNCTION("""COMPUTED_VALUE"""),"Greenway Apartments") -> Greenway Apartments | F18: =IFERROR(__xludf.DUMMYFUNCTION("""COMPUTED_VALUE"""),"324B") -> 324B | G18: =IFERROR(__xludf.DUMMYFUNCTION("""COMPUTED_VALUE"""),"Helen Ives") -> Helen Ives | H18: =IFERROR(__xludf.DUMMYFUNCTION("""COMPUTED_VALUE"""),8.572188168E9) -> 8572188168 | I18: =IFERROR(__xludf.DUMMYFUNCTION("""COMPUTED_VALUE"""),"3PM-5PM") -> 3PM-5PM | J18: =IFERROR(__xludf.DUMMYFUNCTION("""COMPUTED_VALUE"""),0.0) -> 0 | K18: =IFERROR(__xludf.DUMMYFUNCTION("""COMPUTED_VALUE"""),"Complete") -> Complete | L18: =IFERROR(__xludf.DUMMYFUNCTION("""COMPUTED_VALUE"""),"0 kits") -> 0 kits | N18: =IFERROR(__xludf.DUMMYFUNCTION("""COMPUTED_VALUE"""),287.0) -> 287 | O18: =IFERROR(__xludf.DUMMYFUNCTION("""COMPUTED_VALUE"""),"23 Monmouth Street Brookline, Massachusetts 02446") -> 23 Monmouth Street Brookline, Massachusetts 02446 | P18: =IFERROR(__xludf.DUMMYFUNCTION("""COMPUTED_VALUE"""),"Kit Delivery") -> Kit Delivery | T18: =IFERROR(__xludf.DUMMYFUNCTION("""COMPUTED_VALUE"""),46134.6340625) -> 46134.634
A19: =IFERROR(__xludf.DUMMYFUNCTION("""COMPUTED_VALUE"""),"KIT-#17572") -> KIT-#17572 | B19: =IFERROR(__xludf.DUMMYFUNCTION("""COMPUTED_VALUE"""),46160.0) -> 46160 | C19: =IFERROR(__xludf.DUMMYFUNCTION("""COMPUTED_VALUE"""),"Kit Delivery") -> Kit Delivery | D19: =IFERROR(__xludf.DUMMYFUNCTION("""COMPUTED_VALUE"""),1.0) -> 1 | E19: =IFERROR(__xludf.DUMMYFUNCTION("""COMPUTED_VALUE"""),"Off-Campus") -> Off-Campus | G19: =IFERROR(__xludf.DUMMYFUNCTION("""COMPUTED_VALUE"""),"Sam Modlinger") -> Sam Modlinger | H19: =IFERROR(__xludf.DUMMYFUNCTION("""COMPUTED_VALUE"""),6.467570626E9) -> 6467570626 | I19: =IFERROR(__xludf.DUMMYFUNCTION("""COMPUTED_VALUE"""),"10AM-12PM") -> 10AM-12PM | J19: =IFERROR(__xludf.DUMMYFUNCTION("""COMPUTED_VALUE"""),0.0) -> 0 | K19: =IFERROR(__xludf.DUMMYFUNCTION("""COMPUTED_VALUE"""),"Complete") -> Complete | N19: =IFERROR(__xludf.DUMMYFUNCTION("""COMPUTED_VALUE"""),350.0) -> 350 | O19: =IFERROR(__xludf.DUMMYFUNCTION("""COMPUTED_VALUE"""),"6127 waterman blvd") -> 6127 waterman blvd | P19: =IFERROR(__xludf.DUMMYFUNCTION("""COMPUTED_VALUE"""),"Kit Delivery") -> Kit Delivery | T19: =IFERROR(__xludf.DUMMYFUNCTION("""COMPUTED_VALUE"""),46130.474340277775) -> 46130.474
A20: =IFERROR(__xludf.DUMMYFUNCTION("""COMPUTED_VALUE"""),"KIT-#17408") -> KIT-#17408 | B20: =IFERROR(__xludf.DUMMYFUNCTION("""COMPUTED_VALUE"""),46125.0) -> 46125 | C20: =IFERROR(__xludf.DUMMYFUNCTION("""COMPUTED_VALUE"""),"Kit Delivery") -> Kit Delivery | D20: =IFERROR(__xludf.DUMMYFUNCTION("""COMPUTED_VALUE"""),1.0) -> 1 | E20: =IFERROR(__xludf.DUMMYFUNCTION("""COMPUTED_VALUE"""),"LL6200") -> LL6200 | F20: =IFERROR(__xludf.DUMMYFUNCTION("""COMPUTED_VALUE"""),"111B") -> 111B | G20: =IFERROR(__xludf.DUMMYFUNCTION("""COMPUTED_VALUE"""),"Chelsea Smalling") -> Chelsea Smalling | H20: =IFERROR(__xludf.DUMMYFUNCTION("""COMPUTED_VALUE"""),7.542642584E9) -> 7542642584 | I20: =IFERROR(__xludf.DUMMYFUNCTION("""COMPUTED_VALUE"""),"2PM-4PM") -> 2PM-4PM | J20: =IFERROR(__xludf.DUMMYFUNCTION("""COMPUTED_VALUE"""),2.0) -> 2 | K20: =IFERROR(__xludf.DUMMYFUNCTION("""COMPUTED_VALUE"""),"Complete") -> Complete | M20: =IFERROR(__xludf.DUMMYFUNCTION("""COMPUTED_VALUE"""),46122.83730324074) -> 46122.837 | N20: =IFERROR(__xludf.DUMMYFUNCTION("""COMPUTED_VALUE"""),205.0) -> 205 | P20: =IFERROR(__xludf.DUMMYFUNCTION("""COMPUTED_VALUE"""),"Kit Delivery") -> Kit Delivery | S20: =IFERROR(__xludf.DUMMYFUNCTION("""COMPUTED_VALUE"""),46122.84841435185) -> 46122.848 | U20: =IFERROR(__xludf.DUMMYFUNCTION("""COMPUTED_VALUE"""),"#REF!") -> #REF!
A21: =IFERROR(__xludf.DUMMYFUNCTION("""COMPUTED_VALUE"""),"KIT-#17492") -> KIT-#17492 | B21: =IFERROR(__xludf.DUMMYFUNCTION("""COMPUTED_VALUE"""),46128.0) -> 46128 | C21: =IFERROR(__xludf.DUMMYFUNCTION("""COMPUTED_VALUE"""),"Kit Delivery") -> Kit Delivery | D21: =IFERROR(__xludf.DUMMYFUNCTION("""COMPUTED_VALUE"""),2.0) -> 2 | E21: =IFERROR(__xludf.DUMMYFUNCTION("""COMPUTED_VALUE"""),"Rutledge") -> Rutledge | F21: =IFERROR(__xludf.DUMMYFUNCTION("""COMPUTED_VALUE"""),"242A") -> 242A | G21: =IFERROR(__xludf.DUMMYFUNCTION("""COMPUTED_VALUE"""),"David Kern") -> David Kern | H21: =IFERROR(__xludf.DUMMYFUNCTION("""COMPUTED_VALUE"""),9.176968178E9) -> 9176968178 | I21: =IFERROR(__xludf.DUMMYFUNCTION("""COMPUTED_VALUE"""),"2PM-4PM") -> 2PM-4PM | J21: =IFERROR(__xludf.DUMMYFUNCTION("""COMPUTED_VALUE"""),1.0) -> 1 | K21: =IFERROR(__xludf.DUMMYFUNCTION("""COMPUTED_VALUE"""),"Complete") -> Complete | M21: =IFERROR(__xludf.DUMMYFUNCTION("""COMPUTED_VALUE"""),46125.84377314815) -> 46125.844 | N21: =IFERROR(__xludf.DUMMYFUNCTION("""COMPUTED_VALUE"""),71.0) -> 71 | P21: =IFERROR(__xludf.DUMMYFUNCTION("""COMPUTED_VALUE"""),"Kit Delivery") -> Kit Delivery | Q21: =IFERROR(__xludf.DUMMYFUNCTION("""COMPUTED_VALUE"""),"Summer storage") -> Summer storage | S21: =IFERROR(__xludf.DUMMYFUNCTION("""COMPUTED_VALUE"""),"Dispatch_Photos/KIT--17492/KIT--17492.Photo.011457.jpg") -> Dispatch_Photos/KIT--17492/KIT--17492.Photo.011457.jpg | T21: =IFERROR(__xludf.DUMMYFUNCTION("""COMPUTED_VALUE"""),46125.849328703705) -> 46125.849 | U21: =IFERROR(__xludf.DUMMYFUNCTION("""COMPUTED_VALUE"""),"#17492") -> #17492
A22: =IFERROR(__xludf.DUMMYFUNCTION("""COMPUTED_VALUE"""),"KIT-#17591") -> KIT-#17591 | B22: =IFERROR(__xludf.DUMMYFUNCTION("""COMPUTED_VALUE"""),46134.0) -> 46134 | C22: =IFERROR(__xludf.DUMMYFUNCTION("""COMPUTED_VALUE"""),"Kit Delivery") -> Kit Delivery | D22: =IFERROR(__xludf.DUMMYFUNCTION("""COMPUTED_VALUE"""),1.0) -> 1 | E22: =IFERROR(__xludf.DUMMYFUNCTION("""COMPUTED_VALUE"""),"Beaumont") -> Beaumont | F22: =IFERROR(__xludf.DUMMYFUNCTION("""COMPUTED_VALUE"""),207.0) -> 207 | G22: =IFERROR(__xludf.DUMMYFUNCTION("""COMPUTED_VALUE"""),"Tom Wang") -> Tom Wang | H22: =IFERROR(__xludf.DUMMYFUNCTION("""COMPUTED_VALUE"""),3.142241746E9) -> 3142241746 | I22: =IFERROR(__xludf.DUMMYFUNCTION("""COMPUTED_VALUE"""),"3PM-5PM") -> 3PM-5PM | J22: =IFERROR(__xludf.DUMMYFUNCTION("""COMPUTED_VALUE"""),2.0) -> 2 | K22: =IFERROR(__xludf.DUMMYFUNCTION("""COMPUTED_VALUE"""),"Complete") -> Complete | M22: =IFERROR(__xludf.DUMMYFUNCTION("""COMPUTED_VALUE"""),46133.775775462964) -> 46133.776 | N22: =IFERROR(__xludf.DUMMYFUNCTION("""COMPUTED_VALUE"""),11.0) -> 11 | P22: =IFERROR(__xludf.DUMMYFUNCTION("""COMPUTED_VALUE"""),"Kit Delivery") -> Kit Delivery | S22: =IFERROR(__xludf.DUMMYFUNCTION("""COMPUTED_VALUE"""),"Dispatch_Images/KIT--17591.Photos.233703.jpg") -> Dispatch_Images/KIT--17591.Photos.233703.jpg | T22: =IFERROR(__xludf.DUMMYFUNCTION("""COMPUTED_VALUE"""),46133.77988425926) -> 46133.78
A23: =IFERROR(__xludf.DUMMYFUNCTION("""COMPUTED_VALUE"""),"KIT-#17363") -> KIT-#17363 | B23: =IFERROR(__xludf.DUMMYFUNCTION("""COMPUTED_VALUE"""),46136.0) -> 46136 | C23: =IFERROR(__xludf.DUMMYFUNCTION("""COMPUTED_VALUE"""),"Kit Delivery") -> Kit Delivery | D23: =IFERROR(__xludf.DUMMYFUNCTION("""COMPUTED_VALUE"""),1.0) -> 1 | E23: =IFERROR(__xludf.DUMMYFUNCTION("""COMPUTED_VALUE"""),"Millbrook Bldg. 2") -> Millbrook Bldg. 2 | F23: =IFERROR(__xludf.DUMMYFUNCTION("""COMPUTED_VALUE"""),"203C") -> 203C | G23: =IFERROR(__xludf.DUMMYFUNCTION("""COMPUTED_VALUE"""),"Doyoon Kim") -> Doyoon Kim | H23: =IFERROR(__xludf.DUMMYFUNCTION("""COMPUTED_VALUE"""),1.039438367E9) -> 1039438367 | I23: =IFERROR(__xludf.DUMMYFUNCTION("""COMPUTED_VALUE"""),"9AM-11AM") -> 9AM-11AM | J23: =IFERROR(__xludf.DUMMYFUNCTION("""COMPUTED_VALUE"""),1.0) -> 1 | K23: =IFERROR(__xludf.DUMMYFUNCTION("""COMPUTED_VALUE"""),"Complete") -> Complete | M23: =IFERROR(__xludf.DUMMYFUNCTION("""COMPUTED_VALUE"""),46123.97975694445) -> 46123.98 | N23: =IFERROR(__xludf.DUMMYFUNCTION("""COMPUTED_VALUE"""),188.0) -> 188 | P23: =IFERROR(__xludf.DUMMYFUNCTION("""COMPUTED_VALUE"""),"Kit Delivery") -> Kit Delivery | S23: =IFERROR(__xludf.DUMMYFUNCTION("""COMPUTED_VALUE"""),46124.4096875) -> 46124.41
A24: =IFERROR(__xludf.DUMMYFUNCTION("""COMPUTED_VALUE"""),"KIT-#17075") -> KIT-#17075 | B24: =IFERROR(__xludf.DUMMYFUNCTION("""COMPUTED_VALUE"""),46137.0) -> 46137 | C24: =IFERROR(__xludf.DUMMYFUNCTION("""COMPUTED_VALUE"""),"Kit Delivery") -> Kit Delivery | D24: =IFERROR(__xludf.DUMMYFUNCTION("""COMPUTED_VALUE"""),1.0) -> 1 | E24: =IFERROR(__xludf.DUMMYFUNCTION("""COMPUTED_VALUE"""),"Danforth") -> Danforth | F24: =IFERROR(__xludf.DUMMYFUNCTION("""COMPUTED_VALUE"""),3304.0) -> 3304 | G24: =IFERROR(__xludf.DUMMYFUNCTION("""COMPUTED_VALUE"""),"Benjamin Schwed") -> Benjamin Schwed | H24: =IFERROR(__xludf.DUMMYFUNCTION("""COMPUTED_VALUE"""),5.163590784E9) -> 5163590784 | I24: =IFERROR(__xludf.DUMMYFUNCTION("""COMPUTED_VALUE"""),"3PM-5PM") -> 3PM-5PM | J24: =IFERROR(__xludf.DUMMYFUNCTION("""COMPUTED_VALUE"""),1.0) -> 1 | K24: =IFERROR(__xludf.DUMMYFUNCTION("""COMPUTED_VALUE"""),"Complete") -> Complete | M24: =IFERROR(__xludf.DUMMYFUNCTION("""COMPUTED_VALUE"""),46123.56894675926) -> 46123.569 | N24: =IFERROR(__xludf.DUMMYFUNCTION("""COMPUTED_VALUE"""),30.0) -> 30 | P24: =IFERROR(__xludf.DUMMYFUNCTION("""COMPUTED_VALUE"""),"Kit Delivery") -> Kit Delivery | S24: =IFERROR(__xludf.DUMMYFUNCTION("""COMPUTED_VALUE"""),46123.61150462963) -> 46123.611
A25: =IFERROR(__xludf.DUMMYFUNCTION("""COMPUTED_VALUE"""),"KIT-#17541") -> KIT-#17541 | B25: =IFERROR(__xludf.DUMMYFUNCTION("""COMPUTED_VALUE"""),46137.0) -> 46137 | C25: =IFERROR(__xludf.DUMMYFUNCTION("""COMPUTED_VALUE"""),"Kit Delivery") -> Kit Delivery | D25: =IFERROR(__xludf.DUMMYFUNCTION("""COMPUTED_VALUE"""),2.0) -> 2 | E25: =IFERROR(__xludf.DUMMYFUNCTION("""COMPUTED_VALUE"""),"Umrath") -> Umrath | F25: =IFERROR(__xludf.DUMMYFUNCTION("""COMPUTED_VALUE"""),2235.0) -> 2235 | G25: =IFERROR(__xludf.DUMMYFUNCTION("""COMPUTED_VALUE"""),"Giovanna Springer") -> Giovanna Springer | H25: =IFERROR(__xludf.DUMMYFUNCTION("""COMPUTED_VALUE"""),9.174471523E9) -> 9174471523 | I25: =IFERROR(__xludf.DUMMYFUNCTION("""COMPUTED_VALUE"""),"9AM-11AM") -> 9AM-11AM | J25: =IFERROR(__xludf.DUMMYFUNCTION("""COMPUTED_VALUE"""),1.0) -> 1 | K25: =IFERROR(__xludf.DUMMYFUNCTION("""COMPUTED_VALUE"""),"Complete") -> Complete | M25: =IFERROR(__xludf.DUMMYFUNCTION("""COMPUTED_VALUE"""),46129.88265046296) -> 46129.883 | N25: =IFERROR(__xludf.DUMMYFUNCTION("""COMPUTED_VALUE"""),162.0) -> 162 | P25: =IFERROR(__xludf.DUMMYFUNCTION("""COMPUTED_VALUE"""),"Kit Delivery") -> Kit Delivery | S25: =IFERROR(__xludf.DUMMYFUNCTION("""COMPUTED_VALUE"""),"Dispatch_Images/KIT--17541.Photos.021057.jpg") -> Dispatch_Images/KIT--17541.Photos.021057.jpg | T25: =IFERROR(__xludf.DUMMYFUNCTION("""COMPUTED_VALUE"""),46129.884050925924) -> 46129.884
A26: =IFERROR(__xludf.DUMMYFUNCTION("""COMPUTED_VALUE"""),"KIT-#17536") -> KIT-#17536 | B26: =IFERROR(__xludf.DUMMYFUNCTION("""COMPUTED_VALUE"""),46137.0) -> 46137 | C26: =IFERROR(__xludf.DUMMYFUNCTION("""COMPUTED_VALUE"""),"Kit Delivery") -> Kit Delivery | D26: =IFERROR(__xludf.DUMMYFUNCTION("""COMPUTED_VALUE"""),2.0) -> 2 | E26: =IFERROR(__xludf.DUMMYFUNCTION("""COMPUTED_VALUE"""),"Danforth") -> Danforth | F26: =IFERROR(__xludf.DUMMYFUNCTION("""COMPUTED_VALUE"""),4415.0) -> 4415 | G26: =IFERROR(__xludf.DUMMYFUNCTION("""COMPUTED_VALUE"""),"Claire Rigdon") -> Claire Rigdon | H26: =IFERROR(__xludf.DUMMYFUNCTION("""COMPUTED_VALUE"""),2.152018284E9) -> 2152018284 | I26: =IFERROR(__xludf.DUMMYFUNCTION("""COMPUTED_VALUE"""),"3PM-5PM") -> 3PM-5PM | J26: =IFERROR(__xludf.DUMMYFUNCTION("""COMPUTED_VALUE"""),1.0) -> 1 | K26: =IFERROR(__xludf.DUMMYFUNCTION("""COMPUTED_VALUE"""),"Complete") -> Complete | M26: =IFERROR(__xludf.DUMMYFUNCTION("""COMPUTED_VALUE"""),46129.91130787037) -> 46129.911 | N26: =IFERROR(__xludf.DUMMYFUNCTION("""COMPUTED_VALUE"""),45.0) -> 45 | P26: =IFERROR(__xludf.DUMMYFUNCTION("""COMPUTED_VALUE"""),"Kit Delivery") -> Kit Delivery | S26: =IFERROR(__xludf.DUMMYFUNCTION("""COMPUTED_VALUE"""),"Dispatch_Images/KIT--17536.Photos.025214.jpg") -> Dispatch_Images/KIT--17536.Photos.025214.jpg | T26: =IFERROR(__xludf.DUMMYFUNCTION("""COMPUTED_VALUE"""),46129.911840277775) -> 46129.912
A27: =IFERROR(__xludf.DUMMYFUNCTION("""COMPUTED_VALUE"""),"KIT-#17685") -> KIT-#17685 | B27: =IFERROR(__xludf.DUMMYFUNCTION("""COMPUTED_VALUE"""),46137.0) -> 46137 | C27: =IFERROR(__xludf.DUMMYFUNCTION("""COMPUTED_VALUE"""),"Kit Delivery") -> Kit Delivery | D27: =IFERROR(__xludf.DUMMYFUNCTION("""COMPUTED_VALUE"""),2.0) -> 2 | E27: =IFERROR(__xludf.DUMMYFUNCTION("""COMPUTED_VALUE"""),"Hitzeman") -> Hitzeman | F27: =IFERROR(__xludf.DUMMYFUNCTION("""COMPUTED_VALUE"""),22.0) -> 22 | G27: =IFERROR(__xludf.DUMMYFUNCTION("""COMPUTED_VALUE"""),"Kelly Zhang*") -> Kelly Zhang* | H27: =IFERROR(__xludf.DUMMYFUNCTION("""COMPUTED_VALUE"""),3.142242038E9) -> 3142242038 | I27: =IFERROR(__xludf.DUMMYFUNCTION("""COMPUTED_VALUE"""),"10AM-12PM") -> 10AM-12PM | J27: =IFERROR(__xludf.DUMMYFUNCTION("""COMPUTED_VALUE"""),1.0) -> 1 | K27: =IFERROR(__xludf.DUMMYFUNCTION("""COMPUTED_VALUE"""),"Complete") -> Complete | M27: =IFERROR(__xludf.DUMMYFUNCTION("""COMPUTED_VALUE"""),46134.75690972222) -> 46134.757 | N27: =IFERROR(__xludf.DUMMYFUNCTION("""COMPUTED_VALUE"""),2.0) -> 2 | P27: =IFERROR(__xludf.DUMMYFUNCTION("""COMPUTED_VALUE"""),"Kit Delivery") -> Kit Delivery | S27: =IFERROR(__xludf.DUMMYFUNCTION("""COMPUTED_VALUE"""),"Dispatch_Images/KIT--17685.Photos.230954.jpg") -> Dispatch_Images/KIT--17685.Photos.230954.jpg | T27: =IFERROR(__xludf.DUMMYFUNCTION("""COMPUTED_VALUE"""),46134.75907407407) -> 46134.759
A28: =IFERROR(__xludf.DUMMYFUNCTION("""COMPUTED_VALUE"""),"KIT-#17714") -> KIT-#17714 | B28: =IFERROR(__xludf.DUMMYFUNCTION("""COMPUTED_VALUE"""),46137.0) -> 46137 | C28: =IFERROR(__xludf.DUMMYFUNCTION("""COMPUTED_VALUE"""),"Kit Delivery") -> Kit Delivery | D28: =IFERROR(__xludf.DUMMYFUNCTION("""COMPUTED_VALUE"""),2.0) -> 2 | E28: =IFERROR(__xludf.DUMMYFUNCTION("""COMPUTED_VALUE"""),"Dardick") -> Dardick | F28: =IFERROR(__xludf.DUMMYFUNCTION("""COMPUTED_VALUE"""),4420.0) -> 4420 | G28: =IFERROR(__xludf.DUMMYFUNCTION("""COMPUTED_VALUE"""),"Evie Frohsin") -> Evie Frohsin | H28: =IFERROR(__xludf.DUMMYFUNCTION("""COMPUTED_VALUE"""),2.058954063E9) -> 2058954063 | I28: =IFERROR(__xludf.DUMMYFUNCTION("""COMPUTED_VALUE"""),"12PM-2PM") -> 12PM-2PM | J28: =IFERROR(__xludf.DUMMYFUNCTION("""COMPUTED_VALUE"""),1.0) -> 1 | K28: =IFERROR(__xludf.DUMMYFUNCTION("""COMPUTED_VALUE"""),"Complete") -> Complete | M28: =IFERROR(__xludf.DUMMYFUNCTION("""COMPUTED_VALUE"""),46136.575162037036) -> 46136.575 | N28: =IFERROR(__xludf.DUMMYFUNCTION("""COMPUTED_VALUE"""),109.0) -> 109 | P28: =IFERROR(__xludf.DUMMYFUNCTION("""COMPUTED_VALUE"""),"Kit Delivery") -> Kit Delivery | S28: =IFERROR(__xludf.DUMMYFUNCTION("""COMPUTED_VALUE"""),"Dispatch_Images/KIT--17714.Photos.184810.jpg") -> Dispatch_Images/KIT--17714.Photos.184810.jpg | T28: =IFERROR(__xludf.DUMMYFUNCTION("""COMPUTED_VALUE"""),46136.57850694445) -> 46136.579
A29: =IFERROR(__xludf.DUMMYFUNCTION("""COMPUTED_VALUE"""),"KIT-#17149") -> KIT-#17149 | B29: =IFERROR(__xludf.DUMMYFUNCTION("""COMPUTED_VALUE"""),46139.0) -> 46139 | C29: =IFERROR(__xludf.DUMMYFUNCTION("""COMPUTED_VALUE"""),"Kit Delivery") -> Kit Delivery | D29: =IFERROR(__xludf.DUMMYFUNCTION("""COMPUTED_VALUE"""),1.0) -> 1 | E29: =IFERROR(__xludf.DUMMYFUNCTION("""COMPUTED_VALUE"""),"Lee") -> Lee | F29: =IFERROR(__xludf.DUMMYFUNCTION("""COMPUTED_VALUE"""),"Ground Floor 006") -> Ground Floor 006 | G29: =IFERROR(__xludf.DUMMYFUNCTION("""COMPUTED_VALUE"""),"Crystal Liu") -> Crystal Liu | H29: =IFERROR(__xludf.DUMMYFUNCTION("""COMPUTED_VALUE"""),7.812268576E9) -> 7812268576 | I29: =IFERROR(__xludf.DUMMYFUNCTION("""COMPUTED_VALUE"""),"9AM-11AM") -> 9AM-11AM | J29: =IFERROR(__xludf.DUMMYFUNCTION("""COMPUTED_VALUE"""),1.0) -> 1 | K29: =IFERROR(__xludf.DUMMYFUNCTION("""COMPUTED_VALUE"""),"Complete") -> Complete | M29: =IFERROR(__xludf.DUMMYFUNCTION("""COMPUTED_VALUE"""),46123.7647337963) -> 46123.765 | N29: =IFERROR(__xludf.DUMMYFUNCTION("""COMPUTED_VALUE"""),61.0) -> 61 | P29: =IFERROR(__xludf.DUMMYFUNCTION("""COMPUTED_VALUE"""),"Kit Delivery") -> Kit Delivery | S29: =IFERROR(__xludf.DUMMYFUNCTION("""COMPUTED_VALUE"""),46123.796273148146) -> 46123.796
A30: =IFERROR(__xludf.DUMMYFUNCTION("""COMPUTED_VALUE"""),"KIT-#17364") -> KIT-#17364 | B30: =IFERROR(__xludf.DUMMYFUNCTION("""COMPUTED_VALUE"""),46139.0) -> 46139 | C30: =IFERROR(__xludf.DUMMYFUNCTION("""COMPUTED_VALUE"""),"Kit Delivery") -> Kit Delivery | D30: =IFERROR(__xludf.DUMMYFUNCTION("""COMPUTED_VALUE"""),1.0) -> 1 | E30: =IFERROR(__xludf.DUMMYFUNCTION("""COMPUTED_VALUE"""),"Eliot A") -> Eliot A | F30: =IFERROR(__xludf.DUMMYFUNCTION("""COMPUTED_VALUE"""),2052.0) -> 2052 | G30: =IFERROR(__xludf.DUMMYFUNCTION("""COMPUTED_VALUE"""),"Ava Ayad") -> Ava Ayad | H30: =IFERROR(__xludf.DUMMYFUNCTION("""COMPUTED_VALUE"""),8.172395173E9) -> 8172395173 | I30: =IFERROR(__xludf.DUMMYFUNCTION("""COMPUTED_VALUE"""),"3PM-5PM") -> 3PM-5PM | J30: =IFERROR(__xludf.DUMMYFUNCTION("""COMPUTED_VALUE"""),2.0) -> 2 | K30: =IFERROR(__xludf.DUMMYFUNCTION("""COMPUTED_VALUE"""),"Complete") -> Complete | M30: =IFERROR(__xludf.DUMMYFUNCTION("""COMPUTED_VALUE"""),46123.87986111111) -> 46123.88 | N30: =IFERROR(__xludf.DUMMYFUNCTION("""COMPUTED_VALUE"""),22.0) -> 22 | P30: =IFERROR(__xludf.DUMMYFUNCTION("""COMPUTED_VALUE"""),"Kit Delivery") -> Kit Delivery | S30: =IFERROR(__xludf.DUMMYFUNCTION("""COMPUTED_VALUE"""),46124.4096875) -> 46124.41
A31: =IFERROR(__xludf.DUMMYFUNCTION("""COMPUTED_VALUE"""),"KIT-#17147") -> KIT-#17147 | B31: =IFERROR(__xludf.DUMMYFUNCTION("""COMPUTED_VALUE"""),46139.0) -> 46139 | C31: =IFERROR(__xludf.DUMMYFUNCTION("""COMPUTED_VALUE"""),"Kit Delivery") -> Kit Delivery | D31: =IFERROR(__xludf.DUMMYFUNCTION("""COMPUTED_VALUE"""),1.0) -> 1 | E31: =IFERROR(__xludf.DUMMYFUNCTION("""COMPUTED_VALUE"""),"Eliot A") -> Eliot A | F31: =IFERROR(__xludf.DUMMYFUNCTION("""COMPUTED_VALUE"""),"Lower Level 0403") -> Lower Level 0403 | G31: =IFERROR(__xludf.DUMMYFUNCTION("""COMPUTED_VALUE"""),"Belinda Dong") -> Belinda Dong | H31: =IFERROR(__xludf.DUMMYFUNCTION("""COMPUTED_VALUE"""),5.772139303E9) -> 5772139303 | I31: =IFERROR(__xludf.DUMMYFUNCTION("""COMPUTED_VALUE"""),"2PM-4PM") -> 2PM-4PM | J31: =IFERROR(__xludf.DUMMYFUNCTION("""COMPUTED_VALUE"""),1.0) -> 1 | K31: =IFERROR(__xludf.DUMMYFUNCTION("""COMPUTED_VALUE"""),"Complete") -> Complete | M31: =IFERROR(__xludf.DUMMYFUNCTION("""COMPUTED_VALUE"""),46123.88358796296) -> 46123.884 | N31: =IFERROR(__xludf.DUMMYFUNCTION("""COMPUTED_VALUE"""),15.0) -> 15 | P31: =IFERROR(__xludf.DUMMYFUNCTION("""COMPUTED_VALUE"""),"Kit Delivery") -> Kit Delivery | S31: =IFERROR(__xludf.DUMMYFUNCTION("""COMPUTED_VALUE"""),46124.4096875) -> 46124.41
A32: =IFERROR(__xludf.DUMMYFUNCTION("""COMPUTED_VALUE"""),"KIT-#17114") -> KIT-#17114 | B32: =IFERROR(__xludf.DUMMYFUNCTION("""COMPUTED_VALUE"""),46139.0) -> 46139 | C32: =IFERROR(__xludf.DUMMYFUNCTION("""COMPUTED_VALUE"""),"Kit Delivery") -> Kit Delivery | D32: =IFERROR(__xludf.DUMMYFUNCTION("""COMPUTED_VALUE"""),1.0) -> 1 | E32: =IFERROR(__xludf.DUMMYFUNCTION("""COMPUTED_VALUE"""),"Dardick") -> Dardick | F32: =IFERROR(__xludf.DUMMYFUNCTION("""COMPUTED_VALUE"""),"409 Left side") -> 409 Left side | G32: =IFERROR(__xludf.DUMMYFUNCTION("""COMPUTED_VALUE"""),"Lily Rulnick") -> Lily Rulnick | H32: =IFERROR(__xludf.DUMMYFUNCTION("""COMPUTED_VALUE"""),2.409944982E9) -> 2409944982 | I32: =IFERROR(__xludf.DUMMYFUNCTION("""COMPUTED_VALUE"""),"10AM-12PM") -> 10AM-12PM | J32: =IFERROR(__xludf.DUMMYFUNCTION("""COMPUTED_VALUE"""),1.0) -> 1 | K32: =IFERROR(__xludf.DUMMYFUNCTION("""COMPUTED_VALUE"""),"Complete") -> Complete | M32: =IFERROR(__xludf.DUMMYFUNCTION("""COMPUTED_VALUE"""),46124.03331018519) -> 46124.033 | N32: =IFERROR(__xludf.DUMMYFUNCTION("""COMPUTED_VALUE"""),88.0) -> 88 | P32: =IFERROR(__xludf.DUMMYFUNCTION("""COMPUTED_VALUE"""),"Kit Delivery") -> Kit Delivery | S32: =IFERROR(__xludf.DUMMYFUNCTION("""COMPUTED_VALUE"""),46124.4096875) -> 46124.41
A33: =IFERROR(__xludf.DUMMYFUNCTION("""COMPUTED_VALUE"""),"KIT-#17303") -> KIT-#17303 | B33: =IFERROR(__xludf.DUMMYFUNCTION("""COMPUTED_VALUE"""),46139.0) -> 46139 | C33: =IFERROR(__xludf.DUMMYFUNCTION("""COMPUTED_VALUE"""),"Kit Delivery") -> Kit Delivery | D33: =IFERROR(__xludf.DUMMYFUNCTION("""COMPUTED_VALUE"""),2.0) -> 2 | E33: =IFERROR(__xludf.DUMMYFUNCTION("""COMPUTED_VALUE"""),"House 5") -> House 5 | F33: =IFERROR(__xludf.DUMMYFUNCTION("""COMPUTED_VALUE"""),308.0) -> 308 | G33: =IFERROR(__xludf.DUMMYFUNCTION("""COMPUTED_VALUE"""),"Yike Li (Grace)") -> Yike Li (Grace) | H33: =IFERROR(__xludf.DUMMYFUNCTION("""COMPUTED_VALUE"""),8.613911331289E12) -> 8613911331289 | I33: =IFERROR(__xludf.DUMMYFUNCTION("""COMPUTED_VALUE"""),"12PM-2PM") -> 12PM-2PM | J33: =IFERROR(__xludf.DUMMYFUNCTION("""COMPUTED_VALUE"""),1.0) -> 1 | K33: =IFERROR(__xludf.DUMMYFUNCTION("""COMPUTED_VALUE"""),"Complete") -> Complete | M33: =IFERROR(__xludf.DUMMYFUNCTION("""COMPUTED_VALUE"""),46129.92461805556) -> 46129.925 | N33: =IFERROR(__xludf.DUMMYFUNCTION("""COMPUTED_VALUE"""),302.0) -> 302 | P33: =IFERROR(__xludf.DUMMYFUNCTION("""COMPUTED_VALUE"""),"Kit Delivery") -> Kit Delivery | S33: =IFERROR(__xludf.DUMMYFUNCTION("""COMPUTED_VALUE"""),"Dispatch_Images/KIT--17303.Photos.031123.jpg") -> Dispatch_Images/KIT--17303.Photos.031123.jpg | T33: =IFERROR(__xludf.DUMMYFUNCTION("""COMPUTED_VALUE"""),46129.925717592596) -> 46129.926
A34: =IFERROR(__xludf.DUMMYFUNCTION("""COMPUTED_VALUE"""),"KIT-#17110") -> KIT-#17110 | B34: =IFERROR(__xludf.DUMMYFUNCTION("""COMPUTED_VALUE"""),46139.0) -> 46139 | C34: =IFERROR(__xludf.DUMMYFUNCTION("""COMPUTED_VALUE"""),"Kit Delivery") -> Kit Delivery | D34: =IFERROR(__xludf.DUMMYFUNCTION("""COMPUTED_VALUE"""),2.0) -> 2 | E34: =IFERROR(__xludf.DUMMYFUNCTION("""COMPUTED_VALUE"""),"6627 UDrive") -> 6627 UDrive | F34: =IFERROR(__xludf.DUMMYFUNCTION("""COMPUTED_VALUE"""),"2W B") -> 2W B | G34: =IFERROR(__xludf.DUMMYFUNCTION("""COMPUTED_VALUE"""),"Liora Raimondi") -> Liora Raimondi | H34: =IFERROR(__xludf.DUMMYFUNCTION("""COMPUTED_VALUE"""),5.162417683E9) -> 5162417683 | I34: =IFERROR(__xludf.DUMMYFUNCTION("""COMPUTED_VALUE"""),"9AM-11AM") -> 9AM-11AM | J34: =IFERROR(__xludf.DUMMYFUNCTION("""COMPUTED_VALUE"""),1.0) -> 1 | K34: =IFERROR(__xludf.DUMMYFUNCTION("""COMPUTED_VALUE"""),"Complete") -> Complete | M34: =IFERROR(__xludf.DUMMYFUNCTION("""COMPUTED_VALUE"""),46129.93157407407) -> 46129.932 | N34: =IFERROR(__xludf.DUMMYFUNCTION("""COMPUTED_VALUE"""),310.0) -> 310 | P34: =IFERROR(__xludf.DUMMYFUNCTION("""COMPUTED_VALUE"""),"Kit Delivery") -> Kit Delivery | S34: =IFERROR(__xludf.DUMMYFUNCTION("""COMPUTED_VALUE"""),"Dispatch_Images/KIT--17110.Photos.032125.jpg") -> Dispatch_Images/KIT--17110.Photos.032125.jpg | T34: =IFERROR(__xludf.DUMMYFUNCTION("""COMPUTED_VALUE"""),46129.93267361111) -> 46129.933
A35: =IFERROR(__xludf.DUMMYFUNCTION("""COMPUTED_VALUE"""),"KIT-#17070") -> KIT-#17070 | B35: =IFERROR(__xludf.DUMMYFUNCTION("""COMPUTED_VALUE"""),46139.0) -> 46139 | C35: =IFERROR(__xludf.DUMMYFUNCTION("""COMPUTED_VALUE"""),"Kit Delivery") -> Kit Delivery | D35: =IFERROR(__xludf.DUMMYFUNCTION("""COMPUTED_VALUE"""),2.0) -> 2 | E35: =IFERROR(__xludf.DUMMYFUNCTION("""COMPUTED_VALUE"""),"Off-Campus") -> Off-Campus | G35: =IFERROR(__xludf.DUMMYFUNCTION("""COMPUTED_VALUE"""),"JORDAN KIM") -> JORDAN KIM | H35: =IFERROR(__xludf.DUMMYFUNCTION("""COMPUTED_VALUE"""),8.187513679E9) -> 8187513679 | I35: =IFERROR(__xludf.DUMMYFUNCTION("""COMPUTED_VALUE"""),"9AM-11AM") -> 9AM-11AM | J35: =IFERROR(__xludf.DUMMYFUNCTION("""COMPUTED_VALUE"""),1.0) -> 1 | K35: =IFERROR(__xludf.DUMMYFUNCTION("""COMPUTED_VALUE"""),"Complete") -> Complete | M35: =IFERROR(__xludf.DUMMYFUNCTION("""COMPUTED_VALUE"""),46129.93913194444) -> 46129.939 | N35: =IFERROR(__xludf.DUMMYFUNCTION("""COMPUTED_VALUE"""),327.0) -> 327 | O35: =IFERROR(__xludf.DUMMYFUNCTION("""COMPUTED_VALUE"""),"5959 McPherson Avenue, Floor G") -> 5959 McPherson Avenue, Floor G | P35: =IFERROR(__xludf.DUMMYFUNCTION("""COMPUTED_VALUE"""),"Kit Delivery") -> Kit Delivery | S35: =IFERROR(__xludf.DUMMYFUNCTION("""COMPUTED_VALUE"""),"Dispatch_Images/KIT--17070.Photos.033217.jpg") -> Dispatch_Images/KIT--17070.Photos.033217.jpg | T35: =IFERROR(__xludf.DUMMYFUNCTION("""COMPUTED_VALUE"""),46129.93960648148) -> 46129.94
A36: =IFERROR(__xludf.DUMMYFUNCTION("""COMPUTED_VALUE"""),"KIT-#17294") -> KIT-#17294 | B36: =IFERROR(__xludf.DUMMYFUNCTION("""COMPUTED_VALUE"""),46139.0) -> 46139 | C36: =IFERROR(__xludf.DUMMYFUNCTION("""COMPUTED_VALUE"""),"Kit Delivery") -> Kit Delivery | D36: =IFERROR(__xludf.DUMMYFUNCTION("""COMPUTED_VALUE"""),2.0) -> 2 | E36: =IFERROR(__xludf.DUMMYFUNCTION("""COMPUTED_VALUE"""),"Off-Campus") -> Off-Campus | G36: =IFERROR(__xludf.DUMMYFUNCTION("""COMPUTED_VALUE"""),"Peiyu Qian*") -> Peiyu Qian* | H36: =IFERROR(__xludf.DUMMYFUNCTION("""COMPUTED_VALUE"""),7.302268851E9) -> 7302268851 | I36: =IFERROR(__xludf.DUMMYFUNCTION("""COMPUTED_VALUE"""),"09:00 AM to 11:00 AM") -> 09:00 AM to 11:00 AM | J36: =IFERROR(__xludf.DUMMYFUNCTION("""COMPUTED_VALUE"""),1.0) -> 1 | K36: =IFERROR(__xludf.DUMMYFUNCTION("""COMPUTED_VALUE"""),"Complete") -> Complete | M36: =IFERROR(__xludf.DUMMYFUNCTION("""COMPUTED_VALUE"""),46134.81003472222) -> 46134.81 | N36: =IFERROR(__xludf.DUMMYFUNCTION("""COMPUTED_VALUE"""),715.0) -> 715 | O36: =IFERROR(__xludf.DUMMYFUNCTION("""COMPUTED_VALUE"""),"212S Meramec Ave. 2406") -> 212S Meramec Ave. 2406 | P36: =IFERROR(__xludf.DUMMYFUNCTION("""COMPUTED_VALUE"""),"Kit Delivery") -> Kit Delivery | S36: =IFERROR(__xludf.DUMMYFUNCTION("""COMPUTED_VALUE"""),"Dispatch_Images/KIT--17294.Photos.002623.jpg") -> Dispatch_Images/KIT--17294.Photos.002623.jpg | T36: =IFERROR(__xludf.DUMMYFUNCTION("""COMPUTED_VALUE"""),46134.814618055556) -> 46134.815
A37: =IFERROR(__xludf.DUMMYFUNCTION("""COMPUTED_VALUE"""),"KIT-#17240") -> KIT-#17240 | B37: =IFERROR(__xludf.DUMMYFUNCTION("""COMPUTED_VALUE"""),46140.0) -> 46140 | C37: =IFERROR(__xludf.DUMMYFUNCTION("""COMPUTED_VALUE"""),"Kit Delivery") -> Kit Delivery | D37: =IFERROR(__xludf.DUMMYFUNCTION("""COMPUTED_VALUE"""),1.0) -> 1 | E37: =IFERROR(__xludf.DUMMYFUNCTION("""COMPUTED_VALUE"""),"Park") -> Park | F37: =IFERROR(__xludf.DUMMYFUNCTION("""COMPUTED_VALUE"""),481.0) -> 481 | G37: =IFERROR(__xludf.DUMMYFUNCTION("""COMPUTED_VALUE"""),"Naveli Singh") -> Naveli Singh | H37: =IFERROR(__xludf.DUMMYFUNCTION("""COMPUTED_VALUE"""),4.087991099E9) -> 4087991099 | I37: =IFERROR(__xludf.DUMMYFUNCTION("""COMPUTED_VALUE"""),"3PM-5PM") -> 3PM-5PM | J37: =IFERROR(__xludf.DUMMYFUNCTION("""COMPUTED_VALUE"""),1.0) -> 1 | K37: =IFERROR(__xludf.DUMMYFUNCTION("""COMPUTED_VALUE"""),"Complete") -> Complete | M37: =IFERROR(__xludf.DUMMYFUNCTION("""COMPUTED_VALUE"""),46123.60449074074) -> 46123.604 | N37: =IFERROR(__xludf.DUMMYFUNCTION("""COMPUTED_VALUE"""),53.0) -> 53 | P37: =IFERROR(__xludf.DUMMYFUNCTION("""COMPUTED_VALUE"""),"Kit Delivery") -> Kit Delivery | S37: =IFERROR(__xludf.DUMMYFUNCTION("""COMPUTED_VALUE"""),46123.61150462963) -> 46123.611
A38: =IFERROR(__xludf.DUMMYFUNCTION("""COMPUTED_VALUE"""),"KIT-#17233") -> KIT-#17233 | B38: =IFERROR(__xludf.DUMMYFUNCTION("""COMPUTED_VALUE"""),46140.0) -> 46140 | C38: =IFERROR(__xludf.DUMMYFUNCTION("""COMPUTED_VALUE"""),"Kit Delivery") -> Kit Delivery | D38: =IFERROR(__xludf.DUMMYFUNCTION("""COMPUTED_VALUE"""),1.0) -> 1 | E38: =IFERROR(__xludf.DUMMYFUNCTION("""COMPUTED_VALUE"""),"Liggett") -> Liggett | F38: =IFERROR(__xludf.DUMMYFUNCTION("""COMPUTED_VALUE"""),"2274A") -> 2274A | G38: =IFERROR(__xludf.DUMMYFUNCTION("""COMPUTED_VALUE"""),"Sophie Schwartz") -> Sophie Schwartz | H38: =IFERROR(__xludf.DUMMYFUNCTION("""COMPUTED_VALUE"""),"(949)230-0616") -> (949)230-0616 | I38: =IFERROR(__xludf.DUMMYFUNCTION("""COMPUTED_VALUE"""),"3PM-5PM") -> 3PM-5PM | J38: =IFERROR(__xludf.DUMMYFUNCTION("""COMPUTED_VALUE"""),1.0) -> 1 | K38: =IFERROR(__xludf.DUMMYFUNCTION("""COMPUTED_VALUE"""),"Complete") -> Complete | M38: =IFERROR(__xludf.DUMMYFUNCTION("""COMPUTED_VALUE"""),46124.045949074076) -> 46124.046 | N38: =IFERROR(__xludf.DUMMYFUNCTION("""COMPUTED_VALUE"""),147.0) -> 147 | P38: =IFERROR(__xludf.DUMMYFUNCTION("""COMPUTED_VALUE"""),"Kit Delivery") -> Kit Delivery | S38: =IFERROR(__xludf.DUMMYFUNCTION("""COMPUTED_VALUE"""),46124.4096875) -> 46124.41
A39: =IFERROR(__xludf.DUMMYFUNCTION("""COMPUTED_VALUE"""),"KIT-#17094") -> KIT-#17094 | B39: =IFERROR(__xludf.DUMMYFUNCTION("""COMPUTED_VALUE"""),46140.0) -> 46140 | C39: =IFERROR(__xludf.DUMMYFUNCTION("""COMPUTED_VALUE"""),"Kit Delivery") -> Kit Delivery | D39: =IFERROR(__xludf.DUMMYFUNCTION("""COMPUTED_VALUE"""),1.0) -> 1 | E39: =IFERROR(__xludf.DUMMYFUNCTION("""COMPUTED_VALUE"""),"Liggett") -> Liggett | F39: =IFERROR(__xludf.DUMMYFUNCTION("""COMPUTED_VALUE"""),"2274 (Drom Room) (There will be 2 tables in 2270 Common Area)") -> 2274 (Drom Room) (There will be 2 tables in 2270 Common Area) | G39: =IFERROR(__xludf.DUMMYFUNCTION("""COMPUTED_VALUE"""),"Sophie Schwartz") -> Sophie Schwartz | H39: =IFERROR(__xludf.DUMMYFUNCTION("""COMPUTED_VALUE"""),9.492300616E9) -> 9492300616 | I39: =IFERROR(__xludf.DUMMYFUNCTION("""COMPUTED_VALUE"""),"3PM-5PM") -> 3PM-5PM | J39: =IFERROR(__xludf.DUMMYFUNCTION("""COMPUTED_VALUE"""),2.0) -> 2 | K39: =IFERROR(__xludf.DUMMYFUNCTION("""COMPUTED_VALUE"""),"Complete") -> Complete | M39: =IFERROR(__xludf.DUMMYFUNCTION("""COMPUTED_VALUE"""),46124.045960648145) -> 46124.046 | N39: =IFERROR(__xludf.DUMMYFUNCTION("""COMPUTED_VALUE"""),146.0) -> 146 | P39: =IFERROR(__xludf.DUMMYFUNCTION("""COMPUTED_VALUE"""),"Kit Delivery") -> Kit Delivery | S39: =IFERROR(__xludf.DUMMYFUNCTION("""COMPUTED_VALUE"""),46124.4096875) -> 46124.41
A40: =IFERROR(__xludf.DUMMYFUNCTION("""COMPUTED_VALUE"""),"KIT-#17559") -> KIT-#17559 | B40: =IFERROR(__xludf.DUMMYFUNCTION("""COMPUTED_VALUE"""),46140.0) -> 46140 | C40: =IFERROR(__xludf.DUMMYFUNCTION("""COMPUTED_VALUE"""),"Kit Delivery") -> Kit Delivery | D40: =IFERROR(__xludf.DUMMYFUNCTION("""COMPUTED_VALUE"""),2.0) -> 2 | E40: =IFERROR(__xludf.DUMMYFUNCTION("""COMPUTED_VALUE"""),"Eliot B") -> Eliot B | F40: =IFERROR(__xludf.DUMMYFUNCTION("""COMPUTED_VALUE"""),1033.0) -> 1033 | G40: =IFERROR(__xludf.DUMMYFUNCTION("""COMPUTED_VALUE"""),"Zia Bärfuss—Liao") -> Zia Bärfuss—Liao | H40: =IFERROR(__xludf.DUMMYFUNCTION("""COMPUTED_VALUE"""),3.147325905E9) -> 3147325905 | I40: =IFERROR(__xludf.DUMMYFUNCTION("""COMPUTED_VALUE"""),"11AM-1PM") -> 11AM-1PM | J40: =IFERROR(__xludf.DUMMYFUNCTION("""COMPUTED_VALUE"""),1.0) -> 1 | K40: =IFERROR(__xludf.DUMMYFUNCTION("""COMPUTED_VALUE"""),"Complete") -> Complete | M40: =IFERROR(__xludf.DUMMYFUNCTION("""COMPUTED_VALUE"""),46129.84064814815) -> 46129.841 | N40: =IFERROR(__xludf.DUMMYFUNCTION("""COMPUTED_VALUE"""),30.0) -> 30 | P40: =IFERROR(__xludf.DUMMYFUNCTION("""COMPUTED_VALUE"""),"Kit Delivery") -> Kit Delivery | S40: =IFERROR(__xludf.DUMMYFUNCTION("""COMPUTED_VALUE"""),"Dispatch_Images/KIT--17559.Photos.011029.jpg") -> Dispatch_Images/KIT--17559.Photos.011029.jpg | T40: =IFERROR(__xludf.DUMMYFUNCTION("""COMPUTED_VALUE"""),46129.84243055555) -> 46129.842
A41: =IFERROR(__xludf.DUMMYFUNCTION("""COMPUTED_VALUE"""),"KIT-#17510") -> KIT-#17510 | B41: =IFERROR(__xludf.DUMMYFUNCTION("""COMPUTED_VALUE"""),46140.0) -> 46140 | C41: =IFERROR(__xludf.DUMMYFUNCTION("""COMPUTED_VALUE"""),"Kit Delivery") -> Kit Delivery | D41: =IFERROR(__xludf.DUMMYFUNCTION("""COMPUTED_VALUE"""),3.0) -> 3 | E41: =IFERROR(__xludf.DUMMYFUNCTION("""COMPUTED_VALUE"""),"Koenig") -> Koenig | F41: =IFERROR(__xludf.DUMMYFUNCTION("""COMPUTED_VALUE"""),3316.0) -> 3316 | G41: =IFERROR(__xludf.DUMMYFUNCTION("""COMPUTED_VALUE"""),"Emmy May") -> Emmy May | H41: =IFERROR(__xludf.DUMMYFUNCTION("""COMPUTED_VALUE"""),8.174803764E9) -> 8174803764 | I41: =IFERROR(__xludf.DUMMYFUNCTION("""COMPUTED_VALUE"""),"11AM-1PM") -> 11AM-1PM | J41: =IFERROR(__xludf.DUMMYFUNCTION("""COMPUTED_VALUE"""),1.0) -> 1 | K41: =IFERROR(__xludf.DUMMYFUNCTION("""COMPUTED_VALUE"""),"Complete") -> Complete | M41: =IFERROR(__xludf.DUMMYFUNCTION("""COMPUTED_VALUE"""),46130.435636574075) -> 46130.436 | N41: =IFERROR(__xludf.DUMMYFUNCTION("""COMPUTED_VALUE"""),207.0) -> 207 | P41: =IFERROR(__xludf.DUMMYFUNCTION("""COMPUTED_VALUE"""),"Kit Delivery") -> Kit Delivery | S41: =IFERROR(__xludf.DUMMYFUNCTION("""COMPUTED_VALUE"""),"Dispatch_Images/KIT--17510.Photos.152716.jpg") -> Dispatch_Images/KIT--17510.Photos.152716.jpg | T41: =IFERROR(__xludf.DUMMYFUNCTION("""COMPUTED_VALUE"""),46130.43962962963) -> 46130.44
A42: =IFERROR(__xludf.DUMMYFUNCTION("""COMPUTED_VALUE"""),"KIT-#17422") -> KIT-#17422 | B42: =IFERROR(__xludf.DUMMYFUNCTION("""COMPUTED_VALUE"""),46140.0) -> 46140 | C42: =IFERROR(__xludf.DUMMYFUNCTION("""COMPUTED_VALUE"""),"Kit Delivery") -> Kit Delivery | D42: =IFERROR(__xludf.DUMMYFUNCTION("""COMPUTED_VALUE"""),3.0) -> 3 | E42: =IFERROR(__xludf.DUMMYFUNCTION("""COMPUTED_VALUE"""),"Village East") -> Village East | F42: =IFERROR(__xludf.DUMMYFUNCTION("""COMPUTED_VALUE"""),2092.0) -> 2092 | G42: =IFERROR(__xludf.DUMMYFUNCTION("""COMPUTED_VALUE"""),"Anna Siegel") -> Anna Siegel | H42: =IFERROR(__xludf.DUMMYFUNCTION("""COMPUTED_VALUE"""),5.732590239E9) -> 5732590239 | I42: =IFERROR(__xludf.DUMMYFUNCTION("""COMPUTED_VALUE"""),"9AM-11AM") -> 9AM-11AM | J42: =IFERROR(__xludf.DUMMYFUNCTION("""COMPUTED_VALUE"""),1.0) -> 1 | K42: =IFERROR(__xludf.DUMMYFUNCTION("""COMPUTED_VALUE"""),"Complete") -> Complete | M42: =IFERROR(__xludf.DUMMYFUNCTION("""COMPUTED_VALUE"""),46130.48664351852) -> 46130.487 | N42: =IFERROR(__xludf.DUMMYFUNCTION("""COMPUTED_VALUE"""),268.0) -> 268 | P42: =IFERROR(__xludf.DUMMYFUNCTION("""COMPUTED_VALUE"""),"Kit Delivery") -> Kit Delivery | S42: =IFERROR(__xludf.DUMMYFUNCTION("""COMPUTED_VALUE"""),"Dispatch_Images/KIT--17422.Photos.164042.jpg") -> Dispatch_Images/KIT--17422.Photos.164042.jpg | T42: =IFERROR(__xludf.DUMMYFUNCTION("""COMPUTED_VALUE"""),46130.488229166665) -> 46130.488
A43: =IFERROR(__xludf.DUMMYFUNCTION("""COMPUTED_VALUE"""),"KIT-#17668") -> KIT-#17668 | B43: =IFERROR(__xludf.DUMMYFUNCTION("""COMPUTED_VALUE"""),46140.0) -> 46140 | C43: =IFERROR(__xludf.DUMMYFUNCTION("""COMPUTED_VALUE"""),"Kit Delivery") -> Kit Delivery | D43: =IFERROR(__xludf.DUMMYFUNCTION("""COMPUTED_VALUE"""),2.0) -> 2 | E43: =IFERROR(__xludf.DUMMYFUNCTION("""COMPUTED_VALUE"""),"Wheeler") -> Wheeler | F43: =IFERROR(__xludf.DUMMYFUNCTION("""COMPUTED_VALUE"""),2090.0) -> 2090 | G43: =IFERROR(__xludf.DUMMYFUNCTION("""COMPUTED_VALUE"""),"Beckett Miller*") -> Beckett Miller* | H43: =IFERROR(__xludf.DUMMYFUNCTION("""COMPUTED_VALUE"""),1.6507879908E10) -> 16507879908 | I43: =IFERROR(__xludf.DUMMYFUNCTION("""COMPUTED_VALUE"""),"12PM-2PM") -> 12PM-2PM | J43: =IFERROR(__xludf.DUMMYFUNCTION("""COMPUTED_VALUE"""),1.0) -> 1 | K43: =IFERROR(__xludf.DUMMYFUNCTION("""COMPUTED_VALUE"""),"Complete") -> Complete | M43: =IFERROR(__xludf.DUMMYFUNCTION("""COMPUTED_VALUE"""),46134.70043981481) -> 46134.7 | N43: =IFERROR(__xludf.DUMMYFUNCTION("""COMPUTED_VALUE"""),63.0) -> 63 | P43: =IFERROR(__xludf.DUMMYFUNCTION("""COMPUTED_VALUE"""),"Kit Delivery") -> Kit Delivery | S43: =IFERROR(__xludf.DUMMYFUNCTION("""COMPUTED_VALUE"""),"Dispatch_Images/KIT--17668.Photos.214834.jpg") -> Dispatch_Images/KIT--17668.Photos.214834.jpg | T43: =IFERROR(__xludf.DUMMYFUNCTION("""COMPUTED_VALUE"""),46134.703518518516) -> 46134.704
A44: =IFERROR(__xludf.DUMMYFUNCTION("""COMPUTED_VALUE"""),"KIT-#17629") -> KIT-#17629 | B44: =IFERROR(__xludf.DUMMYFUNCTION("""COMPUTED_VALUE"""),46140.0) -> 46140 | C44: =IFERROR(__xludf.DUMMYFUNCTION("""COMPUTED_VALUE"""),"Kit Delivery") -> Kit Delivery | D44: =IFERROR(__xludf.DUMMYFUNCTION("""COMPUTED_VALUE"""),2.0) -> 2 | E44: =IFERROR(__xludf.DUMMYFUNCTION("""COMPUTED_VALUE"""),"Umrath") -> Umrath | F44: =IFERROR(__xludf.DUMMYFUNCTION("""COMPUTED_VALUE"""),2235.0) -> 2235 | G44: =IFERROR(__xludf.DUMMYFUNCTION("""COMPUTED_VALUE"""),"Ava A. Malick*") -> Ava A. Malick* | H44: =IFERROR(__xludf.DUMMYFUNCTION("""COMPUTED_VALUE"""),9.176694027E9) -> 9176694027 | I44: =IFERROR(__xludf.DUMMYFUNCTION("""COMPUTED_VALUE"""),"9AM-11AM") -> 9AM-11AM | J44: =IFERROR(__xludf.DUMMYFUNCTION("""COMPUTED_VALUE"""),2.0) -> 2 | K44: =IFERROR(__xludf.DUMMYFUNCTION("""COMPUTED_VALUE"""),"Complete") -> Complete | M44: =IFERROR(__xludf.DUMMYFUNCTION("""COMPUTED_VALUE"""),46134.76447916667) -> 46134.764 | N44: =IFERROR(__xludf.DUMMYFUNCTION("""COMPUTED_VALUE"""),141.0) -> 141 | P44: =IFERROR(__xludf.DUMMYFUNCTION("""COMPUTED_VALUE"""),"Kit Delivery") -> Kit Delivery | S44: =IFERROR(__xludf.DUMMYFUNCTION("""COMPUTED_VALUE"""),"Dispatch_Images/KIT--17629.Photos.232048.jpg") -> Dispatch_Images/KIT--17629.Photos.232048.jpg | T44: =IFERROR(__xludf.DUMMYFUNCTION("""COMPUTED_VALUE"""),46134.76600694445) -> 46134.766
A45: =IFERROR(__xludf.DUMMYFUNCTION("""COMPUTED_VALUE"""),"KIT-#17650") -> KIT-#17650 | B45: =IFERROR(__xludf.DUMMYFUNCTION("""COMPUTED_VALUE"""),46140.0) -> 46140 | C45: =IFERROR(__xludf.DUMMYFUNCTION("""COMPUTED_VALUE"""),"Kit Delivery") -> Kit Delivery | D45: =IFERROR(__xludf.DUMMYFUNCTION("""COMPUTED_VALUE"""),2.0) -> 2 | E45: =IFERROR(__xludf.DUMMYFUNCTION("""COMPUTED_VALUE"""),"Off-Campus") -> Off-Campus | G45: =IFERROR(__xludf.DUMMYFUNCTION("""COMPUTED_VALUE"""),"Yi Zheng") -> Yi Zheng | H45: =IFERROR(__xludf.DUMMYFUNCTION("""COMPUTED_VALUE"""),9.497057772E9) -> 9497057772 | I45: =IFERROR(__xludf.DUMMYFUNCTION("""COMPUTED_VALUE"""),"9AM-11AM") -> 9AM-11AM | J45: =IFERROR(__xludf.DUMMYFUNCTION("""COMPUTED_VALUE"""),1.0) -> 1 | K45: =IFERROR(__xludf.DUMMYFUNCTION("""COMPUTED_VALUE"""),"Complete") -> Complete | L45: =IFERROR(__xludf.DUMMYFUNCTION("""COMPUTED_VALUE"""),"david did 4/23") -> david did 4/23 | N45: =IFERROR(__xludf.DUMMYFUNCTION("""COMPUTED_VALUE"""),281.0) -> 281 | O45: =IFERROR(__xludf.DUMMYFUNCTION("""COMPUTED_VALUE"""),"6136 Delmar Blvd, Apt 302, Saint Louis, MO 63112") -> 6136 Delmar Blvd, Apt 302, Saint Louis, MO 63112 | P45: =IFERROR(__xludf.DUMMYFUNCTION("""COMPUTED_VALUE"""),"Kit Delivery") -> Kit Delivery | T45: =IFERROR(__xludf.DUMMYFUNCTION("""COMPUTED_VALUE"""),46135.65489583334) -> 46135.655
A46: =IFERROR(__xludf.DUMMYFUNCTION("""COMPUTED_VALUE"""),"KIT-#17258") -> KIT-#17258 | B46: =IFERROR(__xludf.DUMMYFUNCTION("""COMPUTED_VALUE"""),46141.0) -> 46141 | C46: =IFERROR(__xludf.DUMMYFUNCTION("""COMPUTED_VALUE"""),"Kit Delivery") -> Kit Delivery | D46: =IFERROR(__xludf.DUMMYFUNCTION("""COMPUTED_VALUE"""),1.0) -> 1 | E46: =IFERROR(__xludf.DUMMYFUNCTION("""COMPUTED_VALUE"""),"Danforth") -> Danforth | F46: =IFERROR(__xludf.DUMMYFUNCTION("""COMPUTED_VALUE"""),4430.0) -> 4430 | G46: =IFERROR(__xludf.DUMMYFUNCTION("""COMPUTED_VALUE"""),"Levi Cutler") -> Levi Cutler | H46: =IFERROR(__xludf.DUMMYFUNCTION("""COMPUTED_VALUE"""),3.234014182E9) -> 3234014182 | I46: =IFERROR(__xludf.DUMMYFUNCTION("""COMPUTED_VALUE"""),"9AM-11AM") -> 9AM-11AM | J46: =IFERROR(__xludf.DUMMYFUNCTION("""COMPUTED_VALUE"""),2.0) -> 2 | K46: =IFERROR(__xludf.DUMMYFUNCTION("""COMPUTED_VALUE"""),"Complete") -> Complete | M46: =IFERROR(__xludf.DUMMYFUNCTION("""COMPUTED_VALUE"""),46123.58806712963) -> 46123.588 | N46: =IFERROR(__xludf.DUMMYFUNCTION("""COMPUTED_VALUE"""),42.0) -> 42 | P46: =IFERROR(__xludf.DUMMYFUNCTION("""COMPUTED_VALUE"""),"Kit Delivery") -> Kit Delivery | S46: =IFERROR(__xludf.DUMMYFUNCTION("""COMPUTED_VALUE"""),46123.61150462963) -> 46123.611
A47: =IFERROR(__xludf.DUMMYFUNCTION("""COMPUTED_VALUE"""),"KIT-#17272") -> KIT-#17272 | B47: =IFERROR(__xludf.DUMMYFUNCTION("""COMPUTED_VALUE"""),46141.0) -> 46141 | C47: =IFERROR(__xludf.DUMMYFUNCTION("""COMPUTED_VALUE"""),"Kit Delivery") -> Kit Delivery | D47: =IFERROR(__xludf.DUMMYFUNCTION("""COMPUTED_VALUE"""),1.0) -> 1 | E47: =IFERROR(__xludf.DUMMYFUNCTION("""COMPUTED_VALUE"""),"Hurd") -> Hurd | F47: =IFERROR(__xludf.DUMMYFUNCTION("""COMPUTED_VALUE"""),312.0) -> 312 | G47: =IFERROR(__xludf.DUMMYFUNCTION("""COMPUTED_VALUE"""),"Nancy Bai") -> Nancy Bai | H47: =IFERROR(__xludf.DUMMYFUNCTION("""COMPUTED_VALUE"""),5.572289736E9) -> 5572289736 | I47: =IFERROR(__xludf.DUMMYFUNCTION("""COMPUTED_VALUE"""),"2PM-4PM") -> 2PM-4PM | J47: =IFERROR(__xludf.DUMMYFUNCTION("""COMPUTED_VALUE"""),2.0) -> 2 | K47: =IFERROR(__xludf.DUMMYFUNCTION("""COMPUTED_VALUE"""),"Complete") -> Complete | M47: =IFERROR(__xludf.DUMMYFUNCTION("""COMPUTED_VALUE"""),46123.69918981481) -> 46123.699 | N47: =IFERROR(__xludf.DUMMYFUNCTION("""COMPUTED_VALUE"""),6.0) -> 6 | P47: =IFERROR(__xludf.DUMMYFUNCTION("""COMPUTED_VALUE"""),"Kit Delivery") -> Kit Delivery | S47: =IFERROR(__xludf.DUMMYFUNCTION("""COMPUTED_VALUE"""),46123.70133101852) -> 46123.701
A48: =IFERROR(__xludf.DUMMYFUNCTION("""COMPUTED_VALUE"""),"KIT-#17193") -> KIT-#17193 | B48: =IFERROR(__xludf.DUMMYFUNCTION("""COMPUTED_VALUE"""),46141.0) -> 46141 | C48: =IFERROR(__xludf.DUMMYFUNCTION("""COMPUTED_VALUE"""),"Kit Delivery") -> Kit Delivery | D48: =IFERROR(__xludf.DUMMYFUNCTION("""COMPUTED_VALUE"""),1.0) -> 1 | E48: =IFERROR(__xludf.DUMMYFUNCTION("""COMPUTED_VALUE"""),"Gregg") -> Gregg | F48: =IFERROR(__xludf.DUMMYFUNCTION("""COMPUTED_VALUE"""),3102.0) -> 3102 | G48: =IFERROR(__xludf.DUMMYFUNCTION("""COMPUTED_VALUE"""),"Kaila Brooks") -> Kaila Brooks | H48: =IFERROR(__xludf.DUMMYFUNCTION("""COMPUTED_VALUE"""),8.454439805E9) -> 8454439805 | I48: =IFERROR(__xludf.DUMMYFUNCTION("""COMPUTED_VALUE"""),"9AM-11AM") -> 9AM-11AM | J48: =IFERROR(__xludf.DUMMYFUNCTION("""COMPUTED_VALUE"""),2.0) -> 2 | K48: =IFERROR(__xludf.DUMMYFUNCTION("""COMPUTED_VALUE"""),"Complete") -> Complete | M48: =IFERROR(__xludf.DUMMYFUNCTION("""COMPUTED_VALUE"""),46123.824212962965) -> 46123.824 | N48: =IFERROR(__xludf.DUMMYFUNCTION("""COMPUTED_VALUE"""),153.0) -> 153 | P48: =IFERROR(__xludf.DUMMYFUNCTION("""COMPUTED_VALUE"""),"Kit Delivery") -> Kit Delivery | S48: =IFERROR(__xludf.DUMMYFUNCTION("""COMPUTED_VALUE"""),46124.4096875) -> 46124.41
A49: =IFERROR(__xludf.DUMMYFUNCTION("""COMPUTED_VALUE"""),"KIT-#17189") -> KIT-#17189 | B49: =IFERROR(__xludf.DUMMYFUNCTION("""COMPUTED_VALUE"""),46141.0) -> 46141 | C49: =IFERROR(__xludf.DUMMYFUNCTION("""COMPUTED_VALUE"""),"Kit Delivery") -> Kit Delivery | D49: =IFERROR(__xludf.DUMMYFUNCTION("""COMPUTED_VALUE"""),1.0) -> 1 | E49: =IFERROR(__xludf.DUMMYFUNCTION("""COMPUTED_VALUE"""),"Eliot A") -> Eliot A | F49: =IFERROR(__xludf.DUMMYFUNCTION("""COMPUTED_VALUE"""),2131.0) -> 2131 | G49: =IFERROR(__xludf.DUMMYFUNCTION("""COMPUTED_VALUE"""),"Portia Francois") -> Portia Francois | H49: =IFERROR(__xludf.DUMMYFUNCTION("""COMPUTED_VALUE"""),5.202381522E9) -> 5202381522 | I49: =IFERROR(__xludf.DUMMYFUNCTION("""COMPUTED_VALUE"""),"9AM-11AM") -> 9AM-11AM | J49: =IFERROR(__xludf.DUMMYFUNCTION("""COMPUTED_VALUE"""),2.0) -> 2 | K49: =IFERROR(__xludf.DUMMYFUNCTION("""COMPUTED_VALUE"""),"Complete") -> Complete | M49: =IFERROR(__xludf.DUMMYFUNCTION("""COMPUTED_VALUE"""),46123.877905092595) -> 46123.878 | N49: =IFERROR(__xludf.DUMMYFUNCTION("""COMPUTED_VALUE"""),23.0) -> 23 | P49: =IFERROR(__xludf.DUMMYFUNCTION("""COMPUTED_VALUE"""),"Kit Delivery") -> Kit Delivery | S49: =IFERROR(__xludf.DUMMYFUNCTION("""COMPUTED_VALUE"""),46124.4096875) -> 46124.41
A50: =IFERROR(__xludf.DUMMYFUNCTION("""COMPUTED_VALUE"""),"KIT-#17383") -> KIT-#17383 | B50: =IFERROR(__xludf.DUMMYFUNCTION("""COMPUTED_VALUE"""),46141.0) -> 46141 | C50: =IFERROR(__xludf.DUMMYFUNCTION("""COMPUTED_VALUE"""),"Kit Delivery") -> Kit Delivery | D50: =IFERROR(__xludf.DUMMYFUNCTION("""COMPUTED_VALUE"""),1.0) -> 1 | E50: =IFERROR(__xludf.DUMMYFUNCTION("""COMPUTED_VALUE"""),"Lopata") -> Lopata | F50: =IFERROR(__xludf.DUMMYFUNCTION("""COMPUTED_VALUE"""),"Suite3050RoomA") -> Suite3050RoomA | G50: =IFERROR(__xludf.DUMMYFUNCTION("""COMPUTED_VALUE"""),"Paisley Flamenbaum") -> Paisley Flamenbaum | H50: =IFERROR(__xludf.DUMMYFUNCTION("""COMPUTED_VALUE"""),9.145259746E9) -> 9145259746 | I50: =IFERROR(__xludf.DUMMYFUNCTION("""COMPUTED_VALUE"""),"9AM-11AM") -> 9AM-11AM | J50: =IFERROR(__xludf.DUMMYFUNCTION("""COMPUTED_VALUE"""),1.0) -> 1 | K50: =IFERROR(__xludf.DUMMYFUNCTION("""COMPUTED_VALUE"""),"Complete") -> Complete | M50: =IFERROR(__xludf.DUMMYFUNCTION("""COMPUTED_VALUE"""),46123.95502314815) -> 46123.955 | N50: =IFERROR(__xludf.DUMMYFUNCTION("""COMPUTED_VALUE"""),173.0) -> 173 | P50: =IFERROR(__xludf.DUMMYFUNCTION("""COMPUTED_VALUE"""),"Kit Delivery") -> Kit Delivery | S50: =IFERROR(__xludf.DUMMYFUNCTION("""COMPUTED_VALUE"""),46124.4096875) -> 46124.41
A51: =IFERROR(__xludf.DUMMYFUNCTION("""COMPUTED_VALUE"""),"KIT-#17454") -> KIT-#17454 | B51: =IFERROR(__xludf.DUMMYFUNCTION("""COMPUTED_VALUE"""),46141.0) -> 46141 | C51: =IFERROR(__xludf.DUMMYFUNCTION("""COMPUTED_VALUE"""),"Kit Delivery") -> Kit Delivery | D51: =IFERROR(__xludf.DUMMYFUNCTION("""COMPUTED_VALUE"""),1.0) -> 1 | E51: =IFERROR(__xludf.DUMMYFUNCTION("""COMPUTED_VALUE"""),"Dardick") -> Dardick | F51: =IFERROR(__xludf.DUMMYFUNCTION("""COMPUTED_VALUE"""),3305.0) -> 3305 | G51: =IFERROR(__xludf.DUMMYFUNCTION("""COMPUTED_VALUE"""),"Olivia Petlak") -> Olivia Petlak | H51: =IFERROR(__xludf.DUMMYFUNCTION("""COMPUTED_VALUE"""),4.24303052E9) -> 4243030520 | I51: =IFERROR(__xludf.DUMMYFUNCTION("""COMPUTED_VALUE"""),"3PM-5PM") -> 3PM-5PM | J51: =IFERROR(__xludf.DUMMYFUNCTION("""COMPUTED_VALUE"""),1.0) -> 1 | K51: =IFERROR(__xludf.DUMMYFUNCTION("""COMPUTED_VALUE"""),"Complete") -> Complete | M51: =IFERROR(__xludf.DUMMYFUNCTION("""COMPUTED_VALUE"""),46130.390798611115) -> 46130.391 | N51: =IFERROR(__xludf.DUMMYFUNCTION("""COMPUTED_VALUE"""),123.0) -> 123 | P51: =IFERROR(__xludf.DUMMYFUNCTION("""COMPUTED_VALUE"""),"Kit Delivery") -> Kit Delivery | S51: =IFERROR(__xludf.DUMMYFUNCTION("""COMPUTED_VALUE"""),"Dispatch_Images/KIT--17454.Photos.142242.jpg") -> Dispatch_Images/KIT--17454.Photos.142242.jpg | T51: =IFERROR(__xludf.DUMMYFUNCTION("""COMPUTED_VALUE"""),46130.39099537037) -> 46130.391
A52: =IFERROR(__xludf.DUMMYFUNCTION("""COMPUTED_VALUE"""),"KIT-#17471") -> KIT-#17471 | B52: =IFERROR(__xludf.DUMMYFUNCTION("""COMPUTED_VALUE"""),46141.0) -> 46141 | C52: =IFERROR(__xludf.DUMMYFUNCTION("""COMPUTED_VALUE"""),"Kit Delivery") -> Kit Delivery | D52: =IFERROR(__xludf.DUMMYFUNCTION("""COMPUTED_VALUE"""),2.0) -> 2 | E52: =IFERROR(__xludf.DUMMYFUNCTION("""COMPUTED_VALUE"""),"Park") -> Park | F52: =IFERROR(__xludf.DUMMYFUNCTION("""COMPUTED_VALUE"""),162.0) -> 162 | G52: =IFERROR(__xludf.DUMMYFUNCTION("""COMPUTED_VALUE"""),"Casey Ference*") -> Casey Ference* | H52: =IFERROR(__xludf.DUMMYFUNCTION("""COMPUTED_VALUE"""),9.17414012E9) -> 9174140120 | I52: =IFERROR(__xludf.DUMMYFUNCTION("""COMPUTED_VALUE"""),"3PM-5PM") -> 3PM-5PM | J52: =IFERROR(__xludf.DUMMYFUNCTION("""COMPUTED_VALUE"""),1.0) -> 1 | K52: =IFERROR(__xludf.DUMMYFUNCTION("""COMPUTED_VALUE"""),"Complete") -> Complete | M52: =IFERROR(__xludf.DUMMYFUNCTION("""COMPUTED_VALUE"""),46134.72127314815) -> 46134.721 | N52: =IFERROR(__xludf.DUMMYFUNCTION("""COMPUTED_VALUE"""),68.0) -> 68 | P52: =IFERROR(__xludf.DUMMYFUNCTION("""COMPUTED_VALUE"""),"Kit Delivery") -> Kit Delivery | S52: =IFERROR(__xludf.DUMMYFUNCTION("""COMPUTED_VALUE"""),"Dispatch_Images/KIT--17471.Photos.221834.jpg") -> Dispatch_Images/KIT--17471.Photos.221834.jpg | T52: =IFERROR(__xludf.DUMMYFUNCTION("""COMPUTED_VALUE"""),46134.724340277775) -> 46134.724
A53: =IFERROR(__xludf.DUMMYFUNCTION("""COMPUTED_VALUE"""),"KIT-#17493") -> KIT-#17493 | B53: =IFERROR(__xludf.DUMMYFUNCTION("""COMPUTED_VALUE"""),46141.0) -> 46141 | C53: =IFERROR(__xludf.DUMMYFUNCTION("""COMPUTED_VALUE"""),"Kit Delivery") -> Kit Delivery | D53: =IFERROR(__xludf.DUMMYFUNCTION("""COMPUTED_VALUE"""),2.0) -> 2 | E53: =IFERROR(__xludf.DUMMYFUNCTION("""COMPUTED_VALUE"""),"Myers") -> Myers | F53: =IFERROR(__xludf.DUMMYFUNCTION("""COMPUTED_VALUE"""),343.0) -> 343 | G53: =IFERROR(__xludf.DUMMYFUNCTION("""COMPUTED_VALUE"""),"Max Zeller*") -> Max Zeller* | H53: =IFERROR(__xludf.DUMMYFUNCTION("""COMPUTED_VALUE"""),6.50241876E9) -> 6502418760 | I53: =IFERROR(__xludf.DUMMYFUNCTION("""COMPUTED_VALUE"""),"10AM-12PM") -> 10AM-12PM | J53: =IFERROR(__xludf.DUMMYFUNCTION("""COMPUTED_VALUE"""),1.0) -> 1 | K53: =IFERROR(__xludf.DUMMYFUNCTION("""COMPUTED_VALUE"""),"Complete") -> Complete | M53: =IFERROR(__xludf.DUMMYFUNCTION("""COMPUTED_VALUE"""),46134.75255787037) -> 46134.753 | N53: =IFERROR(__xludf.DUMMYFUNCTION("""COMPUTED_VALUE"""),25.0) -> 25 | O53: =IFERROR(__xludf.DUMMYFUNCTION("""COMPUTED_VALUE"""),"4137 Donald Dr Palo Alto, CA 94306") -> 4137 Donald Dr Palo Alto, CA 94306 | P53: =IFERROR(__xludf.DUMMYFUNCTION("""COMPUTED_VALUE"""),"Kit Delivery") -> Kit Delivery | Q53: =IFERROR(__xludf.DUMMYFUNCTION("""COMPUTED_VALUE"""),"Student phone number: 650-441-2955") -> Student phone number: 650-441-2955 | S53: =IFERROR(__xludf.DUMMYFUNCTION("""COMPUTED_VALUE"""),"Dispatch_Images/KIT--17493.Photos.230338.jpg") -> Dispatch_Images/KIT--17493.Photos.230338.jpg | T53: =IFERROR(__xludf.DUMMYFUNCTION("""COMPUTED_VALUE"""),46134.75907407407) -> 46134.759
A54: =IFERROR(__xludf.DUMMYFUNCTION("""COMPUTED_VALUE"""),"KIT-#17606") -> KIT-#17606 | B54: =IFERROR(__xludf.DUMMYFUNCTION("""COMPUTED_VALUE"""),46141.0) -> 46141 | C54: =IFERROR(__xludf.DUMMYFUNCTION("""COMPUTED_VALUE"""),"Kit Delivery") -> Kit Delivery | D54: =IFERROR(__xludf.DUMMYFUNCTION("""COMPUTED_VALUE"""),2.0) -> 2 | E54: =IFERROR(__xludf.DUMMYFUNCTION("""COMPUTED_VALUE"""),"Lien") -> Lien | F54: =IFERROR(__xludf.DUMMYFUNCTION("""COMPUTED_VALUE"""),1117.0) -> 1117 | G54: =IFERROR(__xludf.DUMMYFUNCTION("""COMPUTED_VALUE"""),"Ella Zhu") -> Ella Zhu | H54: =IFERROR(__xludf.DUMMYFUNCTION("""COMPUTED_VALUE"""),2.038181729E9) -> 2038181729 | I54: =IFERROR(__xludf.DUMMYFUNCTION("""COMPUTED_VALUE"""),"9AM-11AM") -> 9AM-11AM | J54: =IFERROR(__xludf.DUMMYFUNCTION("""COMPUTED_VALUE"""),1.0) -> 1 | K54: =IFERROR(__xludf.DUMMYFUNCTION("""COMPUTED_VALUE"""),"Complete") -> Complete | M54: =IFERROR(__xludf.DUMMYFUNCTION("""COMPUTED_VALUE"""),46136.57098379629) -> 46136.571 | N54: =IFERROR(__xludf.DUMMYFUNCTION("""COMPUTED_VALUE"""),165.0) -> 165 | P54: =IFERROR(__xludf.DUMMYFUNCTION("""COMPUTED_VALUE"""),"Kit Delivery") -> Kit Delivery | S54: =IFERROR(__xludf.DUMMYFUNCTION("""COMPUTED_VALUE"""),"Dispatch_Images/KIT--17606.Photos.184209.jpg") -> Dispatch_Images/KIT--17606.Photos.184209.jpg | T54: =IFERROR(__xludf.DUMMYFUNCTION("""COMPUTED_VALUE"""),46136.57157407407) -> 46136.572
A55: =IFERROR(__xludf.DUMMYFUNCTION("""COMPUTED_VALUE"""),"KIT-#17820") -> KIT-#17820 | B55: =IFERROR(__xludf.DUMMYFUNCTION("""COMPUTED_VALUE"""),46141.0) -> 46141 | C55: =IFERROR(__xludf.DUMMYFUNCTION("""COMPUTED_VALUE"""),"Kit Delivery") -> Kit Delivery | D55: =IFERROR(__xludf.DUMMYFUNCTION("""COMPUTED_VALUE"""),3.0) -> 3 | E55: =IFERROR(__xludf.DUMMYFUNCTION("""COMPUTED_VALUE"""),"Koenig") -> Koenig | F55: =IFERROR(__xludf.DUMMYFUNCTION("""COMPUTED_VALUE"""),1112.0) -> 1112 | G55: =IFERROR(__xludf.DUMMYFUNCTION("""COMPUTED_VALUE"""),"Ethan Talapatra") -> Ethan Talapatra | H55: =IFERROR(__xludf.DUMMYFUNCTION("""COMPUTED_VALUE"""),2.022954621E9) -> 2022954621 | I55: =IFERROR(__xludf.DUMMYFUNCTION("""COMPUTED_VALUE"""),"3PM-5PM") -> 3PM-5PM | J55: =IFERROR(__xludf.DUMMYFUNCTION("""COMPUTED_VALUE"""),1.0) -> 1 | K55: =IFERROR(__xludf.DUMMYFUNCTION("""COMPUTED_VALUE"""),"Complete") -> Complete | M55: =IFERROR(__xludf.DUMMYFUNCTION("""COMPUTED_VALUE"""),46139.706562499996) -> 46139.707 | N55: =IFERROR(__xludf.DUMMYFUNCTION("""COMPUTED_VALUE"""),31.0) -> 31 | P55: =IFERROR(__xludf.DUMMYFUNCTION("""COMPUTED_VALUE"""),"Kit Delivery") -> Kit Delivery | S55: =IFERROR(__xludf.DUMMYFUNCTION("""COMPUTED_VALUE"""),"Dispatch_Images/KIT--17820.Photos.215723.jpg") -> Dispatch_Images/KIT--17820.Photos.215723.jpg | T55: =IFERROR(__xludf.DUMMYFUNCTION("""COMPUTED_VALUE"""),46139.71046296296) -> 46139.71
A56: =IFERROR(__xludf.DUMMYFUNCTION("""COMPUTED_VALUE"""),"KIT-#17097") -> KIT-#17097 | B56: =IFERROR(__xludf.DUMMYFUNCTION("""COMPUTED_VALUE"""),46142.0) -> 46142 | C56: =IFERROR(__xludf.DUMMYFUNCTION("""COMPUTED_VALUE"""),"Kit Delivery") -> Kit Delivery | D56: =IFERROR(__xludf.DUMMYFUNCTION("""COMPUTED_VALUE"""),1.0) -> 1 | E56: =IFERROR(__xludf.DUMMYFUNCTION("""COMPUTED_VALUE"""),"Park") -> Park | F56: =IFERROR(__xludf.DUMMYFUNCTION("""COMPUTED_VALUE"""),370.0) -> 370 | G56: =IFERROR(__xludf.DUMMYFUNCTION("""COMPUTED_VALUE"""),"Sydney Caplan") -> Sydney Caplan | H56: =IFERROR(__xludf.DUMMYFUNCTION("""COMPUTED_VALUE"""),9.84960909E9) -> 9849609090 | I56: =IFERROR(__xludf.DUMMYFUNCTION("""COMPUTED_VALUE"""),"11AM-1PM") -> 11AM-1PM | J56: =IFERROR(__xludf.DUMMYFUNCTION("""COMPUTED_VALUE"""),1.0) -> 1 | K56: =IFERROR(__xludf.DUMMYFUNCTION("""COMPUTED_VALUE"""),"Complete") -> Complete | M56: =IFERROR(__xludf.DUMMYFUNCTION("""COMPUTED_VALUE"""),46123.610543981486) -> 46123.611 | N56: =IFERROR(__xludf.DUMMYFUNCTION("""COMPUTED_VALUE"""),48.0) -> 48 | P56: =IFERROR(__xludf.DUMMYFUNCTION("""COMPUTED_VALUE"""),"Kit Delivery") -> Kit Delivery | S56: =IFERROR(__xludf.DUMMYFUNCTION("""COMPUTED_VALUE"""),46123.61150462963) -> 46123.611
